# Comparing `tmp/cpptools-1.0.0.win-amd64.zip` & `tmp/cpptools-1.0.1.win-amd64.zip`

## zipinfo {}

```diff
@@ -1,22 +1,22 @@
-Zip file size: 265042 bytes, number of entries: 151
-drwxrwxrwx  2.0 fat        0 b- stor 23-Apr-28 14:50 Program Files/
-drwxrwxrwx  2.0 fat        0 b- stor 23-Apr-28 14:50 Program Files/WindowsApps/
-drwxrwxrwx  2.0 fat        0 b- stor 23-Apr-28 14:50 Program Files/WindowsApps/PythonSoftwareFoundation.Python.3.11_3.11.1008.0_x64__qbz5n2kfra8p0/
-drwxrwxrwx  2.0 fat        0 b- stor 23-Apr-28 14:50 Program Files/WindowsApps/PythonSoftwareFoundation.Python.3.11_3.11.1008.0_x64__qbz5n2kfra8p0/Lib/
-drwxrwxrwx  2.0 fat        0 b- stor 23-Apr-28 14:50 Program Files/WindowsApps/PythonSoftwareFoundation.Python.3.11_3.11.1008.0_x64__qbz5n2kfra8p0/Scripts/
-drwxrwxrwx  2.0 fat        0 b- stor 23-Apr-28 14:50 Program Files/WindowsApps/PythonSoftwareFoundation.Python.3.11_3.11.1008.0_x64__qbz5n2kfra8p0/Lib/site-packages/
-drwxrwxrwx  2.0 fat        0 b- stor 23-Apr-28 14:50 Program Files/WindowsApps/PythonSoftwareFoundation.Python.3.11_3.11.1008.0_x64__qbz5n2kfra8p0/Lib/site-packages/conanbuild/
-drwxrwxrwx  2.0 fat        0 b- stor 23-Apr-28 14:50 Program Files/WindowsApps/PythonSoftwareFoundation.Python.3.11_3.11.1008.0_x64__qbz5n2kfra8p0/Lib/site-packages/cpptools-1.0.0-py3.11.egg-info/
-drwxrwxrwx  2.0 fat        0 b- stor 23-Apr-28 14:50 Program Files/WindowsApps/PythonSoftwareFoundation.Python.3.11_3.11.1008.0_x64__qbz5n2kfra8p0/Lib/site-packages/oasc/
-drwxrwxrwx  2.0 fat        0 b- stor 23-Apr-28 14:50 Program Files/WindowsApps/PythonSoftwareFoundation.Python.3.11_3.11.1008.0_x64__qbz5n2kfra8p0/Lib/site-packages/startcpp/
-drwxrwxrwx  2.0 fat        0 b- stor 23-Apr-28 14:50 Program Files/WindowsApps/PythonSoftwareFoundation.Python.3.11_3.11.1008.0_x64__qbz5n2kfra8p0/Lib/site-packages/conanbuild/targets/
-drwxrwxrwx  2.0 fat        0 b- stor 23-Apr-28 14:50 Program Files/WindowsApps/PythonSoftwareFoundation.Python.3.11_3.11.1008.0_x64__qbz5n2kfra8p0/Lib/site-packages/conanbuild/__pycache__/
--rw-rw-rw-  2.0 fat    12820 b- defN 23-Apr-20 14:34 Program Files/WindowsApps/PythonSoftwareFoundation.Python.3.11_3.11.1008.0_x64__qbz5n2kfra8p0/Lib/site-packages/conanbuild/builder.py
--rw-rw-rw-  2.0 fat    13292 b- defN 23-Apr-28 09:31 Program Files/WindowsApps/PythonSoftwareFoundation.Python.3.11_3.11.1008.0_x64__qbz5n2kfra8p0/Lib/site-packages/conanbuild/conanfile.py
+Zip file size: 266656 bytes, number of entries: 151
+drwxrwxrwx  2.0 fat        0 b- stor 23-Jun-01 18:56 Program Files/
+drwxrwxrwx  2.0 fat        0 b- stor 23-Jun-01 18:56 Program Files/WindowsApps/
+drwxrwxrwx  2.0 fat        0 b- stor 23-Jun-01 18:56 Program Files/WindowsApps/PythonSoftwareFoundation.Python.3.11_3.11.1008.0_x64__qbz5n2kfra8p0/
+drwxrwxrwx  2.0 fat        0 b- stor 23-Jun-01 18:56 Program Files/WindowsApps/PythonSoftwareFoundation.Python.3.11_3.11.1008.0_x64__qbz5n2kfra8p0/Lib/
+drwxrwxrwx  2.0 fat        0 b- stor 23-Jun-01 18:56 Program Files/WindowsApps/PythonSoftwareFoundation.Python.3.11_3.11.1008.0_x64__qbz5n2kfra8p0/Scripts/
+drwxrwxrwx  2.0 fat        0 b- stor 23-Jun-01 18:56 Program Files/WindowsApps/PythonSoftwareFoundation.Python.3.11_3.11.1008.0_x64__qbz5n2kfra8p0/Lib/site-packages/
+drwxrwxrwx  2.0 fat        0 b- stor 23-Jun-01 18:56 Program Files/WindowsApps/PythonSoftwareFoundation.Python.3.11_3.11.1008.0_x64__qbz5n2kfra8p0/Lib/site-packages/conanbuild/
+drwxrwxrwx  2.0 fat        0 b- stor 23-Jun-01 18:56 Program Files/WindowsApps/PythonSoftwareFoundation.Python.3.11_3.11.1008.0_x64__qbz5n2kfra8p0/Lib/site-packages/cpptools-1.0.1-py3.11.egg-info/
+drwxrwxrwx  2.0 fat        0 b- stor 23-Jun-01 18:56 Program Files/WindowsApps/PythonSoftwareFoundation.Python.3.11_3.11.1008.0_x64__qbz5n2kfra8p0/Lib/site-packages/oasc/
+drwxrwxrwx  2.0 fat        0 b- stor 23-Jun-01 18:56 Program Files/WindowsApps/PythonSoftwareFoundation.Python.3.11_3.11.1008.0_x64__qbz5n2kfra8p0/Lib/site-packages/startcpp/
+drwxrwxrwx  2.0 fat        0 b- stor 23-Jun-01 18:56 Program Files/WindowsApps/PythonSoftwareFoundation.Python.3.11_3.11.1008.0_x64__qbz5n2kfra8p0/Lib/site-packages/conanbuild/targets/
+drwxrwxrwx  2.0 fat        0 b- stor 23-Jun-01 18:56 Program Files/WindowsApps/PythonSoftwareFoundation.Python.3.11_3.11.1008.0_x64__qbz5n2kfra8p0/Lib/site-packages/conanbuild/__pycache__/
+-rw-rw-rw-  2.0 fat    13304 b- defN 23-Jun-01 17:32 Program Files/WindowsApps/PythonSoftwareFoundation.Python.3.11_3.11.1008.0_x64__qbz5n2kfra8p0/Lib/site-packages/conanbuild/builder.py
+-rw-rw-rw-  2.0 fat    13292 b- defN 23-Jun-01 17:33 Program Files/WindowsApps/PythonSoftwareFoundation.Python.3.11_3.11.1008.0_x64__qbz5n2kfra8p0/Lib/site-packages/conanbuild/conanfile.py
 -rw-rw-rw-  2.0 fat     2762 b- defN 23-Mar-30 11:42 Program Files/WindowsApps/PythonSoftwareFoundation.Python.3.11_3.11.1008.0_x64__qbz5n2kfra8p0/Lib/site-packages/conanbuild/README.md
 -rw-rw-rw-  2.0 fat        0 b- defN 23-Feb-15 14:42 Program Files/WindowsApps/PythonSoftwareFoundation.Python.3.11_3.11.1008.0_x64__qbz5n2kfra8p0/Lib/site-packages/conanbuild/__init__.py
 -rw-rw-rw-  2.0 fat     4388 b- defN 23-Feb-16 09:35 Program Files/WindowsApps/PythonSoftwareFoundation.Python.3.11_3.11.1008.0_x64__qbz5n2kfra8p0/Lib/site-packages/conanbuild/targets/abseil.py.in
 -rw-rw-rw-  2.0 fat     7008 b- defN 23-Apr-06 09:45 Program Files/WindowsApps/PythonSoftwareFoundation.Python.3.11_3.11.1008.0_x64__qbz5n2kfra8p0/Lib/site-packages/conanbuild/targets/cairo.py.in
 -rw-rw-rw-  2.0 fat     1627 b- defN 23-Apr-06 09:45 Program Files/WindowsApps/PythonSoftwareFoundation.Python.3.11_3.11.1008.0_x64__qbz5n2kfra8p0/Lib/site-packages/conanbuild/targets/CameraCtrl.py.in
 -rw-rw-rw-  2.0 fat      720 b- defN 23-Apr-06 09:45 Program Files/WindowsApps/PythonSoftwareFoundation.Python.3.11_3.11.1008.0_x64__qbz5n2kfra8p0/Lib/site-packages/conanbuild/targets/disruptor.py.in
 -rw-rw-rw-  2.0 fat     1749 b- defN 23-Apr-06 09:45 Program Files/WindowsApps/PythonSoftwareFoundation.Python.3.11_3.11.1008.0_x64__qbz5n2kfra8p0/Lib/site-packages/conanbuild/targets/expat.py.in
@@ -77,77 +77,77 @@
 -rw-rw-rw-  2.0 fat        0 b- defN 23-Feb-07 16:18 Program Files/WindowsApps/PythonSoftwareFoundation.Python.3.11_3.11.1008.0_x64__qbz5n2kfra8p0/Lib/site-packages/conanbuild/targets/protobuf.py.in
 -rw-rw-rw-  2.0 fat        0 b- defN 23-Feb-07 16:18 Program Files/WindowsApps/PythonSoftwareFoundation.Python.3.11_3.11.1008.0_x64__qbz5n2kfra8p0/Lib/site-packages/conanbuild/targets/Protoc.py.in
 -rw-rw-rw-  2.0 fat        0 b- defN 23-Feb-07 16:18 Program Files/WindowsApps/PythonSoftwareFoundation.Python.3.11_3.11.1008.0_x64__qbz5n2kfra8p0/Lib/site-packages/conanbuild/targets/protoc_installer.py.in
 -rw-rw-rw-  2.0 fat        0 b- defN 23-Feb-07 16:18 Program Files/WindowsApps/PythonSoftwareFoundation.Python.3.11_3.11.1008.0_x64__qbz5n2kfra8p0/Lib/site-packages/conanbuild/targets/pthread-win.py.in
 -rw-rw-rw-  2.0 fat        0 b- defN 23-Feb-07 16:18 Program Files/WindowsApps/PythonSoftwareFoundation.Python.3.11_3.11.1008.0_x64__qbz5n2kfra8p0/Lib/site-packages/conanbuild/targets/pthread.py.in
 -rw-rw-rw-  2.0 fat        0 b- defN 23-Feb-07 16:18 Program Files/WindowsApps/PythonSoftwareFoundation.Python.3.11_3.11.1008.0_x64__qbz5n2kfra8p0/Lib/site-packages/conanbuild/targets/ptlib.py.in
 -rw-rw-rw-  2.0 fat        0 b- defN 23-Feb-07 16:18 Program Files/WindowsApps/PythonSoftwareFoundation.Python.3.11_3.11.1008.0_x64__qbz5n2kfra8p0/Lib/site-packages/conanbuild/targets/readline.py.in
--rw-rw-rw-  2.0 fat     3433 b- defN 23-Apr-10 16:45 Program Files/WindowsApps/PythonSoftwareFoundation.Python.3.11_3.11.1008.0_x64__qbz5n2kfra8p0/Lib/site-packages/conanbuild/targets/repos.yaml
+-rw-rw-rw-  2.0 fat     3437 b- defN 23-Jun-01 16:45 Program Files/WindowsApps/PythonSoftwareFoundation.Python.3.11_3.11.1008.0_x64__qbz5n2kfra8p0/Lib/site-packages/conanbuild/targets/repos.yaml
 -rw-rw-rw-  2.0 fat        0 b- defN 23-Feb-07 16:18 Program Files/WindowsApps/PythonSoftwareFoundation.Python.3.11_3.11.1008.0_x64__qbz5n2kfra8p0/Lib/site-packages/conanbuild/targets/resiprocate.py.in
 -rw-rw-rw-  2.0 fat        0 b- defN 23-Feb-07 16:18 Program Files/WindowsApps/PythonSoftwareFoundation.Python.3.11_3.11.1008.0_x64__qbz5n2kfra8p0/Lib/site-packages/conanbuild/targets/signalwire-client-c.py.in
 -rw-rw-rw-  2.0 fat        0 b- defN 23-Feb-07 16:18 Program Files/WindowsApps/PythonSoftwareFoundation.Python.3.11_3.11.1008.0_x64__qbz5n2kfra8p0/Lib/site-packages/conanbuild/targets/SipEngine.py.in
 -rw-rw-rw-  2.0 fat        0 b- defN 23-Feb-07 16:18 Program Files/WindowsApps/PythonSoftwareFoundation.Python.3.11_3.11.1008.0_x64__qbz5n2kfra8p0/Lib/site-packages/conanbuild/targets/spandsp.py.in
 -rw-rw-rw-  2.0 fat        0 b- defN 23-Feb-07 16:18 Program Files/WindowsApps/PythonSoftwareFoundation.Python.3.11_3.11.1008.0_x64__qbz5n2kfra8p0/Lib/site-packages/conanbuild/targets/speex.py.in
 -rw-rw-rw-  2.0 fat        0 b- defN 23-Feb-07 16:18 Program Files/WindowsApps/PythonSoftwareFoundation.Python.3.11_3.11.1008.0_x64__qbz5n2kfra8p0/Lib/site-packages/conanbuild/targets/sqlite3.py.in
--rw-rw-rw-  2.0 fat        0 b- defN 23-Feb-07 16:18 Program Files/WindowsApps/PythonSoftwareFoundation.Python.3.11_3.11.1008.0_x64__qbz5n2kfra8p0/Lib/site-packages/conanbuild/targets/StackEngine.py.in
+-rw-rw-rw-  2.0 fat     4947 b- defN 23-Jun-01 16:45 Program Files/WindowsApps/PythonSoftwareFoundation.Python.3.11_3.11.1008.0_x64__qbz5n2kfra8p0/Lib/site-packages/conanbuild/targets/StackEngine.py.in
 -rw-rw-rw-  2.0 fat     4119 b- defN 23-Apr-06 09:45 Program Files/WindowsApps/PythonSoftwareFoundation.Python.3.11_3.11.1008.0_x64__qbz5n2kfra8p0/Lib/site-packages/conanbuild/targets/stunlib.py.in
 -rw-rw-rw-  2.0 fat        0 b- defN 23-Feb-07 16:18 Program Files/WindowsApps/PythonSoftwareFoundation.Python.3.11_3.11.1008.0_x64__qbz5n2kfra8p0/Lib/site-packages/conanbuild/targets/tcmalloc.py.in
 -rw-rw-rw-  2.0 fat        0 b- defN 23-Feb-07 16:18 Program Files/WindowsApps/PythonSoftwareFoundation.Python.3.11_3.11.1008.0_x64__qbz5n2kfra8p0/Lib/site-packages/conanbuild/targets/termcap.py.in
 -rw-rw-rw-  2.0 fat     4542 b- defN 23-Mar-20 17:38 Program Files/WindowsApps/PythonSoftwareFoundation.Python.3.11_3.11.1008.0_x64__qbz5n2kfra8p0/Lib/site-packages/conanbuild/targets/usrsctp.py.in
 -rw-rw-rw-  2.0 fat        0 b- defN 23-Feb-07 16:18 Program Files/WindowsApps/PythonSoftwareFoundation.Python.3.11_3.11.1008.0_x64__qbz5n2kfra8p0/Lib/site-packages/conanbuild/targets/VirtualDevice.py.in
 -rw-rw-rw-  2.0 fat        0 b- defN 23-Feb-07 16:18 Program Files/WindowsApps/PythonSoftwareFoundation.Python.3.11_3.11.1008.0_x64__qbz5n2kfra8p0/Lib/site-packages/conanbuild/targets/vpx.py.in
 -rw-rw-rw-  2.0 fat        0 b- defN 23-Feb-07 16:18 Program Files/WindowsApps/PythonSoftwareFoundation.Python.3.11_3.11.1008.0_x64__qbz5n2kfra8p0/Lib/site-packages/conanbuild/targets/winsdk_samples.py.in
 -rw-rw-rw-  2.0 fat     2721 b- defN 23-Feb-22 18:06 Program Files/WindowsApps/PythonSoftwareFoundation.Python.3.11_3.11.1008.0_x64__qbz5n2kfra8p0/Lib/site-packages/conanbuild/targets/wxsvg.py.in
 -rw-rw-rw-  2.0 fat     8452 b- defN 23-Mar-07 16:57 Program Files/WindowsApps/PythonSoftwareFoundation.Python.3.11_3.11.1008.0_x64__qbz5n2kfra8p0/Lib/site-packages/conanbuild/targets/wxWidgets.py.in
 -rw-rw-rw-  2.0 fat        0 b- defN 23-Feb-07 16:18 Program Files/WindowsApps/PythonSoftwareFoundation.Python.3.11_3.11.1008.0_x64__qbz5n2kfra8p0/Lib/site-packages/conanbuild/targets/xpack.py.in
 -rw-rw-rw-  2.0 fat        0 b- defN 23-Feb-07 16:18 Program Files/WindowsApps/PythonSoftwareFoundation.Python.3.11_3.11.1008.0_x64__qbz5n2kfra8p0/Lib/site-packages/conanbuild/targets/zlib.py.in
--rw-rw-rw-  2.0 fat    19300 b- defN 23-Apr-28 14:50 Program Files/WindowsApps/PythonSoftwareFoundation.Python.3.11_3.11.1008.0_x64__qbz5n2kfra8p0/Lib/site-packages/conanbuild/__pycache__/builder.cpython-311.pyc
--rw-rw-rw-  2.0 fat    15621 b- defN 23-Apr-28 14:50 Program Files/WindowsApps/PythonSoftwareFoundation.Python.3.11_3.11.1008.0_x64__qbz5n2kfra8p0/Lib/site-packages/conanbuild/__pycache__/conanfile.cpython-311.pyc
--rw-rw-rw-  2.0 fat      244 b- defN 23-Apr-28 14:50 Program Files/WindowsApps/PythonSoftwareFoundation.Python.3.11_3.11.1008.0_x64__qbz5n2kfra8p0/Lib/site-packages/conanbuild/__pycache__/__init__.cpython-311.pyc
--rw-rw-rw-  2.0 fat        1 b- defN 23-Apr-28 14:50 Program Files/WindowsApps/PythonSoftwareFoundation.Python.3.11_3.11.1008.0_x64__qbz5n2kfra8p0/Lib/site-packages/cpptools-1.0.0-py3.11.egg-info/dependency_links.txt
--rw-rw-rw-  2.0 fat      112 b- defN 23-Apr-28 14:50 Program Files/WindowsApps/PythonSoftwareFoundation.Python.3.11_3.11.1008.0_x64__qbz5n2kfra8p0/Lib/site-packages/cpptools-1.0.0-py3.11.egg-info/entry_points.txt
--rw-rw-rw-  2.0 fat     1070 b- defN 23-Apr-28 14:50 Program Files/WindowsApps/PythonSoftwareFoundation.Python.3.11_3.11.1008.0_x64__qbz5n2kfra8p0/Lib/site-packages/cpptools-1.0.0-py3.11.egg-info/PKG-INFO
--rw-rw-rw-  2.0 fat     3719 b- defN 23-Apr-28 14:50 Program Files/WindowsApps/PythonSoftwareFoundation.Python.3.11_3.11.1008.0_x64__qbz5n2kfra8p0/Lib/site-packages/cpptools-1.0.0-py3.11.egg-info/SOURCES.txt
--rw-rw-rw-  2.0 fat       25 b- defN 23-Apr-28 14:50 Program Files/WindowsApps/PythonSoftwareFoundation.Python.3.11_3.11.1008.0_x64__qbz5n2kfra8p0/Lib/site-packages/cpptools-1.0.0-py3.11.egg-info/top_level.txt
-drwxrwxrwx  2.0 fat        0 b- stor 23-Apr-28 14:50 Program Files/WindowsApps/PythonSoftwareFoundation.Python.3.11_3.11.1008.0_x64__qbz5n2kfra8p0/Lib/site-packages/oasc/core/
-drwxrwxrwx  2.0 fat        0 b- stor 23-Apr-28 14:50 Program Files/WindowsApps/PythonSoftwareFoundation.Python.3.11_3.11.1008.0_x64__qbz5n2kfra8p0/Lib/site-packages/oasc/tmpl/
-drwxrwxrwx  2.0 fat        0 b- stor 23-Apr-28 14:50 Program Files/WindowsApps/PythonSoftwareFoundation.Python.3.11_3.11.1008.0_x64__qbz5n2kfra8p0/Lib/site-packages/oasc/__pycache__/
--rw-rw-rw-  2.0 fat    47070 b- defN 23-Apr-28 10:23 Program Files/WindowsApps/PythonSoftwareFoundation.Python.3.11_3.11.1008.0_x64__qbz5n2kfra8p0/Lib/site-packages/oasc/CppGenerator.py
--rw-rw-rw-  2.0 fat     4258 b- defN 23-Apr-28 14:15 Program Files/WindowsApps/PythonSoftwareFoundation.Python.3.11_3.11.1008.0_x64__qbz5n2kfra8p0/Lib/site-packages/oasc/OpenAPIXG.py
+-rw-rw-rw-  2.0 fat    19912 b- defN 23-Jun-01 18:56 Program Files/WindowsApps/PythonSoftwareFoundation.Python.3.11_3.11.1008.0_x64__qbz5n2kfra8p0/Lib/site-packages/conanbuild/__pycache__/builder.cpython-311.pyc
+-rw-rw-rw-  2.0 fat    15621 b- defN 23-Jun-01 18:56 Program Files/WindowsApps/PythonSoftwareFoundation.Python.3.11_3.11.1008.0_x64__qbz5n2kfra8p0/Lib/site-packages/conanbuild/__pycache__/conanfile.cpython-311.pyc
+-rw-rw-rw-  2.0 fat      244 b- defN 23-Jun-01 18:56 Program Files/WindowsApps/PythonSoftwareFoundation.Python.3.11_3.11.1008.0_x64__qbz5n2kfra8p0/Lib/site-packages/conanbuild/__pycache__/__init__.cpython-311.pyc
+-rw-rw-rw-  2.0 fat        1 b- defN 23-Jun-01 18:56 Program Files/WindowsApps/PythonSoftwareFoundation.Python.3.11_3.11.1008.0_x64__qbz5n2kfra8p0/Lib/site-packages/cpptools-1.0.1-py3.11.egg-info/dependency_links.txt
+-rw-rw-rw-  2.0 fat      112 b- defN 23-Jun-01 18:56 Program Files/WindowsApps/PythonSoftwareFoundation.Python.3.11_3.11.1008.0_x64__qbz5n2kfra8p0/Lib/site-packages/cpptools-1.0.1-py3.11.egg-info/entry_points.txt
+-rw-rw-rw-  2.0 fat     1070 b- defN 23-Jun-01 18:56 Program Files/WindowsApps/PythonSoftwareFoundation.Python.3.11_3.11.1008.0_x64__qbz5n2kfra8p0/Lib/site-packages/cpptools-1.0.1-py3.11.egg-info/PKG-INFO
+-rw-rw-rw-  2.0 fat     3719 b- defN 23-Jun-01 18:56 Program Files/WindowsApps/PythonSoftwareFoundation.Python.3.11_3.11.1008.0_x64__qbz5n2kfra8p0/Lib/site-packages/cpptools-1.0.1-py3.11.egg-info/SOURCES.txt
+-rw-rw-rw-  2.0 fat       25 b- defN 23-Jun-01 18:56 Program Files/WindowsApps/PythonSoftwareFoundation.Python.3.11_3.11.1008.0_x64__qbz5n2kfra8p0/Lib/site-packages/cpptools-1.0.1-py3.11.egg-info/top_level.txt
+drwxrwxrwx  2.0 fat        0 b- stor 23-Jun-01 18:56 Program Files/WindowsApps/PythonSoftwareFoundation.Python.3.11_3.11.1008.0_x64__qbz5n2kfra8p0/Lib/site-packages/oasc/core/
+drwxrwxrwx  2.0 fat        0 b- stor 23-Jun-01 18:56 Program Files/WindowsApps/PythonSoftwareFoundation.Python.3.11_3.11.1008.0_x64__qbz5n2kfra8p0/Lib/site-packages/oasc/tmpl/
+drwxrwxrwx  2.0 fat        0 b- stor 23-Jun-01 18:56 Program Files/WindowsApps/PythonSoftwareFoundation.Python.3.11_3.11.1008.0_x64__qbz5n2kfra8p0/Lib/site-packages/oasc/__pycache__/
+-rw-rw-rw-  2.0 fat    47070 b- defN 23-Jun-01 16:55 Program Files/WindowsApps/PythonSoftwareFoundation.Python.3.11_3.11.1008.0_x64__qbz5n2kfra8p0/Lib/site-packages/oasc/CppGenerator.py
+-rw-rw-rw-  2.0 fat     4258 b- defN 23-Jun-01 16:55 Program Files/WindowsApps/PythonSoftwareFoundation.Python.3.11_3.11.1008.0_x64__qbz5n2kfra8p0/Lib/site-packages/oasc/OpenAPIXG.py
 -rw-rw-rw-  2.0 fat      689 b- defN 23-Apr-28 14:16 Program Files/WindowsApps/PythonSoftwareFoundation.Python.3.11_3.11.1008.0_x64__qbz5n2kfra8p0/Lib/site-packages/oasc/README.md
 -rw-rw-rw-  2.0 fat        0 b- defN 23-Mar-29 14:51 Program Files/WindowsApps/PythonSoftwareFoundation.Python.3.11_3.11.1008.0_x64__qbz5n2kfra8p0/Lib/site-packages/oasc/__init__.py
-drwxrwxrwx  2.0 fat        0 b- stor 23-Apr-28 14:50 Program Files/WindowsApps/PythonSoftwareFoundation.Python.3.11_3.11.1008.0_x64__qbz5n2kfra8p0/Lib/site-packages/oasc/core/include/
-drwxrwxrwx  2.0 fat        0 b- stor 23-Apr-28 14:50 Program Files/WindowsApps/PythonSoftwareFoundation.Python.3.11_3.11.1008.0_x64__qbz5n2kfra8p0/Lib/site-packages/oasc/core/src/
+drwxrwxrwx  2.0 fat        0 b- stor 23-Jun-01 18:56 Program Files/WindowsApps/PythonSoftwareFoundation.Python.3.11_3.11.1008.0_x64__qbz5n2kfra8p0/Lib/site-packages/oasc/core/include/
+drwxrwxrwx  2.0 fat        0 b- stor 23-Jun-01 18:56 Program Files/WindowsApps/PythonSoftwareFoundation.Python.3.11_3.11.1008.0_x64__qbz5n2kfra8p0/Lib/site-packages/oasc/core/src/
 -rw-rw-rw-  2.0 fat      549 b- defN 23-Apr-28 10:41 Program Files/WindowsApps/PythonSoftwareFoundation.Python.3.11_3.11.1008.0_x64__qbz5n2kfra8p0/Lib/site-packages/oasc/core/CMakeLists.txt
-drwxrwxrwx  2.0 fat        0 b- stor 23-Apr-28 14:50 Program Files/WindowsApps/PythonSoftwareFoundation.Python.3.11_3.11.1008.0_x64__qbz5n2kfra8p0/Lib/site-packages/oasc/core/include/mlapi/
-drwxrwxrwx  2.0 fat        0 b- stor 23-Apr-28 14:50 Program Files/WindowsApps/PythonSoftwareFoundation.Python.3.11_3.11.1008.0_x64__qbz5n2kfra8p0/Lib/site-packages/oasc/core/include/mlapi/core/
+drwxrwxrwx  2.0 fat        0 b- stor 23-Jun-01 18:56 Program Files/WindowsApps/PythonSoftwareFoundation.Python.3.11_3.11.1008.0_x64__qbz5n2kfra8p0/Lib/site-packages/oasc/core/include/mlapi/
+drwxrwxrwx  2.0 fat        0 b- stor 23-Jun-01 18:56 Program Files/WindowsApps/PythonSoftwareFoundation.Python.3.11_3.11.1008.0_x64__qbz5n2kfra8p0/Lib/site-packages/oasc/core/include/mlapi/core/
 -rw-rw-rw-  2.0 fat     2313 b- defN 22-Dec-07 12:07 Program Files/WindowsApps/PythonSoftwareFoundation.Python.3.11_3.11.1008.0_x64__qbz5n2kfra8p0/Lib/site-packages/oasc/core/include/mlapi/core/ApiCore.h
 -rw-rw-rw-  2.0 fat      707 b- defN 22-Dec-07 11:57 Program Files/WindowsApps/PythonSoftwareFoundation.Python.3.11_3.11.1008.0_x64__qbz5n2kfra8p0/Lib/site-packages/oasc/core/include/mlapi/core/Config.h
 -rw-rw-rw-  2.0 fat     5096 b- defN 23-Apr-25 14:44 Program Files/WindowsApps/PythonSoftwareFoundation.Python.3.11_3.11.1008.0_x64__qbz5n2kfra8p0/Lib/site-packages/oasc/core/src/ApiCore.cxx
 -rw-rw-rw-  2.0 fat      877 b- defN 22-Dec-07 12:08 Program Files/WindowsApps/PythonSoftwareFoundation.Python.3.11_3.11.1008.0_x64__qbz5n2kfra8p0/Lib/site-packages/oasc/core/src/Config.cxx
-drwxrwxrwx  2.0 fat        0 b- stor 23-Apr-28 14:50 Program Files/WindowsApps/PythonSoftwareFoundation.Python.3.11_3.11.1008.0_x64__qbz5n2kfra8p0/Lib/site-packages/oasc/tmpl/cmake/
+drwxrwxrwx  2.0 fat        0 b- stor 23-Jun-01 18:56 Program Files/WindowsApps/PythonSoftwareFoundation.Python.3.11_3.11.1008.0_x64__qbz5n2kfra8p0/Lib/site-packages/oasc/tmpl/cmake/
 -rw-rw-rw-  2.0 fat     1396 b- defN 23-Apr-28 09:24 Program Files/WindowsApps/PythonSoftwareFoundation.Python.3.11_3.11.1008.0_x64__qbz5n2kfra8p0/Lib/site-packages/oasc/tmpl/CMakeLists.txt
 -rw-rw-rw-  2.0 fat      164 b- defN 22-Dec-28 09:42 Program Files/WindowsApps/PythonSoftwareFoundation.Python.3.11_3.11.1008.0_x64__qbz5n2kfra8p0/Lib/site-packages/oasc/tmpl/conanfile.txt
 -rw-rw-rw-  2.0 fat     4253 b- defN 23-Apr-28 10:23 Program Files/WindowsApps/PythonSoftwareFoundation.Python.3.11_3.11.1008.0_x64__qbz5n2kfra8p0/Lib/site-packages/oasc/tmpl/test.cxx
 -rw-rw-rw-  2.0 fat     1134 b- defN 23-Mar-29 17:25 Program Files/WindowsApps/PythonSoftwareFoundation.Python.3.11_3.11.1008.0_x64__qbz5n2kfra8p0/Lib/site-packages/oasc/tmpl/cmake/config.cmake
 -rw-rw-rw-  2.0 fat     2345 b- defN 23-Apr-06 09:45 Program Files/WindowsApps/PythonSoftwareFoundation.Python.3.11_3.11.1008.0_x64__qbz5n2kfra8p0/Lib/site-packages/oasc/tmpl/cmake/install_conan_deps.cmake
--rw-rw-rw-  2.0 fat    70807 b- defN 23-Apr-28 14:50 Program Files/WindowsApps/PythonSoftwareFoundation.Python.3.11_3.11.1008.0_x64__qbz5n2kfra8p0/Lib/site-packages/oasc/__pycache__/CppGenerator.cpython-311.pyc
--rw-rw-rw-  2.0 fat     8531 b- defN 23-Apr-28 14:50 Program Files/WindowsApps/PythonSoftwareFoundation.Python.3.11_3.11.1008.0_x64__qbz5n2kfra8p0/Lib/site-packages/oasc/__pycache__/OpenAPIXG.cpython-311.pyc
--rw-rw-rw-  2.0 fat      238 b- defN 23-Apr-28 14:50 Program Files/WindowsApps/PythonSoftwareFoundation.Python.3.11_3.11.1008.0_x64__qbz5n2kfra8p0/Lib/site-packages/oasc/__pycache__/__init__.cpython-311.pyc
-drwxrwxrwx  2.0 fat        0 b- stor 23-Apr-28 14:50 Program Files/WindowsApps/PythonSoftwareFoundation.Python.3.11_3.11.1008.0_x64__qbz5n2kfra8p0/Lib/site-packages/startcpp/cmake/
-drwxrwxrwx  2.0 fat        0 b- stor 23-Apr-28 14:50 Program Files/WindowsApps/PythonSoftwareFoundation.Python.3.11_3.11.1008.0_x64__qbz5n2kfra8p0/Lib/site-packages/startcpp/__pycache__/
+-rw-rw-rw-  2.0 fat    70807 b- defN 23-Jun-01 18:56 Program Files/WindowsApps/PythonSoftwareFoundation.Python.3.11_3.11.1008.0_x64__qbz5n2kfra8p0/Lib/site-packages/oasc/__pycache__/CppGenerator.cpython-311.pyc
+-rw-rw-rw-  2.0 fat     8531 b- defN 23-Jun-01 18:56 Program Files/WindowsApps/PythonSoftwareFoundation.Python.3.11_3.11.1008.0_x64__qbz5n2kfra8p0/Lib/site-packages/oasc/__pycache__/OpenAPIXG.cpython-311.pyc
+-rw-rw-rw-  2.0 fat      238 b- defN 23-Jun-01 18:56 Program Files/WindowsApps/PythonSoftwareFoundation.Python.3.11_3.11.1008.0_x64__qbz5n2kfra8p0/Lib/site-packages/oasc/__pycache__/__init__.cpython-311.pyc
+drwxrwxrwx  2.0 fat        0 b- stor 23-Jun-01 18:56 Program Files/WindowsApps/PythonSoftwareFoundation.Python.3.11_3.11.1008.0_x64__qbz5n2kfra8p0/Lib/site-packages/startcpp/cmake/
+drwxrwxrwx  2.0 fat        0 b- stor 23-Jun-01 18:56 Program Files/WindowsApps/PythonSoftwareFoundation.Python.3.11_3.11.1008.0_x64__qbz5n2kfra8p0/Lib/site-packages/startcpp/__pycache__/
 -rw-rw-rw-  2.0 fat       75 b- defN 23-Mar-28 17:20 Program Files/WindowsApps/PythonSoftwareFoundation.Python.3.11_3.11.1008.0_x64__qbz5n2kfra8p0/Lib/site-packages/startcpp/conanfile.txt.in
--rw-rw-rw-  2.0 fat     4364 b- defN 23-Mar-30 11:08 Program Files/WindowsApps/PythonSoftwareFoundation.Python.3.11_3.11.1008.0_x64__qbz5n2kfra8p0/Lib/site-packages/startcpp/entry.py
+-rw-rw-rw-  2.0 fat     4364 b- defN 23-Jun-01 16:55 Program Files/WindowsApps/PythonSoftwareFoundation.Python.3.11_3.11.1008.0_x64__qbz5n2kfra8p0/Lib/site-packages/startcpp/entry.py
 -rw-rw-rw-  2.0 fat        0 b- defN 23-Mar-30 11:50 Program Files/WindowsApps/PythonSoftwareFoundation.Python.3.11_3.11.1008.0_x64__qbz5n2kfra8p0/Lib/site-packages/startcpp/README.md
 -rw-rw-rw-  2.0 fat        0 b- defN 23-Mar-29 14:51 Program Files/WindowsApps/PythonSoftwareFoundation.Python.3.11_3.11.1008.0_x64__qbz5n2kfra8p0/Lib/site-packages/startcpp/__init__.py
 -rw-rw-rw-  2.0 fat     1134 b- defN 23-Mar-29 17:25 Program Files/WindowsApps/PythonSoftwareFoundation.Python.3.11_3.11.1008.0_x64__qbz5n2kfra8p0/Lib/site-packages/startcpp/cmake/config.cmake
 -rw-rw-rw-  2.0 fat     2345 b- defN 23-Apr-06 09:45 Program Files/WindowsApps/PythonSoftwareFoundation.Python.3.11_3.11.1008.0_x64__qbz5n2kfra8p0/Lib/site-packages/startcpp/cmake/install_conan_deps.cmake
 -rw-rw-rw-  2.0 fat        0 b- defN 23-Mar-28 17:22 Program Files/WindowsApps/PythonSoftwareFoundation.Python.3.11_3.11.1008.0_x64__qbz5n2kfra8p0/Lib/site-packages/startcpp/cmake/platform.cmake
--rw-rw-rw-  2.0 fat     8098 b- defN 23-Apr-28 14:50 Program Files/WindowsApps/PythonSoftwareFoundation.Python.3.11_3.11.1008.0_x64__qbz5n2kfra8p0/Lib/site-packages/startcpp/__pycache__/entry.cpython-311.pyc
--rw-rw-rw-  2.0 fat      242 b- defN 23-Apr-28 14:50 Program Files/WindowsApps/PythonSoftwareFoundation.Python.3.11_3.11.1008.0_x64__qbz5n2kfra8p0/Lib/site-packages/startcpp/__pycache__/__init__.cpython-311.pyc
--rw-rw-rw-  2.0 fat     1096 b- defN 23-Apr-28 14:50 Program Files/WindowsApps/PythonSoftwareFoundation.Python.3.11_3.11.1008.0_x64__qbz5n2kfra8p0/Scripts/conanbuild-script.py
--rwx---     2.0 fat    74752 b- defN 23-Apr-28 14:50 Program Files/WindowsApps/PythonSoftwareFoundation.Python.3.11_3.11.1008.0_x64__qbz5n2kfra8p0/Scripts/conanbuild.exe
--rw-rw-rw-  2.0 fat     1084 b- defN 23-Apr-28 14:50 Program Files/WindowsApps/PythonSoftwareFoundation.Python.3.11_3.11.1008.0_x64__qbz5n2kfra8p0/Scripts/oasc-script.py
--rwx---     2.0 fat    74752 b- defN 23-Apr-28 14:50 Program Files/WindowsApps/PythonSoftwareFoundation.Python.3.11_3.11.1008.0_x64__qbz5n2kfra8p0/Scripts/oasc.exe
--rw-rw-rw-  2.0 fat     1092 b- defN 23-Apr-28 14:50 Program Files/WindowsApps/PythonSoftwareFoundation.Python.3.11_3.11.1008.0_x64__qbz5n2kfra8p0/Scripts/startcpp-script.py
--rwx---     2.0 fat    74752 b- defN 23-Apr-28 14:50 Program Files/WindowsApps/PythonSoftwareFoundation.Python.3.11_3.11.1008.0_x64__qbz5n2kfra8p0/Scripts/startcpp.exe
-151 files, 534192 bytes uncompressed, 211610 bytes compressed:  60.4%
+-rw-rw-rw-  2.0 fat     8098 b- defN 23-Jun-01 18:56 Program Files/WindowsApps/PythonSoftwareFoundation.Python.3.11_3.11.1008.0_x64__qbz5n2kfra8p0/Lib/site-packages/startcpp/__pycache__/entry.cpython-311.pyc
+-rw-rw-rw-  2.0 fat      242 b- defN 23-Jun-01 18:56 Program Files/WindowsApps/PythonSoftwareFoundation.Python.3.11_3.11.1008.0_x64__qbz5n2kfra8p0/Lib/site-packages/startcpp/__pycache__/__init__.cpython-311.pyc
+-rw-rw-rw-  2.0 fat     1096 b- defN 23-Jun-01 18:56 Program Files/WindowsApps/PythonSoftwareFoundation.Python.3.11_3.11.1008.0_x64__qbz5n2kfra8p0/Scripts/conanbuild-script.py
+-rwx---     2.0 fat    74752 b- defN 23-Jun-01 18:56 Program Files/WindowsApps/PythonSoftwareFoundation.Python.3.11_3.11.1008.0_x64__qbz5n2kfra8p0/Scripts/conanbuild.exe
+-rw-rw-rw-  2.0 fat     1084 b- defN 23-Jun-01 18:56 Program Files/WindowsApps/PythonSoftwareFoundation.Python.3.11_3.11.1008.0_x64__qbz5n2kfra8p0/Scripts/oasc-script.py
+-rwx---     2.0 fat    74752 b- defN 23-Jun-01 18:56 Program Files/WindowsApps/PythonSoftwareFoundation.Python.3.11_3.11.1008.0_x64__qbz5n2kfra8p0/Scripts/oasc.exe
+-rw-rw-rw-  2.0 fat     1092 b- defN 23-Jun-01 18:56 Program Files/WindowsApps/PythonSoftwareFoundation.Python.3.11_3.11.1008.0_x64__qbz5n2kfra8p0/Scripts/startcpp-script.py
+-rwx---     2.0 fat    74752 b- defN 23-Jun-01 18:56 Program Files/WindowsApps/PythonSoftwareFoundation.Python.3.11_3.11.1008.0_x64__qbz5n2kfra8p0/Scripts/startcpp.exe
+151 files, 540239 bytes uncompressed, 213224 bytes compressed:  60.5%
```

## zipnote {}

```diff
@@ -15,15 +15,15 @@
 
 Filename: Program Files/WindowsApps/PythonSoftwareFoundation.Python.3.11_3.11.1008.0_x64__qbz5n2kfra8p0/Lib/site-packages/
 Comment: 
 
 Filename: Program Files/WindowsApps/PythonSoftwareFoundation.Python.3.11_3.11.1008.0_x64__qbz5n2kfra8p0/Lib/site-packages/conanbuild/
 Comment: 
 
-Filename: Program Files/WindowsApps/PythonSoftwareFoundation.Python.3.11_3.11.1008.0_x64__qbz5n2kfra8p0/Lib/site-packages/cpptools-1.0.0-py3.11.egg-info/
+Filename: Program Files/WindowsApps/PythonSoftwareFoundation.Python.3.11_3.11.1008.0_x64__qbz5n2kfra8p0/Lib/site-packages/cpptools-1.0.1-py3.11.egg-info/
 Comment: 
 
 Filename: Program Files/WindowsApps/PythonSoftwareFoundation.Python.3.11_3.11.1008.0_x64__qbz5n2kfra8p0/Lib/site-packages/oasc/
 Comment: 
 
 Filename: Program Files/WindowsApps/PythonSoftwareFoundation.Python.3.11_3.11.1008.0_x64__qbz5n2kfra8p0/Lib/site-packages/startcpp/
 Comment: 
@@ -306,27 +306,27 @@
 
 Filename: Program Files/WindowsApps/PythonSoftwareFoundation.Python.3.11_3.11.1008.0_x64__qbz5n2kfra8p0/Lib/site-packages/conanbuild/__pycache__/conanfile.cpython-311.pyc
 Comment: 
 
 Filename: Program Files/WindowsApps/PythonSoftwareFoundation.Python.3.11_3.11.1008.0_x64__qbz5n2kfra8p0/Lib/site-packages/conanbuild/__pycache__/__init__.cpython-311.pyc
 Comment: 
 
-Filename: Program Files/WindowsApps/PythonSoftwareFoundation.Python.3.11_3.11.1008.0_x64__qbz5n2kfra8p0/Lib/site-packages/cpptools-1.0.0-py3.11.egg-info/dependency_links.txt
+Filename: Program Files/WindowsApps/PythonSoftwareFoundation.Python.3.11_3.11.1008.0_x64__qbz5n2kfra8p0/Lib/site-packages/cpptools-1.0.1-py3.11.egg-info/dependency_links.txt
 Comment: 
 
-Filename: Program Files/WindowsApps/PythonSoftwareFoundation.Python.3.11_3.11.1008.0_x64__qbz5n2kfra8p0/Lib/site-packages/cpptools-1.0.0-py3.11.egg-info/entry_points.txt
+Filename: Program Files/WindowsApps/PythonSoftwareFoundation.Python.3.11_3.11.1008.0_x64__qbz5n2kfra8p0/Lib/site-packages/cpptools-1.0.1-py3.11.egg-info/entry_points.txt
 Comment: 
 
-Filename: Program Files/WindowsApps/PythonSoftwareFoundation.Python.3.11_3.11.1008.0_x64__qbz5n2kfra8p0/Lib/site-packages/cpptools-1.0.0-py3.11.egg-info/PKG-INFO
+Filename: Program Files/WindowsApps/PythonSoftwareFoundation.Python.3.11_3.11.1008.0_x64__qbz5n2kfra8p0/Lib/site-packages/cpptools-1.0.1-py3.11.egg-info/PKG-INFO
 Comment: 
 
-Filename: Program Files/WindowsApps/PythonSoftwareFoundation.Python.3.11_3.11.1008.0_x64__qbz5n2kfra8p0/Lib/site-packages/cpptools-1.0.0-py3.11.egg-info/SOURCES.txt
+Filename: Program Files/WindowsApps/PythonSoftwareFoundation.Python.3.11_3.11.1008.0_x64__qbz5n2kfra8p0/Lib/site-packages/cpptools-1.0.1-py3.11.egg-info/SOURCES.txt
 Comment: 
 
-Filename: Program Files/WindowsApps/PythonSoftwareFoundation.Python.3.11_3.11.1008.0_x64__qbz5n2kfra8p0/Lib/site-packages/cpptools-1.0.0-py3.11.egg-info/top_level.txt
+Filename: Program Files/WindowsApps/PythonSoftwareFoundation.Python.3.11_3.11.1008.0_x64__qbz5n2kfra8p0/Lib/site-packages/cpptools-1.0.1-py3.11.egg-info/top_level.txt
 Comment: 
 
 Filename: Program Files/WindowsApps/PythonSoftwareFoundation.Python.3.11_3.11.1008.0_x64__qbz5n2kfra8p0/Lib/site-packages/oasc/core/
 Comment: 
 
 Filename: Program Files/WindowsApps/PythonSoftwareFoundation.Python.3.11_3.11.1008.0_x64__qbz5n2kfra8p0/Lib/site-packages/oasc/tmpl/
 Comment:
```

## Program Files/WindowsApps/PythonSoftwareFoundation.Python.3.11_3.11.1008.0_x64__qbz5n2kfra8p0/Lib/site-packages/conanbuild/builder.py

```diff
@@ -101,22 +101,26 @@
         l = l.replace('\t', '')
         if l.startswith('version='):
             return l.removeprefix('version=')
 
     return None
 
 def run():
+    if not os.path.exists(f'{os.path.expanduser("~")}/.cpptools/conan_targets'):
+        shutil.copytree(f'{os.path.dirname(__file__)}/targets', f'{os.path.expanduser("~")}/.cpptools/conan_targets')
+    
     parser = argparse.ArgumentParser(
         description='Generate project files of MaxME based platform etc.')
 
     parser.add_argument("target", help="the target project name.special an predefined project name or an 'conanfile.py.in'")
     parser.add_argument("-t", "--tag", help="the git tag of target, if specified,  use 'stable' conan channel and use 'tag' as version")
     parser.add_argument("-b","--branch", help="the git branch of target, if specified, use 'branch' as conan channel")
     parser.add_argument("-r", "--ref", help="the git ref identify of target, if specified, use 'dev' as conan chanel and use 'ref' as version")
     parser.add_argument('-v','--version', help='the conan package version, if specified will override default.')
+    parser.add_argument('-d', '--default', help='force use default rule to build package. if not set this option, we first use "${user_dir}/.cpptools/conan_targets" as conanbuild configurations.', action='store_true')
     parser.add_argument('--without_native', action='store_true', help='not build native package')
     parser.add_argument('--android', action='store_true', help='build android package.')
     if get_os_name() == 'Macos':
         parser.add_argument('--ios', action='store_true', help='build ios package.')
     parser.add_argument('--arch', choices=['x86','x86_64','armv7','armv8','all', 'default'], default='default', help='target arch')
     parser.add_argument('--android_arch', choices=['x86','x86_64','armv7','armv8','all', 'default'], default='default', help='android target arch')
     parser.add_argument('--debug', action='store_true', help='build debug package.')
@@ -128,18 +132,21 @@
     parser.add_argument('--upload', action='store_true', help='upload pacakge to conan recip', default=False)
     parser.add_argument('-c', '--chn', help='specify conan channel, will override default rule.')
     parser.add_argument('-s', '--settings', help='specify additional conan settings.', default='')
     parser.add_argument('-e', '--env', help='specify addtional envrioment variables.')
     parser.add_argument('--build_version', help='append building number to version, avalible with CI system.')
 
     args = parser.parse_args()
+    targets_dir = f'{os.path.expanduser("~")}/.cpptools/conan_targets'
+    if args.default:
+        targets_dir = f'{os.path.dirname(__file__)}/targets'
 
     if args.target == 'list':
         print('inside pacakges:\n')
-        refs = os.listdir(f'{os.path.dirname(__file__)}/targets')
+        refs = os.listdir(targets_dir)
         for ref in refs:
             if ref.endswith('.py.in'):
                 print(ref.removesuffix(".py.in"))
         exit(0)
 
     git_ref = ''
     version = ''
@@ -154,22 +161,22 @@
     conan_file = f'{os.path.dirname(__file__)}/conanfile.py'
     if os.path.exists(conan_file) :
         if os.path.isdir(conan_file):
             shutil.rmtree(conan_file)
         else:
             os.remove(Path(conan_file))
 
-    reposes_config = open(f'{os.path.dirname(__file__)}/targets/repos.yaml', "r", encoding='utf-8')
+    reposes_config = open(f'{targets_dir}/repos.yaml', "r", encoding='utf-8')
     reposes = yaml.load(reposes_config, Loader=yaml.Loader)
 
     tmpl_file:str = args.target
     
     if not Path(tmpl_file).is_file() :
-        if find_target(f'{os.path.dirname(__file__)}/targets', f'{tmpl_file}.py.in'):
-            tmpl_file = f'{os.path.dirname(__file__)}/targets/{tmpl_file}.py.in'
+        if find_target(targets_dir, f'{tmpl_file}.py.in'):
+            tmpl_file = f'{targets_dir}/{tmpl_file}.py.in'
         else:
             print('Error: Invalid target.')
             exit(-1)
     else:
         target = read_target_name(tmpl_file)
         version = read_target_version(tmpl_file)
```

## Program Files/WindowsApps/PythonSoftwareFoundation.Python.3.11_3.11.1008.0_x64__qbz5n2kfra8p0/Lib/site-packages/conanbuild/targets/repos.yaml

```diff
@@ -2,15 +2,15 @@
 MaxDS: git@gitlab.gz.cvte.cn:1602
 MaxME: git@gitlab.gz.cvte.cn:1602/sdks/maxme.git
 OpenCV: git@gitlab.gz.cvte.cn:1602
 OpenSSL: git@gitlab.gz.cvte.cn:1602
 Poco: git@gitlab.gz.cvte.cn:1602
 Protoc: git@gitlab.gz.cvte.cn:1602
 SipEngine: git@gitlab.gz.cvte.cn:1602
-StackEngine: git@gitlab.gz.cvte.cn:1602/sdks/maxme.git
+StackEngine: git@gitlab.gz.cvte.cn:1602/sdks/avcengine.git
 VirtualDevice: git@gitlab.gz.cvte.cn:1602
 abseil: https://github.com/abseil/abseil-cpp.git
 cairo: none
 disruptor: git@gitlab.gz.cvte.cn:1602/3rd/disruptor.git
 expat: none
 freetype: git@gitlab.gz.cvte.cn:1602
 gflags: git@gitlab.gz.cvte.cn:1602
```

## Program Files/WindowsApps/PythonSoftwareFoundation.Python.3.11_3.11.1008.0_x64__qbz5n2kfra8p0/Lib/site-packages/conanbuild/targets/StackEngine.py.in

```diff
@@ -0,0 +1,310 @@
+00000000: 6672 6f6d 2063 6f6e 616e 7320 696d 706f  from conans impo
+00000010: 7274 2043 6f6e 616e 4669 6c65 2c20 746f  rt ConanFile, to
+00000020: 6f6c 730d 0a66 726f 6d20 636f 6e61 6e73  ols..from conans
+00000030: 2e75 7469 6c20 696d 706f 7274 2066 696c  .util import fil
+00000040: 6573 0d0a 696d 706f 7274 206f 730d 0a69  es..import os..i
+00000050: 6d70 6f72 7420 7368 7574 696c 0d0a 0d0a  mport shutil....
+00000060: 636c 6173 7320 5374 6163 6b45 6e67 696e  class StackEngin
+00000070: 6543 6f6e 616e 2843 6f6e 616e 4669 6c65  eConan(ConanFile
+00000080: 293a 0d0a 2020 2020 6e61 6d65 203d 2022  ):..    name = "
+00000090: 5374 6163 6b45 6e67 696e 6522 0d0a 2020  StackEngine"..  
+000000a0: 2020 7665 7273 696f 6e20 3d20 2240 7665    version = "@ve
+000000b0: 7273 696f 6e40 220d 0a20 2020 2067 656e  rsion@"..    gen
+000000c0: 6572 6174 6f72 7320 3d20 2263 6d61 6b65  erators = "cmake
+000000d0: 220d 0a20 2020 2073 6574 7469 6e67 7320  "..    settings 
+000000e0: 3d20 226f 7322 2c20 2261 7263 6822 2c20  = "os", "arch", 
+000000f0: 2263 6f6d 7069 6c65 7222 2c20 2262 7569  "compiler", "bui
+00000100: 6c64 5f74 7970 6522 0d0a 2020 2020 6f70  ld_type"..    op
+00000110: 7469 6f6e 7320 3d20 7b22 7368 6172 6564  tions = {"shared
+00000120: 223a 205b 5472 7565 2c20 4661 6c73 655d  ": [True, False]
+00000130: 7d0d 0a20 2020 2064 6566 6175 6c74 5f6f  }..    default_o
+00000140: 7074 696f 6e73 203d 2022 7368 6172 6564  ptions = "shared
+00000150: 3d54 7275 6522 0d0a 2020 2020 7572 6c20  =True"..    url 
+00000160: 3d20 2267 6974 4067 6974 6c61 622e 677a  = "git@gitlab.gz
+00000170: 2e63 7674 652e 636e 3a31 3630 322f 7364  .cvte.cn:1602/sd
+00000180: 6b73 2f61 7663 656e 6769 6e65 2e67 6974  ks/avcengine.git
+00000190: 220d 0a20 2020 2023 206c 6963 656e 7365  "..    # license
+000001a0: 203d 2022 6874 7470 3a2f 2f77 7777 2e7a   = "http://www.z
+000001b0: 6c69 622e 6e65 742f 7a6c 6962 5f6c 6963  lib.net/zlib_lic
+000001c0: 656e 7365 2e68 746d 6c22 0d0a 2020 2020  ense.html"..    
+000001d0: 2320 6465 7363 7269 7074 696f 6e20 3d20  # description = 
+000001e0: 2241 204d 6173 7369 7665 6c79 2053 7069  "A Massively Spi
+000001f0: 6666 7920 5965 7420 4465 6c69 6361 7465  ffy Yet Delicate
+00000200: 6c79 2055 6e6f 6274 7275 7369 7665 2043  ly Unobtrusive C
+00000210: 6f6d 7072 6573 7369 6f6e 204c 6962 7261  ompression Libra
+00000220: 7279 2022 205c 0d0a 2020 2020 2320 2020  ry " \..    #   
+00000230: 2020 2020 2020 2020 2020 2020 2228 416c              "(Al
+00000240: 736f 2046 7265 652c 204e 6f74 2074 6f20  so Free, Not to 
+00000250: 4d65 6e74 696f 6e20 556e 656e 6375 6d62  Mention Unencumb
+00000260: 6572 6564 2062 7920 5061 7465 6e74 7329  ered by Patents)
+00000270: 220d 0a0d 0a20 2020 2064 6566 2063 6f6e  "....    def con
+00000280: 6669 6775 7265 2873 656c 6629 3a0d 0a20  figure(self):.. 
+00000290: 2020 2020 2020 2064 656c 2073 656c 662e         del self.
+000002a0: 7365 7474 696e 6773 2e63 6f6d 7069 6c65  settings.compile
+000002b0: 722e 6c69 6263 7878 0d0a 0d0a 2020 2020  r.libcxx....    
+000002c0: 6465 6620 736f 7572 6365 2873 656c 6629  def source(self)
+000002d0: 3a0d 0a20 2020 2020 2020 2073 656c 662e  :..        self.
+000002e0: 7275 6e28 2767 6974 2063 6c6f 6e65 2067  run('git clone g
+000002f0: 6974 4067 6974 6c61 622e 677a 2e63 7674  it@gitlab.gz.cvt
+00000300: 652e 636e 3a31 3630 322f 7364 6b73 2f61  e.cn:1602/sdks/a
+00000310: 7663 656e 6769 6e65 2e67 6974 2040 6769  vcengine.git @gi
+00000320: 745f 7265 6640 202d 2d64 6570 7468 3d31  t_ref@ --depth=1
+00000330: 202e 2729 0d0a 2020 2020 2020 2020 7265   .')..        re
+00000340: 7475 726e 0d0a 2020 2020 6465 6620 6275  turn..    def bu
+00000350: 696c 6428 7365 6c66 293a 0d0a 2020 2020  ild(self):..    
+00000360: 2020 2020 7072 696e 7428 227a 6c6a 2073      print("zlj s
+00000370: 7461 7274 2063 616c 6c20 6275 696c 6420  tart call build 
+00000380: 6675 6e63 7469 6f6e 2229 0d0a 2020 2020  function")..    
+00000390: 2020 2020 7769 7468 2074 6f6f 6c73 2e63      with tools.c
+000003a0: 6864 6972 2873 656c 662e 6275 696c 645f  hdir(self.build_
+000003b0: 666f 6c64 6572 293a 0d0a 2020 2020 2020  folder):..      
+000003c0: 2020 2020 2020 6966 2873 656c 662e 7365        if(self.se
+000003d0: 7474 696e 6773 2e6f 7320 3d3d 2027 5769  ttings.os == 'Wi
+000003e0: 6e64 6f77 7327 293a 0d0a 2020 2020 2020  ndows'):..      
+000003f0: 2020 2020 2020 2020 2020 636f 6d70 696c            compil
+00000400: 6541 7263 6820 3d20 2727 0d0a 2020 2020  eArch = ''..    
+00000410: 2020 2020 2020 2020 2020 2020 2320 6f6e              # on
+00000420: 6c79 2073 7570 706f 7274 2056 6973 7561  ly support Visua
+00000430: 6c20 5374 7564 696f 2031 3520 3230 3137  l Studio 15 2017
+00000440: 2067 656e 6572 6174 6f72 7320 666f 7220   generators for 
+00000450: 7769 6e64 6f77 730d 0a20 2020 2020 2020  windows..       
+00000460: 2020 2020 2020 2020 2063 6f6d 7069 6c65           compile
+00000470: 4765 6e65 7261 746f 7220 3d20 2756 6973  Generator = 'Vis
+00000480: 7561 6c20 5374 7564 696f 2031 3520 3230  ual Studio 15 20
+00000490: 3137 270d 0a0d 0a20 2020 2020 2020 2020  17'....         
+000004a0: 2020 2020 2020 2069 6620 2873 656c 662e         if (self.
+000004b0: 7365 7474 696e 6773 2e61 7263 6820 3d3d  settings.arch ==
+000004c0: 2027 7838 365f 3634 2729 3a0d 0a20 2020   'x86_64'):..   
+000004d0: 2020 2020 2020 2020 2020 2020 2020 2020                  
+000004e0: 2063 6f6d 7069 6c65 4172 6368 203d 2027   compileArch = '
+000004f0: 5769 6e36 3427 0d0a 0d0a 2020 2020 2020  Win64'....      
+00000500: 2020 2020 2020 2020 2020 7365 6c66 2e72            self.r
+00000510: 756e 2827 636d 616b 6520 2e20 2d47 2022  un('cmake . -G "
+00000520: 2573 2025 7322 202d 4457 4954 485f 5245  %s %s" -DWITH_RE
+00000530: 434f 5244 3d4f 4646 202d 4442 5549 4c44  CORD=OFF -DBUILD
+00000540: 5f53 444b 3d4f 4e20 2d44 434d 414b 455f  _SDK=ON -DCMAKE_
+00000550: 4255 494c 445f 5459 5045 3d25 7320 2d44  BUILD_TYPE=%s -D
+00000560: 434d 414b 455f 494e 5354 414c 4c5f 5052  CMAKE_INSTALL_PR
+00000570: 4546 4958 3d25 7327 2528 636f 6d70 696c  EFIX=%s'%(compil
+00000580: 6547 656e 6572 6174 6f72 2c20 636f 6d70  eGenerator, comp
+00000590: 696c 6541 7263 682c 2073 656c 662e 7365  ileArch, self.se
+000005a0: 7474 696e 6773 2e62 7569 6c64 5f74 7970  ttings.build_typ
+000005b0: 652c 2073 656c 662e 7061 636b 6167 655f  e, self.package_
+000005c0: 666f 6c64 6572 2929 0d0a 2020 2020 2020  folder))..      
+000005d0: 2020 2020 2020 2020 2020 6966 2873 656c            if(sel
+000005e0: 662e 7365 7474 696e 6773 2e61 7263 6820  f.settings.arch 
+000005f0: 3d3d 2022 7838 3622 293a 0d0a 2020 2020  == "x86"):..    
+00000600: 2020 2020 2020 2020 2020 2020 2020 2020                  
+00000610: 746f 6f6c 732e 7265 706c 6163 655f 696e  tools.replace_in
+00000620: 5f66 696c 6528 2277 6562 7274 632d 7372  _file("webrtc-sr
+00000630: 632f 7765 6272 7463 2f61 7069 2f6d 6564  c/webrtc/api/med
+00000640: 6961 7374 7265 616d 5f69 6e74 6572 6661  iastream_interfa
+00000650: 6365 5f61 6e64 5f69 6d70 6c69 6369 745f  ce_and_implicit_
+00000660: 7669 6465 6f5f 6672 616d 655f 6170 692e  video_frame_api.
+00000670: 636d 616b 6522 2c20 2022 6d65 6469 6173  cmake",  "medias
+00000680: 7472 6561 6d5f 696e 7465 7266 6163 655f  tream_interface_
+00000690: 616e 645f 696d 706c 6963 6974 5f76 6964  and_implicit_vid
+000006a0: 656f 5f66 7261 6d65 5f61 7069 222c 2022  eo_frame_api", "
+000006b0: 6d73 5f61 6e64 5f76 6964 656f 5f66 7261  ms_and_video_fra
+000006c0: 6d65 5f61 7069 222c 2073 7472 6963 743d  me_api", strict=
+000006d0: 4661 6c73 6529 0d0a 2020 2020 2020 2020  False)..        
+000006e0: 2020 2020 2020 2020 2020 2020 746f 6f6c              tool
+000006f0: 732e 7265 706c 6163 655f 696e 5f66 696c  s.replace_in_fil
+00000700: 6528 2277 6562 7274 632d 7372 632f 7765  e("webrtc-src/we
+00000710: 6272 7463 2f61 7069 2f6c 6962 6a69 6e67  brtc/api/libjing
+00000720: 6c65 5f70 6565 7263 6f6e 6e65 6374 696f  le_peerconnectio
+00000730: 6e5f 6170 692e 636d 616b 6522 2c20 2022  n_api.cmake",  "
+00000740: 6d65 6469 6173 7472 6561 6d5f 696e 7465  mediastream_inte
+00000750: 7266 6163 655f 616e 645f 696d 706c 6963  rface_and_implic
+00000760: 6974 5f76 6964 656f 5f66 7261 6d65 5f61  it_video_frame_a
+00000770: 7069 222c 2022 6d73 5f61 6e64 5f76 6964  pi", "ms_and_vid
+00000780: 656f 5f66 7261 6d65 5f61 7069 222c 2073  eo_frame_api", s
+00000790: 7472 6963 743d 4661 6c73 6529 0d0a 2020  trict=False)..  
+000007a0: 2020 2020 2020 2020 2020 2020 2020 2020                  
+000007b0: 2020 7365 6c66 2e72 756e 2822 636d 616b    self.run("cmak
+000007c0: 6520 2d2d 6275 696c 6420 2e20 2d2d 7461  e --build . --ta
+000007d0: 7267 6574 2073 7461 636b 656e 6769 6e65  rget stackengine
+000007e0: 202d 2d63 6f6e 6669 6720 2573 202d 2d20   --config %s -- 
+000007f0: 2f6d 6178 6370 7563 6f75 6e74 3a35 3622  /maxcpucount:56"
+00000800: 2573 656c 662e 7365 7474 696e 6773 2e62  %self.settings.b
+00000810: 7569 6c64 5f74 7970 6529 0d0a 2020 2020  uild_type)..    
+00000820: 2020 2020 2020 2020 2020 2020 2020 2020                  
+00000830: 7365 6c66 2e72 756e 2822 636d 616b 6520  self.run("cmake 
+00000840: 2d44 4255 494c 445f 5459 5045 3d25 7320  -DBUILD_TYPE=%s 
+00000850: 2d50 2063 6d61 6b65 5f69 6e73 7461 6c6c  -P cmake_install
+00000860: 2e63 6d61 6b65 2022 2573 656c 662e 7365  .cmake "%self.se
+00000870: 7474 696e 6773 2e62 7569 6c64 5f74 7970  ttings.build_typ
+00000880: 6529 0d0a 2020 2020 2020 2020 2020 2020  e)..            
+00000890: 2020 2020 2020 2020 2362 7569 6c64 206d          #build m
+000008a0: 756c 7469 2d70 726f 6365 7373 2064 6573  ulti-process des
+000008b0: 6b74 6f70 2063 6170 7475 7265 2074 6f6f  ktop capture too
+000008c0: 6c0d 0a20 2020 2020 2020 2020 2020 2020  l..             
+000008d0: 2020 2020 2020 2069 6628 6f73 2e70 6174         if(os.pat
+000008e0: 682e 6973 6669 6c65 2822 6d61 786d 652d  h.isfile("maxme-
+000008f0: 7372 632f 746f 6f6c 732f 6465 736b 746f  src/tools/deskto
+00000900: 705f 6361 7074 7572 655f 686f 7374 2f64  p_capture_host/d
+00000910: 6573 6b74 6f70 5f63 6170 7475 7265 5f68  esktop_capture_h
+00000920: 6f73 742e 7663 7870 726f 6a22 2929 3a0d  ost.vcxproj")):.
+00000930: 0a20 2020 2020 2020 2020 2020 2020 2020  .               
+00000940: 2020 2020 2020 2020 2073 656c 662e 7275           self.ru
+00000950: 6e28 2263 6d61 6b65 202d 2d62 7569 6c64  n("cmake --build
+00000960: 202e 202d 2d74 6172 6765 7420 6465 736b   . --target desk
+00000970: 746f 705f 6361 7074 7572 655f 686f 7374  top_capture_host
+00000980: 202d 2d63 6f6e 6669 6720 2573 202d 2d20   --config %s -- 
+00000990: 2f6d 6178 6370 7563 6f75 6e74 3a35 3622  /maxcpucount:56"
+000009a0: 2573 656c 662e 7365 7474 696e 6773 2e62  %self.settings.b
+000009b0: 7569 6c64 5f74 7970 6529 0d0a 2020 2020  uild_type)..    
+000009c0: 2020 2020 2020 2020 2020 2020 656c 6966              elif
+000009d0: 2873 656c 662e 7365 7474 696e 6773 2e61  (self.settings.a
+000009e0: 7263 6820 3d3d 2022 7838 365f 3634 2229  rch == "x86_64")
+000009f0: 3a0d 0a20 2020 2020 2020 2020 2020 2020  :..             
+00000a00: 2020 2020 2020 2074 6f6f 6c73 2e72 6570         tools.rep
+00000a10: 6c61 6365 5f69 6e5f 6669 6c65 2822 7765  lace_in_file("we
+00000a20: 6272 7463 2d73 7263 2f77 6562 7274 632f  brtc-src/webrtc/
+00000a30: 6170 692f 6d65 6469 6173 7472 6561 6d5f  api/mediastream_
+00000a40: 696e 7465 7266 6163 655f 616e 645f 696d  interface_and_im
+00000a50: 706c 6963 6974 5f76 6964 656f 5f66 7261  plicit_video_fra
+00000a60: 6d65 5f61 7069 2e63 6d61 6b65 222c 2020  me_api.cmake",  
+00000a70: 226d 6564 6961 7374 7265 616d 5f69 6e74  "mediastream_int
+00000a80: 6572 6661 6365 5f61 6e64 5f69 6d70 6c69  erface_and_impli
+00000a90: 6369 745f 7669 6465 6f5f 6672 616d 655f  cit_video_frame_
+00000aa0: 6170 6922 2c20 226d 735f 616e 645f 7669  api", "ms_and_vi
+00000ab0: 6465 6f5f 6672 616d 655f 6170 6922 2c20  deo_frame_api", 
+00000ac0: 7374 7269 6374 3d46 616c 7365 290d 0a20  strict=False).. 
+00000ad0: 2020 2020 2020 2020 2020 2020 2020 2020                  
+00000ae0: 2020 2074 6f6f 6c73 2e72 6570 6c61 6365     tools.replace
+00000af0: 5f69 6e5f 6669 6c65 2822 7765 6272 7463  _in_file("webrtc
+00000b00: 2d73 7263 2f77 6562 7274 632f 6170 692f  -src/webrtc/api/
+00000b10: 6c69 626a 696e 676c 655f 7065 6572 636f  libjingle_peerco
+00000b20: 6e6e 6563 7469 6f6e 5f61 7069 2e63 6d61  nnection_api.cma
+00000b30: 6b65 222c 2020 226d 6564 6961 7374 7265  ke",  "mediastre
+00000b40: 616d 5f69 6e74 6572 6661 6365 5f61 6e64  am_interface_and
+00000b50: 5f69 6d70 6c69 6369 745f 7669 6465 6f5f  _implicit_video_
+00000b60: 6672 616d 655f 6170 6922 2c20 226d 735f  frame_api", "ms_
+00000b70: 616e 645f 7669 6465 6f5f 6672 616d 655f  and_video_frame_
+00000b80: 6170 6922 2c20 7374 7269 6374 3d46 616c  api", strict=Fal
+00000b90: 7365 290d 0a20 2020 2020 2020 2020 2020  se)..           
+00000ba0: 2020 2020 2020 2020 2073 656c 662e 7275           self.ru
+00000bb0: 6e28 2263 6d61 6b65 202d 2d62 7569 6c64  n("cmake --build
+00000bc0: 202e 202d 2d74 6172 6765 7420 7374 6163   . --target stac
+00000bd0: 6b65 6e67 696e 6520 2d2d 636f 6e66 6967  kengine --config
+00000be0: 2025 7320 2d2d 202f 6d61 7863 7075 636f   %s -- /maxcpuco
+00000bf0: 756e 743a 3536 2225 7365 6c66 2e73 6574  unt:56"%self.set
+00000c00: 7469 6e67 732e 6275 696c 645f 7479 7065  tings.build_type
+00000c10: 290d 0a20 2020 2020 2020 2020 2020 2020  )..             
+00000c20: 2020 2020 2020 2073 656c 662e 7275 6e28         self.run(
+00000c30: 2263 6d61 6b65 202d 4442 5549 4c44 5f54  "cmake -DBUILD_T
+00000c40: 5950 453d 2573 202d 5020 636d 616b 655f  YPE=%s -P cmake_
+00000c50: 696e 7374 616c 6c2e 636d 616b 6522 2573  install.cmake"%s
+00000c60: 656c 662e 7365 7474 696e 6773 2e62 7569  elf.settings.bui
+00000c70: 6c64 5f74 7970 6529 0d0a 2020 2020 2020  ld_type)..      
+00000c80: 2020 2020 2020 2020 2020 2020 2020 2362                #b
+00000c90: 7569 6c64 206d 756c 7469 2d70 726f 6365  uild multi-proce
+00000ca0: 7373 2064 6573 6b74 6f70 2063 6170 7475  ss desktop captu
+00000cb0: 7265 2074 6f6f 6c0d 0a20 2020 2020 2020  re tool..       
+00000cc0: 2020 2020 2020 2020 2020 2020 2069 6628               if(
+00000cd0: 6f73 2e70 6174 682e 6973 6669 6c65 2822  os.path.isfile("
+00000ce0: 6d61 786d 652d 7372 632f 746f 6f6c 732f  maxme-src/tools/
+00000cf0: 6465 736b 746f 705f 6361 7074 7572 655f  desktop_capture_
+00000d00: 686f 7374 2f64 6573 6b74 6f70 5f63 6170  host/desktop_cap
+00000d10: 7475 7265 5f68 6f73 742e 7663 7870 726f  ture_host.vcxpro
+00000d20: 6a22 2929 3a0d 0a20 2020 2020 2020 2020  j")):..         
+00000d30: 2020 2020 2020 2020 2020 2020 2020 2073                 s
+00000d40: 656c 662e 7275 6e28 2263 6d61 6b65 202d  elf.run("cmake -
+00000d50: 2d62 7569 6c64 202e 202d 2d74 6172 6765  -build . --targe
+00000d60: 7420 6465 736b 746f 705f 6361 7074 7572  t desktop_captur
+00000d70: 655f 686f 7374 202d 2d63 6f6e 6669 6720  e_host --config 
+00000d80: 2573 202d 2d20 2f6d 6178 6370 7563 6f75  %s -- /maxcpucou
+00000d90: 6e74 3a35 3622 2573 656c 662e 7365 7474  nt:56"%self.sett
+00000da0: 696e 6773 2e62 7569 6c64 5f74 7970 6529  ings.build_type)
+00000db0: 0d0a 0d0a 2020 2020 6465 6620 7061 636b  ....    def pack
+00000dc0: 6167 6528 7365 6c66 293a 0d0a 2020 2020  age(self):..    
+00000dd0: 2020 2020 6966 2873 656c 662e 7365 7474      if(self.sett
+00000de0: 696e 6773 2e6f 7320 3d3d 2022 5769 6e64  ings.os == "Wind
+00000df0: 6f77 7322 293a 0d0a 2020 2020 2020 2020  ows"):..        
+00000e00: 2020 2020 6966 2873 656c 662e 7365 7474      if(self.sett
+00000e10: 696e 6773 2e61 7263 6820 3d3d 2022 7838  ings.arch == "x8
+00000e20: 3622 293a 0d0a 2020 2020 2020 2020 2020  6"):..          
+00000e30: 2020 2020 2020 7368 7574 696c 2e63 6f70        shutil.cop
+00000e40: 7928 6f73 2e70 6174 682e 6a6f 696e 2873  y(os.path.join(s
+00000e50: 656c 662e 6275 696c 645f 666f 6c64 6572  elf.build_folder
+00000e60: 2c20 2762 696e 5c5c 7374 6163 6b65 6e67  , 'bin\\stackeng
+00000e70: 696e 652e 7064 6227 292c 206f 732e 7061  ine.pdb'), os.pa
+00000e80: 7468 2e6a 6f69 6e28 7365 6c66 2e70 6163  th.join(self.pac
+00000e90: 6b61 6765 5f66 6f6c 6465 722c 2027 6269  kage_folder, 'bi
+00000ea0: 6e5c 5c73 7461 636b 656e 6769 6e65 2e70  n\\stackengine.p
+00000eb0: 6462 2729 290d 0a20 2020 2020 2020 2020  db'))..         
+00000ec0: 2020 2020 2020 2073 6875 7469 6c2e 636f         shutil.co
+00000ed0: 7079 286f 732e 7061 7468 2e6a 6f69 6e28  py(os.path.join(
+00000ee0: 7365 6c66 2e62 7569 6c64 5f66 6f6c 6465  self.build_folde
+00000ef0: 722c 2027 6269 6e5c 5c64 6573 6b74 6f70  r, 'bin\\desktop
+00000f00: 5f63 6170 7475 7265 5f68 6f73 742e 7064  _capture_host.pd
+00000f10: 6227 292c 206f 732e 7061 7468 2e6a 6f69  b'), os.path.joi
+00000f20: 6e28 7365 6c66 2e70 6163 6b61 6765 5f66  n(self.package_f
+00000f30: 6f6c 6465 722c 2027 6269 6e5c 5c64 6573  older, 'bin\\des
+00000f40: 6b74 6f70 5f63 6170 7475 7265 5f68 6f73  ktop_capture_hos
+00000f50: 742e 7064 6227 2929 0d0a 2020 2020 2020  t.pdb'))..      
+00000f60: 2020 2020 2020 2020 2020 7368 7574 696c            shutil
+00000f70: 2e63 6f70 7928 6f73 2e70 6174 682e 6a6f  .copy(os.path.jo
+00000f80: 696e 2873 656c 662e 6275 696c 645f 666f  in(self.build_fo
+00000f90: 6c64 6572 2c20 2762 696e 5c5c 6465 736b  lder, 'bin\\desk
+00000fa0: 746f 705f 6361 7074 7572 655f 686f 7374  top_capture_host
+00000fb0: 2e65 7865 2729 2c20 6f73 2e70 6174 682e  .exe'), os.path.
+00000fc0: 6a6f 696e 2873 656c 662e 7061 636b 6167  join(self.packag
+00000fd0: 655f 666f 6c64 6572 2c20 2762 696e 5c5c  e_folder, 'bin\\
+00000fe0: 6465 736b 746f 705f 6361 7074 7572 655f  desktop_capture_
+00000ff0: 686f 7374 2e65 7865 2729 290d 0a20 2020  host.exe'))..   
+00001000: 2020 2020 2020 2020 2065 6c69 6628 7365           elif(se
+00001010: 6c66 2e73 6574 7469 6e67 732e 6172 6368  lf.settings.arch
+00001020: 203d 3d20 2278 3836 5f36 3422 293a 0d0a   == "x86_64"):..
+00001030: 2020 2020 2020 2020 2020 2020 2020 2020                  
+00001040: 7368 7574 696c 2e63 6f70 7928 6f73 2e70  shutil.copy(os.p
+00001050: 6174 682e 6a6f 696e 2873 656c 662e 6275  ath.join(self.bu
+00001060: 696c 645f 666f 6c64 6572 2c20 2762 696e  ild_folder, 'bin
+00001070: 5c5c 7374 6163 6b65 6e67 696e 652e 7064  \\stackengine.pd
+00001080: 6227 292c 206f 732e 7061 7468 2e6a 6f69  b'), os.path.joi
+00001090: 6e28 7365 6c66 2e70 6163 6b61 6765 5f66  n(self.package_f
+000010a0: 6f6c 6465 722c 2027 6269 6e5c 5c73 7461  older, 'bin\\sta
+000010b0: 636b 656e 6769 6e65 2e70 6462 2729 290d  ckengine.pdb')).
+000010c0: 0a20 2020 2020 2020 2020 2020 2020 2020  .               
+000010d0: 2073 6875 7469 6c2e 636f 7079 286f 732e   shutil.copy(os.
+000010e0: 7061 7468 2e6a 6f69 6e28 7365 6c66 2e62  path.join(self.b
+000010f0: 7569 6c64 5f66 6f6c 6465 722c 2027 6269  uild_folder, 'bi
+00001100: 6e5c 5c64 6573 6b74 6f70 5f63 6170 7475  n\\desktop_captu
+00001110: 7265 5f68 6f73 742e 7064 6227 292c 206f  re_host.pdb'), o
+00001120: 732e 7061 7468 2e6a 6f69 6e28 7365 6c66  s.path.join(self
+00001130: 2e70 6163 6b61 6765 5f66 6f6c 6465 722c  .package_folder,
+00001140: 2027 6269 6e5c 5c64 6573 6b74 6f70 5f63   'bin\\desktop_c
+00001150: 6170 7475 7265 5f68 6f73 742e 7064 6227  apture_host.pdb'
+00001160: 2929 0d0a 2020 2020 2020 2020 2020 2020  ))..            
+00001170: 2020 2020 7368 7574 696c 2e63 6f70 7928      shutil.copy(
+00001180: 6f73 2e70 6174 682e 6a6f 696e 2873 656c  os.path.join(sel
+00001190: 662e 6275 696c 645f 666f 6c64 6572 2c20  f.build_folder, 
+000011a0: 2762 696e 5c5c 6465 736b 746f 705f 6361  'bin\\desktop_ca
+000011b0: 7074 7572 655f 686f 7374 2e65 7865 2729  pture_host.exe')
+000011c0: 2c20 6f73 2e70 6174 682e 6a6f 696e 2873  , os.path.join(s
+000011d0: 656c 662e 7061 636b 6167 655f 666f 6c64  elf.package_fold
+000011e0: 6572 2c20 2762 696e 5c5c 6465 736b 746f  er, 'bin\\deskto
+000011f0: 705f 6361 7074 7572 655f 686f 7374 2e65  p_capture_host.e
+00001200: 7865 2729 290d 0a20 2020 2020 2020 2020  xe'))..         
+00001210: 2020 206f 7269 203d 206f 732e 7061 7468     ori = os.path
+00001220: 2e6a 6f69 6e28 7365 6c66 2e70 6163 6b61  .join(self.packa
+00001230: 6765 5f66 6f6c 6465 722c 2027 696e 636c  ge_folder, 'incl
+00001240: 7564 6527 290d 0a20 2020 2020 2020 2020  ude')..         
+00001250: 2020 2074 6d70 203d 206f 732e 7061 7468     tmp = os.path
+00001260: 2e6a 6f69 6e28 7365 6c66 2e70 6163 6b61  .join(self.packa
+00001270: 6765 5f66 6f6c 6465 722c 2027 746d 705f  ge_folder, 'tmp_
+00001280: 696e 636c 7564 6527 290d 0a20 2020 2020  include')..     
+00001290: 2020 2020 2020 206f 732e 7265 6e61 6d65         os.rename
+000012a0: 286f 7269 2c20 746d 7029 0d0a 2020 2020  (ori, tmp)..    
+000012b0: 2020 2020 2020 2020 6f73 2e72 656e 616d          os.renam
+000012c0: 6528 6f73 2e70 6174 682e 6a6f 696e 2874  e(os.path.join(t
+000012d0: 6d70 2c20 2761 7663 656e 6769 6e65 2729  mp, 'avcengine')
+000012e0: 2c20 6f72 6929 0d0a 2020 2020 2020 2020  , ori)..        
+000012f0: 2020 2020 7368 7574 696c 2e72 6d74 7265      shutil.rmtre
+00001300: 6528 746d 7029 0d0a 2020 2020 6465 6620  e(tmp)..    def 
+00001310: 7061 636b 6167 655f 696e 666f 2873 656c  package_info(sel
+00001320: 6629 3a0d 0a20 2020 2020 2020 2073 656c  f):..        sel
+00001330: 662e 6370 705f 696e 666f 2e6c 6962 7320  f.cpp_info.libs 
+00001340: 3d20 5b27 7374 6163 6b65 6e67 696e 6527  = ['stackengine'
+00001350: 5d0d 0a                                  ]..
```

## Program Files/WindowsApps/PythonSoftwareFoundation.Python.3.11_3.11.1008.0_x64__qbz5n2kfra8p0/Lib/site-packages/conanbuild/__pycache__/builder.cpython-311.pyc

### Python bytecode

```diff
@@ -1,10 +1,10 @@
 magic:    0xa70d0d0a
-moddate:  0xdcdc4064 (Thu Apr 20 06:34:04 2023 UTC)
-files sz: 12820
+moddate:  0xc5657864 (Thu Jun  1 09:32:53 2023 UTC)
+files sz: 13304
 code
    argcount  : 0
    nlocals   : 0
    stacksize : 17
    flags     : 0
    code
       0x9700640064016c005a00640064016c015a01640064016c025a02640064
@@ -190,33 +190,33 @@
                296 MAKE_FUNCTION            4 (annotations)
                298 STORE_NAME              22 (read_target_version)
    
    107         300 LOAD_CONST              29 (<code object run, file "\Program Files\WindowsApps\PythonSoftwareFoundation.Python.3.11_3.11.1008.0_x64__qbz5n2kfra8p0\Lib\site-packages\conanbuild\builder.py", line 107>)
                302 MAKE_FUNCTION            0
                304 STORE_NAME              23 (run)
    
-   303         306 LOAD_NAME               24 (__name__)
+   310         306 LOAD_NAME               24 (__name__)
                308 LOAD_CONST              30 ('__main__')
                310 COMPARE_OP               2 (==)
                316 POP_JUMP_FORWARD_IF_FALSE    26 (to 370)
    
-   304         318 PUSH_NULL
+   311         318 PUSH_NULL
                320 LOAD_NAME                1 (sys)
                322 LOAD_ATTR               25 (exit)
                332 PUSH_NULL
                334 LOAD_NAME               23 (run)
                336 PRECALL                  0
                340 CALL                     0
                350 PRECALL                  1
                354 CALL                     1
                364 POP_TOP
                366 LOAD_CONST               1 (None)
                368 RETURN_VALUE
    
-   303     >>  370 LOAD_CONST               1 (None)
+   310     >>  370 LOAD_CONST               1 (None)
                372 RETURN_VALUE
    consts
       0
       None
       ('Path',)
       code
          argcount  : 0
@@ -1169,1396 +1169,1458 @@
          cellvars   ()
          filename   '\\Program Files\\WindowsApps\\PythonSoftwareFoundation.Python.3.11_3.11.1008.0_x64__qbz5n2kfra8p0\\Lib\\site-packages\\conanbuild\\builder.py'
          name       'read_target_version'
          firstlineno 97
          lnotab 0x020124012c012c012c012a012eff0203
       code
          argcount  : 0
-         nlocals   : 26
+         nlocals   : 27
          stacksize : 10
          flags     : 3
          code
-            0x97007401000000000000000000006a0100000000000000006401ac02a6
-            010000ab0100000000000000007d007c00a0020000000000000000000000
-            00000000000000000064036404ac05a6020000ab02000000000000000001
-            007c00a00200000000000000000000000000000000000000006406640764
-            08ac05a6030000ab03000000000000000001007c00a00200000000000000
-            000000000000000000000000006409640a640bac05a6030000ab03000000
-            000000000001007c00a00200000000000000000000000000000000000000
-            00640c640d640eac05a6030000ab03000000000000000001007c00a00200
-            00000000000000000000000000000000000000640f64106411ac05a60300
-            00ab03000000000000000001007c00a00200000000000000000000000000
-            00000000000000641264136414ac15a6030000ab03000000000000000001
-            007c00a00200000000000000000000000000000000000000006416641364
-            17ac15a6030000ab03000000000000000001007407000000000000000000
-            00a6000000ab00000000000000000064186b020000000072187c00a00200
-            0000000000000000000000000000000000000064196413641aac15a60300
-            00ab03000000000000000001007c00a00200000000000000000000000000
-            00000000000000641b6700641ca201641d641eac1fa6040000ab04000000
-            000000000001007c00a00200000000000000000000000000000000000000
-            0064206700641ca201641d6421ac1fa6040000ab04000000000000000001
-            007c00a00200000000000000000000000000000000000000006422641364
-            23ac15a6030000ab03000000000000000001007c00a00200000000000000
-            00000000000000000000000000642467006425a2016426ac27a6030000ab
-            03000000000000000001007c00a002000000000000000000000000000000
-            000000000064286429642a6702642bac27a6030000ab0300000000000000
-            0001007c00a0020000000000000000000000000000000000000000642c64
-            2dac05a6020000ab02000000000000000001007c00a00200000000000000
-            00000000000000000000000000642e642fac05a6020000ab020000000000
-            00000001007c00a002000000000000000000000000000000000000000064
-            306431ac05a6020000ab02000000000000000001007c00a0020000000000
-            0000000000000000000000000000006432641364336434ac35a6040000ab
-            04000000000000000001007c00a002000000000000000000000000000000
-            0000000000643664376438ac05a6030000ab03000000000000000001007c
-            00a00200000000000000000000000000000000000000006439643a643b64
-            3cac3da6040000ab04000000000000000001007c00a00200000000000000
-            00000000000000000000000000643e643f6440ac05a6030000ab03000000
-            000000000001007c00a00200000000000000000000000000000000000000
-            0064416442ac05a6020000ab02000000000000000001007c00a004000000
+            0x97007400000000000000000000006a010000000000000000a002000000
+            00000000000000000000000000000000007400000000000000000000006a
+            010000000000000000a00300000000000000000000000000000000000000
+            006401a6010000ab0100000000000000009b0064029d02a6010000ab0100
+            00000000000000735a7409000000000000000000006a0500000000000000
+            007400000000000000000000006a010000000000000000a0060000000000
+            000000000000000000000000000000740e00000000000000000000a60100
+            00ab0100000000000000009b0064039d027400000000000000000000006a
+            010000000000000000a00300000000000000000000000000000000000000
+            006401a6010000ab0100000000000000009b0064029d02a6020000ab0200
+            0000000000000001007411000000000000000000006a0900000000000000
+            006404ac05a6010000ab0100000000000000007d007c00a00a0000000000
+            00000000000000000000000000000064066407ac08a6020000ab02000000
+            000000000001007c00a00a00000000000000000000000000000000000000
+            006409640a640bac08a6030000ab03000000000000000001007c00a00a00
+            00000000000000000000000000000000000000640c640d640eac08a60300
+            00ab03000000000000000001007c00a00a00000000000000000000000000
+            00000000000000640f64106411ac08a6030000ab03000000000000000001
+            007c00a00a00000000000000000000000000000000000000006412641364
+            14ac08a6030000ab03000000000000000001007c00a00a00000000000000
+            000000000000000000000000006415641664176418ac19a6040000ab0400
+            0000000000000001007c00a00a0000000000000000000000000000000000
+            000000641a6418641bac1ca6030000ab03000000000000000001007c00a0
+            0a0000000000000000000000000000000000000000641d6418641eac1ca6
+            030000ab0300000000000000000100741700000000000000000000a60000
+            00ab000000000000000000641f6b020000000072187c00a00a0000000000
+            000000000000000000000000000000642064186421ac1ca6030000ab0300
+            0000000000000001007c00a00a0000000000000000000000000000000000
+            000000642267006423a20164246425ac26a6040000ab0400000000000000
+            0001007c00a00a0000000000000000000000000000000000000000642767
+            006423a20164246428ac26a6040000ab04000000000000000001007c00a0
+            0a000000000000000000000000000000000000000064296418642aac1ca6
+            030000ab03000000000000000001007c00a00a0000000000000000000000
+            000000000000000000642b6700642ca201642dac2ea6030000ab03000000
+            000000000001007c00a00a00000000000000000000000000000000000000
+            00642f6430643167026432ac2ea6030000ab03000000000000000001007c
+            00a00a000000000000000000000000000000000000000064336434ac08a6
+            020000ab02000000000000000001007c00a00a0000000000000000000000
+            00000000000000000064356436ac08a6020000ab02000000000000000001
+            007c00a00a000000000000000000000000000000000000000064376438ac
+            08a6020000ab02000000000000000001007c00a00a000000000000000000
+            000000000000000000000064396418643a643bac3ca6040000ab04000000
+            000000000001007c00a00a00000000000000000000000000000000000000
+            00643d643e643fac08a6030000ab03000000000000000001007c00a00a00
+            000000000000000000000000000000000000006440644164426443ac44a6
+            040000ab04000000000000000001007c00a00a0000000000000000000000
+            000000000000000000644564466447ac08a6030000ab0300000000000000
+            0001007c00a00a0000000000000000000000000000000000000000644864
+            49ac08a6020000ab02000000000000000001007c00a00c00000000000000
+            00000000000000000000000000a6000000ab0000000000000000007d0174
+            00000000000000000000006a010000000000000000a00300000000000000
+            000000000000000000000000006401a6010000ab0100000000000000009b
+            0064029d027d027c016a0d00000000000000007227740000000000000000
+            0000006a010000000000000000a006000000000000000000000000000000
+            0000000000740e00000000000000000000a6010000ab0100000000000000
+            009b0064039d027d027c016a0e0000000000000000644a6b020000000072
+            6e741f00000000000000000000644ba6010000ab01000000000000000001
+            007401000000000000000000006a1000000000000000007c02a6010000ab
+            0100000000000000007d037c0344005d397d047c04a01100000000000000
+            00000000000000000000000000644ca6010000ab01000000000000000072
+            22741f000000000000000000007c04a01200000000000000000000000000
+            00000000000000644ca6010000ab010000000000000000a6010000ab0100
+            0000000000000001008c3a742700000000000000000000644da6010000ab
+            010000000000000000010064437d0564437d0664437d07644e7d087c016a
+            1400000000000000007d097c016a1500000000000000007d0a67007d0b67
+            007d0c7c016a0e00000000000000007d0d7400000000000000000000006a
+            010000000000000000a00600000000000000000000000000000000000000
+            00740e00000000000000000000a6010000ab0100000000000000009b0064
+            4f9d027d0e7400000000000000000000006a010000000000000000a00200
+            000000000000000000000000000000000000007c0ea6010000ab01000000
+            000000000072557400000000000000000000006a010000000000000000a0
+            1600000000000000000000000000000000000000007c0ea6010000ab0100
+            0000000000000072157409000000000000000000006a1700000000000000
+            007c0ea6010000ab01000000000000000001006e21740100000000000000
+            0000006a1800000000000000007433000000000000000000007c0ea60100
+            00ab010000000000000000a6010000ab0100000000000000000100743500
+            0000000000000000007c029b0064509d0264516452ac53a6030000ab0300
+            000000000000007d0f7437000000000000000000006a1c00000000000000
+            007c0f7436000000000000000000006a1d0000000000000000ac54a60200
+            00ab0200000000000000007d107c016a0e00000000000000007d11743300
+            0000000000000000007c11a6010000ab010000000000000000a01e000000
             0000000000000000000000000000000000a6000000ab0000000000000000
-            007d017c016a05000000000000000064436b02000000007293740d000000
-            000000000000006444a6010000ab0100000000000000000100740f000000
-            000000000000006a080000000000000000740e000000000000000000006a
-            090000000000000000a00a00000000000000000000000000000000000000
-            00741600000000000000000000a6010000ab0100000000000000009b0064
-            459d02a6010000ab0100000000000000007d027c0244005d397d037c03a0
-            0c00000000000000000000000000000000000000006446a6010000ab0100
-            000000000000007222740d000000000000000000007c03a00d0000000000
-            0000000000000000000000000000006446a6010000ab0100000000000000
-            00a6010000ab01000000000000000001008c3a741d000000000000000000
-            006447a6010000ab0100000000000000000100643c7d04643c7d05643c7d
-            0664487d077c016a0f00000000000000007d087c016a1000000000000000
-            007d0967007d0a67007d0b7c016a0500000000000000007d0c740e000000
-            000000000000006a090000000000000000a00a0000000000000000000000
-            000000000000000000741600000000000000000000a6010000ab01000000
-            00000000009b0064499d027d0d740e000000000000000000006a09000000
-            0000000000a01100000000000000000000000000000000000000007c0da6
-            010000ab0100000000000000007255740e000000000000000000006a0900
-            00000000000000a01200000000000000000000000000000000000000007c
-            0da6010000ab01000000000000000072157427000000000000000000006a
-            1400000000000000007c0da6010000ab01000000000000000001006e2174
-            0f000000000000000000006a150000000000000000742d00000000000000
-            0000007c0da6010000ab010000000000000000a6010000ab010000000000
-            0000000100742f00000000000000000000740e000000000000000000006a
-            090000000000000000a00a00000000000000000000000000000000000000
-            00741600000000000000000000a6010000ab0100000000000000009b0064
-            4a9d02644b644cac4da6030000ab0300000000000000007d0e7431000000
-            000000000000006a1900000000000000007c0e7430000000000000000000
-            006a1a0000000000000000ac4ea6020000ab0200000000000000007d0f7c
-            016a0500000000000000007d10742d000000000000000000007c10a60100
-            00ab010000000000000000a01b0000000000000000000000000000000000
-            000000a6000000ab00000000000000000073827439000000000000000000
-            00740e000000000000000000006a090000000000000000a00a0000000000
-            000000000000000000000000000000741600000000000000000000a60100
-            00ab0100000000000000009b0064459d027c109b0064469d02a6020000ab
-            020000000000000000722b740e000000000000000000006a090000000000
-            000000a00a00000000000000000000000000000000000000007416000000
-            00000000000000a6010000ab0100000000000000009b00644f7c109b0064
-            469d047d106e3d740d000000000000000000006450a6010000ab01000000
-            00000000000100741d000000000000000000006451a6010000ab01000000
-            000000000001006e1e743b000000000000000000007c10a6010000ab0100
-            000000000000007d0c743d000000000000000000007c10a6010000ab0100
-            000000000000007d05740700000000000000000000a6000000ab00000000
-            00000000007d117c087213743f000000000000000000007c08a6010000ab
-            01000000000000000064476b020000000072147c1164526b020000000072
-            0364537d086e0b7c1164186b02000000007203642a7d086e0264297d087c
-            097213743f000000000000000000007c09a6010000ab0100000000000000
-            0064476b020000000072887c0864536b0200000000720364547d096e7f7c
-            08642a6b0200000000720364557d096e767c0864296b0200000000727074
-            0f000000000000000000006a2000000000000000006456a6010000ab0100
-            000000000000007d127c12a0210000000000000000000000000000000000
-            000000a6000000ab000000000000000000a0220000000000000000000000
-            000000000000000000a6000000ab0000000000000000007d097c09a02300
-            000000000000000000000000000000000000006457a6010000ab01000000
-            000000000064586b0400000000721d7c0964007c09a02400000000000000
-            000000000000000000000000006457a6010000ab01000000000000000085
-            02190000000000000000007d097c016a25000000000000000064596b0200
-            00000072867c1164526b0200000000722b7c0aa026000000000000000000
-            0000000000000000000000645aa6010000ab01000000000000000001007c
-            0aa0260000000000000000000000000000000000000000645ba6010000ab
-            01000000000000000001006ec17c0aa02600000000000000000000000000
-            00000000000000645aa6010000ab01000000000000000001007c0aa02600
-            00000000000000000000000000000000000000645ba6010000ab01000000
-            000000000001007c0aa02600000000000000000000000000000000000000
-            00645ca6010000ab01000000000000000001007c0aa02600000000000000
-            00000000000000000000000000645da6010000ab01000000000000000001
-            006e6c7c016a250000000000000000641d6b020000000072477c1164526b
-            0200000000722b7c0aa02600000000000000000000000000000000000000
-            00645aa6010000ab01000000000000000001007c0aa02600000000000000
-            00000000000000000000000000645ba6010000ab01000000000000000001
-            006e307c0aa0260000000000000000000000000000000000000000645ba6
-            010000ab01000000000000000001006e1a7c0aa026000000000000000000
-            00000000000000000000007c016a250000000000000000a6010000ab0100
-            0000000000000001007c016a27000000000000000064596b020000000072
-            557c0ba0260000000000000000000000000000000000000000645aa60100
-            00ab01000000000000000001007c0ba02600000000000000000000000000
-            00000000000000645ba6010000ab01000000000000000001007c0ba02600
-            00000000000000000000000000000000000000645ca6010000ab01000000
-            000000000001007c0ba02600000000000000000000000000000000000000
-            00645da6010000ab01000000000000000001006e507c016a270000000000
-            000000641d6b0200000000722b7c0ba02600000000000000000000000000
-            00000000000000645ca6010000ab01000000000000000001007c0ba02600
-            00000000000000000000000000000000000000645da6010000ab01000000
-            000000000001006e1a7c0aa0260000000000000000000000000000000000
-            0000007c016a250000000000000000a6010000ab01000000000000000001
-            007c016a2800000000000000007d137c016a2900000000000000007d147c
-            016a2a00000000000000007d157c137213743f000000000000000000007c
-            13a6010000ab01000000000000000064476b0200000000720264297d137c
-            147213743f000000000000000000007c14a6010000ab0100000000000000
-            0064476b0200000000720b64297c136b02000000007203645e7d146e0264
-            5f7d147c157213743f000000000000000000007c15a6010000ab01000000
-            000000000064476b0200000000720264607d157c016a2b00000000000000
-            0072357c016a2b0000000000000000a02200000000000000000000000000
-            00000000000000a6000000ab0000000000000000007d047c016a2b000000
-            0000000000a0220000000000000000000000000000000000000000a60000
-            00ab0000000000000000007d0564617d076e907c016a2c00000000000000
-            0072507c016a2c0000000000000000a02200000000000000000000000000
-            00000000000000a6000000ab0000000000000000007d047c016a2c000000
-            0000000000a0220000000000000000000000000000000000000000a60000
-            00ab0000000000000000007d0564627c016a2c0000000000000000a02200
+            00733b743f000000000000000000007c027c119b00644c9d02a6020000ab
+            02000000000000000072097c029b0064557c119b00644c9d047d116e3d74
+            1f000000000000000000006456a6010000ab010000000000000000010074
+            27000000000000000000006457a6010000ab01000000000000000001006e
+            1e7441000000000000000000007c11a6010000ab0100000000000000007d
+            0d7443000000000000000000007c11a6010000ab0100000000000000007d
+            06741700000000000000000000a6000000ab0000000000000000007d127c
+            0972137445000000000000000000007c09a6010000ab0100000000000000
+            00644d6b020000000072147c1264586b0200000000720364597d096e0b7c
+            12641f6b0200000000720364317d096e0264307d097c0a72137445000000
+            000000000000007c0aa6010000ab010000000000000000644d6b02000000
+            0072887c0964596b02000000007203645a7d0a6e7f7c0964316b02000000
+            007203645b7d0a6e767c0964306b02000000007270740100000000000000
+            0000006a230000000000000000645ca6010000ab0100000000000000007d
+            137c13a0240000000000000000000000000000000000000000a6000000ab
+            000000000000000000a02500000000000000000000000000000000000000
+            00a6000000ab0000000000000000007d0a7c0aa026000000000000000000
+            0000000000000000000000645da6010000ab010000000000000000645e6b
+            0400000000721d7c0a64007c0aa027000000000000000000000000000000
+            0000000000645da6010000ab010000000000000000850219000000000000
+            0000007d0a7c016a280000000000000000645f6b020000000072867c1264
+            586b0200000000722b7c0ba0290000000000000000000000000000000000
+            0000006460a6010000ab01000000000000000001007c0ba0290000000000
+            0000000000000000000000000000006461a6010000ab0100000000000000
+            0001006ec17c0ba029000000000000000000000000000000000000000064
+            60a6010000ab01000000000000000001007c0ba029000000000000000000
+            00000000000000000000006461a6010000ab01000000000000000001007c
+            0ba02900000000000000000000000000000000000000006462a6010000ab
+            01000000000000000001007c0ba029000000000000000000000000000000
+            00000000006463a6010000ab01000000000000000001006e6c7c016a2800
+            0000000000000064246b020000000072477c1264586b0200000000722b7c
+            0ba02900000000000000000000000000000000000000006460a6010000ab
+            01000000000000000001007c0ba029000000000000000000000000000000
+            00000000006461a6010000ab01000000000000000001006e307c0ba02900
+            000000000000000000000000000000000000006461a6010000ab01000000
+            000000000001006e1a7c0ba0290000000000000000000000000000000000
+            0000007c016a280000000000000000a6010000ab01000000000000000001
+            007c016a2a0000000000000000645f6b020000000072557c0ca029000000
+            00000000000000000000000000000000006460a6010000ab010000000000
+            00000001007c0ca029000000000000000000000000000000000000000064
+            61a6010000ab01000000000000000001007c0ca029000000000000000000
+            00000000000000000000006462a6010000ab01000000000000000001007c
+            0ca02900000000000000000000000000000000000000006463a6010000ab
+            01000000000000000001006e507c016a2a000000000000000064246b0200
+            000000722b7c0ca029000000000000000000000000000000000000000064
+            62a6010000ab01000000000000000001007c0ca029000000000000000000
+            00000000000000000000006463a6010000ab01000000000000000001006e
+            1a7c0ba02900000000000000000000000000000000000000007c016a2800
+            00000000000000a6010000ab01000000000000000001007c016a2b000000
+            00000000007d147c016a2c00000000000000007d157c016a2d0000000000
+            0000007d167c1472137445000000000000000000007c14a6010000ab0100
+            00000000000000644d6b0200000000720264307d147c1572137445000000
+            000000000000007c15a6010000ab010000000000000000644d6b02000000
+            00720b64307c146b0200000000720364647d156e0264657d157c16721374
+            45000000000000000000007c16a6010000ab010000000000000000644d6b
+            0200000000720264667d167c016a2e000000000000000072357c016a2e00
+            00000000000000a0250000000000000000000000000000000000000000a6
+            000000ab0000000000000000007d057c016a2e0000000000000000a02500
             00000000000000000000000000000000000000a6000000ab000000000000
-            0000009b0064639d037d066e397c016a2d000000000000000072327c016a
-            2d0000000000000000a02200000000000000000000000000000000000000
-            00a6000000ab0000000000000000007d047c016a2d0000000000000000a0
-            220000000000000000000000000000000000000000a6000000ab00000000
-            00000000007d077c016a2e000000000000000072077c016a2e0000000000
-            0000007d05743f000000000000000000007c05a6010000ab010000000000
-            00000064476b020000000072b77c0f7c016a050000000000000000190000
-            000000000000007d167c167310745f000000000000000000006464a60100
-            00ab01000000000000000001006e98740f000000000000000000006a3000
-            0000000000000064657c169b0064667c016a2d00000000000000009b0064
-            679d05a6010000ab0100000000000000000100740f000000000000000000
-            006a3100000000000000006468a6010000ab010000000000000000010074
-            0f000000000000000000006a2000000000000000006469a6010000ab0100
-            00000000000000a0210000000000000000000000000000000000000000a6
-            000000ab0000000000000000007d057c05a0320000000000000000000000
-            000000000000000000646a643ca6020000ab0200000000000000007d0574
-            0f000000000000000000006a310000000000000000646ba6010000ab0100
-            000000000000000100740f000000000000000000006a3000000000000000
-            00646ca6010000ab01000000000000000001007c016a3300000000000000
-            0072077c016a3300000000000000007d077c016a34000000000000000072
-            0d7c0564577c016a3400000000000000009b009d027a0d00007d057c016a
-            35000000000000000072687c016a350000000000000000a0360000000000
-            000000000000000000000000000000646da6010000ab0100000000000000
-            007d177c1744005d4b7d187c18a036000000000000000000000000000000
-            0000000000646ea6010000ab0100000000000000007d19743f0000000000
-            00000000007c19a6010000ab010000000000000000646f6b020000000072
-            21740f000000000000000000006a3700000000000000007c196447190000
-            000000000000007c19645819000000000000000000a6020000ab02000000
-            000000000001008c4c7427000000000000000000006a3800000000000000
-            007c107c0da6020000ab0200000000000000000100747300000000000000
-            0000007c0d64707c06a6030000ab0300000000000000000100743f000000
-            000000000000007c06a6010000ab01000000000000000064476b04000000
-            0072127473000000000000000000007c0d6471643ca6030000ab03000000
-            000000000001006e147473000000000000000000007c0d647164727c049b
-            009d02a6030000ab0300000000000000000100743f000000000000000000
-            007c05a6010000ab01000000000000000064476b04000000007211747300
-            0000000000000000007c0d64737c05a6030000ab03000000000000000001
-            007c016a3a0000000000000000731f7477000000000000000000007c0d7c
-            077c087c097c0a7c016a3c00000000000000007c016a3d00000000000000
-            00a6070000ab07000000000000000001007c016a3e000000000000000072
-            5c7c13a0220000000000000000000000000000000000000000a6000000ab
-            0000000000000000007d137c14a022000000000000000000000000000000
-            0000000000a6000000ab0000000000000000007d147c15a0220000000000
-            000000000000000000000000000000a6000000ab0000000000000000007d
-            15747f000000000000000000007c0d7c077c137c147c0b7c157c016a3c00
-            000000000000007c016a3d0000000000000000a6080000ab080000000000
-            0000000100740700000000000000000000a6000000ab0000000000000000
-            0064186b020000000072267c016a400000000000000000721f7483000000
-            000000000000007c0d7c077c087c097c0a7c016a3c00000000000000007c
-            016a3d0000000000000000a6070000ab07000000000000000001007c016a
-            4200000000000000007220740f000000000000000000006a300000000000
-            00000064747c0c9b0064757c059b0064767c079b0064779d07a6010000ab
-            01000000000000000001006400530064005300
+            0000007d0664677d086e907c016a2f000000000000000072507c016a2f00
+            00000000000000a0250000000000000000000000000000000000000000a6
+            000000ab0000000000000000007d057c016a2f0000000000000000a02500
+            00000000000000000000000000000000000000a6000000ab000000000000
+            0000007d0664687c016a2f0000000000000000a025000000000000000000
+            0000000000000000000000a6000000ab0000000000000000009b0064699d
+            037d076e397c016a30000000000000000072327c016a3000000000000000
+            00a0250000000000000000000000000000000000000000a6000000ab0000
+            000000000000007d057c016a300000000000000000a02500000000000000
+            00000000000000000000000000a6000000ab0000000000000000007d087c
+            016a31000000000000000072077c016a3100000000000000007d06744500
+            0000000000000000007c06a6010000ab010000000000000000644d6b0200
+            00000072b77c107c016a0e0000000000000000190000000000000000007d
+            177c177310746500000000000000000000646aa6010000ab010000000000
+            00000001006e987401000000000000000000006a33000000000000000064
+            6b7c179b00646c7c016a3000000000000000009b00646d9d05a6010000ab
+            01000000000000000001007401000000000000000000006a340000000000
+            000000646ea6010000ab0100000000000000000100740100000000000000
+            0000006a230000000000000000646fa6010000ab010000000000000000a0
+            240000000000000000000000000000000000000000a6000000ab00000000
+            00000000007d067c06a03500000000000000000000000000000000000000
+            0064706443a6020000ab0200000000000000007d06740100000000000000
+            0000006a3400000000000000006471a6010000ab01000000000000000001
+            007401000000000000000000006a3300000000000000006472a6010000ab
+            01000000000000000001007c016a36000000000000000072077c016a3600
+            000000000000007d087c016a370000000000000000720d7c06645d7c016a
+            3700000000000000009b009d027a0d00007d067c016a3800000000000000
+            0072687c016a380000000000000000a03900000000000000000000000000
+            000000000000006473a6010000ab0100000000000000007d187c1844005d
+            4b7d197c19a03900000000000000000000000000000000000000006474a6
+            010000ab0100000000000000007d1a7445000000000000000000007c1aa6
+            010000ab01000000000000000064756b0200000000722174010000000000
+            00000000006a3a00000000000000007c1a644d190000000000000000007c
+            1a645e19000000000000000000a6020000ab02000000000000000001008c
+            4c7409000000000000000000006a3b00000000000000007c117c0ea60200
+            00ab02000000000000000001007479000000000000000000007c0e64767c
+            07a6030000ab03000000000000000001007445000000000000000000007c
+            07a6010000ab010000000000000000644d6b040000000072127479000000
+            000000000000007c0e64776443a6030000ab03000000000000000001006e
+            147479000000000000000000007c0e647764787c059b009d02a6030000ab
+            03000000000000000001007445000000000000000000007c06a6010000ab
+            010000000000000000644d6b040000000072117479000000000000000000
+            007c0e64797c06a6030000ab03000000000000000001007c016a3d000000
+            0000000000731f747d000000000000000000007c0e7c087c097c0a7c0b7c
+            016a3f00000000000000007c016a400000000000000000a6070000ab0700
+            0000000000000001007c016a410000000000000000725c7c14a025000000
+            0000000000000000000000000000000000a6000000ab0000000000000000
+            007d147c15a0250000000000000000000000000000000000000000a60000
+            00ab0000000000000000007d157c16a02500000000000000000000000000
+            00000000000000a6000000ab0000000000000000007d1674850000000000
+            00000000007c0e7c087c147c157c0c7c167c016a3f00000000000000007c
+            016a400000000000000000a6080000ab0800000000000000000100741700
+            000000000000000000a6000000ab000000000000000000641f6b02000000
+            0072267c016a430000000000000000721f7489000000000000000000007c
+            0e7c087c097c0a7c0b7c016a3f00000000000000007c016a400000000000
+            000000a6070000ab07000000000000000001007c016a4500000000000000
+            0072207401000000000000000000006a330000000000000000647a7c0d9b
+            0064557c069b00647b7c089b00647c9d07a6010000ab0100000000000000
+            0001006400530064005300
          107           0 RESUME                   0
          
-         108           2 LOAD_GLOBAL              1 (NULL + argparse)
-                      14 LOAD_ATTR                1 (ArgumentParser)
-         
-         109          24 LOAD_CONST               1 ('Generate project files of MaxME based platform etc.')
-         
-         108          26 KW_NAMES                 2
-                      28 PRECALL                  1
-                      32 CALL                     1
-                      42 STORE_FAST               0 (parser)
-         
-         111          44 LOAD_FAST                0 (parser)
-                      46 LOAD_METHOD              2 (add_argument)
-                      68 LOAD_CONST               3 ('target')
-                      70 LOAD_CONST               4 ("the target project name.special an predefined project name or an 'conanfile.py.in'")
-                      72 KW_NAMES                 5
-                      74 PRECALL                  2
-                      78 CALL                     2
-                      88 POP_TOP
-         
-         112          90 LOAD_FAST                0 (parser)
-                      92 LOAD_METHOD              2 (add_argument)
-                     114 LOAD_CONST               6 ('-t')
-                     116 LOAD_CONST               7 ('--tag')
-                     118 LOAD_CONST               8 ("the git tag of target, if specified,  use 'stable' conan channel and use 'tag' as version")
-                     120 KW_NAMES                 5
-                     122 PRECALL                  3
-                     126 CALL                     3
-                     136 POP_TOP
-         
-         113         138 LOAD_FAST                0 (parser)
-                     140 LOAD_METHOD              2 (add_argument)
-                     162 LOAD_CONST               9 ('-b')
-                     164 LOAD_CONST              10 ('--branch')
-                     166 LOAD_CONST              11 ("the git branch of target, if specified, use 'branch' as conan channel")
-                     168 KW_NAMES                 5
-                     170 PRECALL                  3
-                     174 CALL                     3
-                     184 POP_TOP
-         
-         114         186 LOAD_FAST                0 (parser)
-                     188 LOAD_METHOD              2 (add_argument)
-                     210 LOAD_CONST              12 ('-r')
-                     212 LOAD_CONST              13 ('--ref')
-                     214 LOAD_CONST              14 ("the git ref identify of target, if specified, use 'dev' as conan chanel and use 'ref' as version")
-                     216 KW_NAMES                 5
-                     218 PRECALL                  3
-                     222 CALL                     3
-                     232 POP_TOP
-         
-         115         234 LOAD_FAST                0 (parser)
-                     236 LOAD_METHOD              2 (add_argument)
-                     258 LOAD_CONST              15 ('-v')
-                     260 LOAD_CONST              16 ('--version')
-                     262 LOAD_CONST              17 ('the conan package version, if specified will override default.')
-                     264 KW_NAMES                 5
-                     266 PRECALL                  3
-                     270 CALL                     3
-                     280 POP_TOP
-         
-         116         282 LOAD_FAST                0 (parser)
-                     284 LOAD_METHOD              2 (add_argument)
-                     306 LOAD_CONST              18 ('--without_native')
-                     308 LOAD_CONST              19 ('store_true')
-                     310 LOAD_CONST              20 ('not build native package')
-                     312 KW_NAMES                21
-                     314 PRECALL                  3
-                     318 CALL                     3
-                     328 POP_TOP
-         
-         117         330 LOAD_FAST                0 (parser)
-                     332 LOAD_METHOD              2 (add_argument)
-                     354 LOAD_CONST              22 ('--android')
-                     356 LOAD_CONST              19 ('store_true')
-                     358 LOAD_CONST              23 ('build android package.')
-                     360 KW_NAMES                21
-                     362 PRECALL                  3
-                     366 CALL                     3
-                     376 POP_TOP
-         
-         118         378 LOAD_GLOBAL              7 (NULL + get_os_name)
-                     390 PRECALL                  0
-                     394 CALL                     0
-                     404 LOAD_CONST              24 ('Macos')
-                     406 COMPARE_OP               2 (==)
-                     412 POP_JUMP_FORWARD_IF_FALSE    24 (to 462)
-         
-         119         414 LOAD_FAST                0 (parser)
-                     416 LOAD_METHOD              2 (add_argument)
-                     438 LOAD_CONST              25 ('--ios')
-                     440 LOAD_CONST              19 ('store_true')
-                     442 LOAD_CONST              26 ('build ios package.')
-                     444 KW_NAMES                21
-                     446 PRECALL                  3
-                     450 CALL                     3
-                     460 POP_TOP
-         
-         120     >>  462 LOAD_FAST                0 (parser)
-                     464 LOAD_METHOD              2 (add_argument)
-                     486 LOAD_CONST              27 ('--arch')
-                     488 BUILD_LIST               0
-                     490 LOAD_CONST              28 (('x86', 'x86_64', 'armv7', 'armv8', 'all', 'default'))
-                     492 LIST_EXTEND              1
-                     494 LOAD_CONST              29 ('default')
-                     496 LOAD_CONST              30 ('target arch')
-                     498 KW_NAMES                31
-                     500 PRECALL                  4
-                     504 CALL                     4
-                     514 POP_TOP
-         
-         121         516 LOAD_FAST                0 (parser)
-                     518 LOAD_METHOD              2 (add_argument)
-                     540 LOAD_CONST              32 ('--android_arch')
-                     542 BUILD_LIST               0
-                     544 LOAD_CONST              28 (('x86', 'x86_64', 'armv7', 'armv8', 'all', 'default'))
-                     546 LIST_EXTEND              1
-                     548 LOAD_CONST              29 ('default')
-                     550 LOAD_CONST              33 ('android target arch')
-                     552 KW_NAMES                31
-                     554 PRECALL                  4
-                     558 CALL                     4
-                     568 POP_TOP
-         
-         122         570 LOAD_FAST                0 (parser)
-                     572 LOAD_METHOD              2 (add_argument)
-                     594 LOAD_CONST              34 ('--debug')
-                     596 LOAD_CONST              19 ('store_true')
-                     598 LOAD_CONST              35 ('build debug package.')
-                     600 KW_NAMES                21
-                     602 PRECALL                  3
-                     606 CALL                     3
-                     616 POP_TOP
-         
-         123         618 LOAD_FAST                0 (parser)
-                     620 LOAD_METHOD              2 (add_argument)
-                     642 LOAD_CONST              36 ('--compiler')
-                     644 BUILD_LIST               0
-                     646 LOAD_CONST              37 (('gcc', 'clang', 'apple-clang', 'Visual Studio'))
-                     648 LIST_EXTEND              1
-                     650 LOAD_CONST              38 ('the compiler')
-                     652 KW_NAMES                39
-                     654 PRECALL                  3
-                     658 CALL                     3
-                     668 POP_TOP
-         
-         124         670 LOAD_FAST                0 (parser)
-                     672 LOAD_METHOD              2 (add_argument)
-                     694 LOAD_CONST              40 ('--android_compiler')
-                     696 LOAD_CONST              41 ('gcc')
-                     698 LOAD_CONST              42 ('clang')
-                     700 BUILD_LIST               2
-                     702 LOAD_CONST              43 ('the android NDK compiler')
-                     704 KW_NAMES                39
-                     706 PRECALL                  3
-                     710 CALL                     3
-                     720 POP_TOP
-         
-         125         722 LOAD_FAST                0 (parser)
-                     724 LOAD_METHOD              2 (add_argument)
-                     746 LOAD_CONST              44 ('--android_compiler_version')
-                     748 LOAD_CONST              45 ('the android compiler version')
-                     750 KW_NAMES                 5
-                     752 PRECALL                  2
-                     756 CALL                     2
-                     766 POP_TOP
-         
-         126         768 LOAD_FAST                0 (parser)
-                     770 LOAD_METHOD              2 (add_argument)
-                     792 LOAD_CONST              46 ('--android_api_level')
-                     794 LOAD_CONST              47 ('the android API level')
-                     796 KW_NAMES                 5
-                     798 PRECALL                  2
-                     802 CALL                     2
-                     812 POP_TOP
-         
-         127         814 LOAD_FAST                0 (parser)
-                     816 LOAD_METHOD              2 (add_argument)
-                     838 LOAD_CONST              48 ('--compiler_version')
-                     840 LOAD_CONST              49 ('the version of compiler')
-                     842 KW_NAMES                 5
-                     844 PRECALL                  2
-                     848 CALL                     2
-                     858 POP_TOP
-         
-         128         860 LOAD_FAST                0 (parser)
-                     862 LOAD_METHOD              2 (add_argument)
-                     884 LOAD_CONST              50 ('--upload')
-                     886 LOAD_CONST              19 ('store_true')
-                     888 LOAD_CONST              51 ('upload pacakge to conan recip')
-                     890 LOAD_CONST              52 (False)
-                     892 KW_NAMES                53
-                     894 PRECALL                  4
-                     898 CALL                     4
-                     908 POP_TOP
-         
-         129         910 LOAD_FAST                0 (parser)
-                     912 LOAD_METHOD              2 (add_argument)
-                     934 LOAD_CONST              54 ('-c')
-                     936 LOAD_CONST              55 ('--chn')
-                     938 LOAD_CONST              56 ('specify conan channel, will override default rule.')
-                     940 KW_NAMES                 5
-                     942 PRECALL                  3
-                     946 CALL                     3
-                     956 POP_TOP
-         
-         130         958 LOAD_FAST                0 (parser)
-                     960 LOAD_METHOD              2 (add_argument)
-                     982 LOAD_CONST              57 ('-s')
-                     984 LOAD_CONST              58 ('--settings')
-                     986 LOAD_CONST              59 ('specify additional conan settings.')
-                     988 LOAD_CONST              60 ('')
-                     990 KW_NAMES                61
-                     992 PRECALL                  4
-                     996 CALL                     4
-                    1006 POP_TOP
-         
-         131        1008 LOAD_FAST                0 (parser)
-                    1010 LOAD_METHOD              2 (add_argument)
-                    1032 LOAD_CONST              62 ('-e')
-                    1034 LOAD_CONST              63 ('--env')
-                    1036 LOAD_CONST              64 ('specify addtional envrioment variables.')
-                    1038 KW_NAMES                 5
-                    1040 PRECALL                  3
-                    1044 CALL                     3
-                    1054 POP_TOP
-         
-         132        1056 LOAD_FAST                0 (parser)
-                    1058 LOAD_METHOD              2 (add_argument)
-                    1080 LOAD_CONST              65 ('--build_version')
-                    1082 LOAD_CONST              66 ('append building number to version, avalible with CI system.')
-                    1084 KW_NAMES                 5
-                    1086 PRECALL                  2
-                    1090 CALL                     2
-                    1100 POP_TOP
-         
-         134        1102 LOAD_FAST                0 (parser)
-                    1104 LOAD_METHOD              4 (parse_args)
-                    1126 PRECALL                  0
-                    1130 CALL                     0
-                    1140 STORE_FAST               1 (args)
-         
-         136        1142 LOAD_FAST                1 (args)
-                    1144 LOAD_ATTR                5 (target)
-                    1154 LOAD_CONST              67 ('list')
-                    1156 COMPARE_OP               2 (==)
-                    1162 POP_JUMP_FORWARD_IF_FALSE   147 (to 1458)
-         
-         137        1164 LOAD_GLOBAL             13 (NULL + print)
-                    1176 LOAD_CONST              68 ('inside pacakges:\n')
-                    1178 PRECALL                  1
-                    1182 CALL                     1
-                    1192 POP_TOP
-         
-         138        1194 LOAD_GLOBAL             15 (NULL + os)
-                    1206 LOAD_ATTR                8 (listdir)
-                    1216 LOAD_GLOBAL             14 (os)
-                    1228 LOAD_ATTR                9 (path)
-                    1238 LOAD_METHOD             10 (dirname)
-                    1260 LOAD_GLOBAL             22 (__file__)
-                    1272 PRECALL                  1
-                    1276 CALL                     1
-                    1286 FORMAT_VALUE             0
-                    1288 LOAD_CONST              69 ('/targets')
-                    1290 BUILD_STRING             2
-                    1292 PRECALL                  1
-                    1296 CALL                     1
-                    1306 STORE_FAST               2 (refs)
-         
-         139        1308 LOAD_FAST                2 (refs)
-                    1310 GET_ITER
-                 >> 1312 FOR_ITER                57 (to 1428)
-                    1314 STORE_FAST               3 (ref)
-         
-         140        1316 LOAD_FAST                3 (ref)
-                    1318 LOAD_METHOD             12 (endswith)
-                    1340 LOAD_CONST              70 ('.py.in')
-                    1342 PRECALL                  1
-                    1346 CALL                     1
-                    1356 POP_JUMP_FORWARD_IF_FALSE    34 (to 1426)
-         
-         141        1358 LOAD_GLOBAL             13 (NULL + print)
-                    1370 LOAD_FAST                3 (ref)
-                    1372 LOAD_METHOD             13 (removesuffix)
-                    1394 LOAD_CONST              70 ('.py.in')
-                    1396 PRECALL                  1
-                    1400 CALL                     1
-                    1410 PRECALL                  1
-                    1414 CALL                     1
-                    1424 POP_TOP
-                 >> 1426 JUMP_BACKWARD           58 (to 1312)
-         
-         142     >> 1428 LOAD_GLOBAL             29 (NULL + exit)
-                    1440 LOAD_CONST              71 (0)
-                    1442 PRECALL                  1
-                    1446 CALL                     1
+         108           2 LOAD_GLOBAL              0 (os)
+                      14 LOAD_ATTR                1 (path)
+                      24 LOAD_METHOD              2 (exists)
+                      46 LOAD_GLOBAL              0 (os)
+                      58 LOAD_ATTR                1 (path)
+                      68 LOAD_METHOD              3 (expanduser)
+                      90 LOAD_CONST               1 ('~')
+                      92 PRECALL                  1
+                      96 CALL                     1
+                     106 FORMAT_VALUE             0
+                     108 LOAD_CONST               2 ('/.cpptools/conan_targets')
+                     110 BUILD_STRING             2
+                     112 PRECALL                  1
+                     116 CALL                     1
+                     126 POP_JUMP_FORWARD_IF_TRUE    90 (to 308)
+         
+         109         128 LOAD_GLOBAL              9 (NULL + shutil)
+                     140 LOAD_ATTR                5 (copytree)
+                     150 LOAD_GLOBAL              0 (os)
+                     162 LOAD_ATTR                1 (path)
+                     172 LOAD_METHOD              6 (dirname)
+                     194 LOAD_GLOBAL             14 (__file__)
+                     206 PRECALL                  1
+                     210 CALL                     1
+                     220 FORMAT_VALUE             0
+                     222 LOAD_CONST               3 ('/targets')
+                     224 BUILD_STRING             2
+                     226 LOAD_GLOBAL              0 (os)
+                     238 LOAD_ATTR                1 (path)
+                     248 LOAD_METHOD              3 (expanduser)
+                     270 LOAD_CONST               1 ('~')
+                     272 PRECALL                  1
+                     276 CALL                     1
+                     286 FORMAT_VALUE             0
+                     288 LOAD_CONST               2 ('/.cpptools/conan_targets')
+                     290 BUILD_STRING             2
+                     292 PRECALL                  2
+                     296 CALL                     2
+                     306 POP_TOP
+         
+         111     >>  308 LOAD_GLOBAL             17 (NULL + argparse)
+                     320 LOAD_ATTR                9 (ArgumentParser)
+         
+         112         330 LOAD_CONST               4 ('Generate project files of MaxME based platform etc.')
+         
+         111         332 KW_NAMES                 5
+                     334 PRECALL                  1
+                     338 CALL                     1
+                     348 STORE_FAST               0 (parser)
+         
+         114         350 LOAD_FAST                0 (parser)
+                     352 LOAD_METHOD             10 (add_argument)
+                     374 LOAD_CONST               6 ('target')
+                     376 LOAD_CONST               7 ("the target project name.special an predefined project name or an 'conanfile.py.in'")
+                     378 KW_NAMES                 8
+                     380 PRECALL                  2
+                     384 CALL                     2
+                     394 POP_TOP
+         
+         115         396 LOAD_FAST                0 (parser)
+                     398 LOAD_METHOD             10 (add_argument)
+                     420 LOAD_CONST               9 ('-t')
+                     422 LOAD_CONST              10 ('--tag')
+                     424 LOAD_CONST              11 ("the git tag of target, if specified,  use 'stable' conan channel and use 'tag' as version")
+                     426 KW_NAMES                 8
+                     428 PRECALL                  3
+                     432 CALL                     3
+                     442 POP_TOP
+         
+         116         444 LOAD_FAST                0 (parser)
+                     446 LOAD_METHOD             10 (add_argument)
+                     468 LOAD_CONST              12 ('-b')
+                     470 LOAD_CONST              13 ('--branch')
+                     472 LOAD_CONST              14 ("the git branch of target, if specified, use 'branch' as conan channel")
+                     474 KW_NAMES                 8
+                     476 PRECALL                  3
+                     480 CALL                     3
+                     490 POP_TOP
+         
+         117         492 LOAD_FAST                0 (parser)
+                     494 LOAD_METHOD             10 (add_argument)
+                     516 LOAD_CONST              15 ('-r')
+                     518 LOAD_CONST              16 ('--ref')
+                     520 LOAD_CONST              17 ("the git ref identify of target, if specified, use 'dev' as conan chanel and use 'ref' as version")
+                     522 KW_NAMES                 8
+                     524 PRECALL                  3
+                     528 CALL                     3
+                     538 POP_TOP
+         
+         118         540 LOAD_FAST                0 (parser)
+                     542 LOAD_METHOD             10 (add_argument)
+                     564 LOAD_CONST              18 ('-v')
+                     566 LOAD_CONST              19 ('--version')
+                     568 LOAD_CONST              20 ('the conan package version, if specified will override default.')
+                     570 KW_NAMES                 8
+                     572 PRECALL                  3
+                     576 CALL                     3
+                     586 POP_TOP
+         
+         119         588 LOAD_FAST                0 (parser)
+                     590 LOAD_METHOD             10 (add_argument)
+                     612 LOAD_CONST              21 ('-d')
+                     614 LOAD_CONST              22 ('--default')
+                     616 LOAD_CONST              23 ('force use default rule to build package. if not set this option, we first use "${user_dir}/.cpptools/conan_targets" as conanbuild configurations.')
+                     618 LOAD_CONST              24 ('store_true')
+                     620 KW_NAMES                25
+                     622 PRECALL                  4
+                     626 CALL                     4
+                     636 POP_TOP
+         
+         120         638 LOAD_FAST                0 (parser)
+                     640 LOAD_METHOD             10 (add_argument)
+                     662 LOAD_CONST              26 ('--without_native')
+                     664 LOAD_CONST              24 ('store_true')
+                     666 LOAD_CONST              27 ('not build native package')
+                     668 KW_NAMES                28
+                     670 PRECALL                  3
+                     674 CALL                     3
+                     684 POP_TOP
+         
+         121         686 LOAD_FAST                0 (parser)
+                     688 LOAD_METHOD             10 (add_argument)
+                     710 LOAD_CONST              29 ('--android')
+                     712 LOAD_CONST              24 ('store_true')
+                     714 LOAD_CONST              30 ('build android package.')
+                     716 KW_NAMES                28
+                     718 PRECALL                  3
+                     722 CALL                     3
+                     732 POP_TOP
+         
+         122         734 LOAD_GLOBAL             23 (NULL + get_os_name)
+                     746 PRECALL                  0
+                     750 CALL                     0
+                     760 LOAD_CONST              31 ('Macos')
+                     762 COMPARE_OP               2 (==)
+                     768 POP_JUMP_FORWARD_IF_FALSE    24 (to 818)
+         
+         123         770 LOAD_FAST                0 (parser)
+                     772 LOAD_METHOD             10 (add_argument)
+                     794 LOAD_CONST              32 ('--ios')
+                     796 LOAD_CONST              24 ('store_true')
+                     798 LOAD_CONST              33 ('build ios package.')
+                     800 KW_NAMES                28
+                     802 PRECALL                  3
+                     806 CALL                     3
+                     816 POP_TOP
+         
+         124     >>  818 LOAD_FAST                0 (parser)
+                     820 LOAD_METHOD             10 (add_argument)
+                     842 LOAD_CONST              34 ('--arch')
+                     844 BUILD_LIST               0
+                     846 LOAD_CONST              35 (('x86', 'x86_64', 'armv7', 'armv8', 'all', 'default'))
+                     848 LIST_EXTEND              1
+                     850 LOAD_CONST              36 ('default')
+                     852 LOAD_CONST              37 ('target arch')
+                     854 KW_NAMES                38
+                     856 PRECALL                  4
+                     860 CALL                     4
+                     870 POP_TOP
+         
+         125         872 LOAD_FAST                0 (parser)
+                     874 LOAD_METHOD             10 (add_argument)
+                     896 LOAD_CONST              39 ('--android_arch')
+                     898 BUILD_LIST               0
+                     900 LOAD_CONST              35 (('x86', 'x86_64', 'armv7', 'armv8', 'all', 'default'))
+                     902 LIST_EXTEND              1
+                     904 LOAD_CONST              36 ('default')
+                     906 LOAD_CONST              40 ('android target arch')
+                     908 KW_NAMES                38
+                     910 PRECALL                  4
+                     914 CALL                     4
+                     924 POP_TOP
+         
+         126         926 LOAD_FAST                0 (parser)
+                     928 LOAD_METHOD             10 (add_argument)
+                     950 LOAD_CONST              41 ('--debug')
+                     952 LOAD_CONST              24 ('store_true')
+                     954 LOAD_CONST              42 ('build debug package.')
+                     956 KW_NAMES                28
+                     958 PRECALL                  3
+                     962 CALL                     3
+                     972 POP_TOP
+         
+         127         974 LOAD_FAST                0 (parser)
+                     976 LOAD_METHOD             10 (add_argument)
+                     998 LOAD_CONST              43 ('--compiler')
+                    1000 BUILD_LIST               0
+                    1002 LOAD_CONST              44 (('gcc', 'clang', 'apple-clang', 'Visual Studio'))
+                    1004 LIST_EXTEND              1
+                    1006 LOAD_CONST              45 ('the compiler')
+                    1008 KW_NAMES                46
+                    1010 PRECALL                  3
+                    1014 CALL                     3
+                    1024 POP_TOP
+         
+         128        1026 LOAD_FAST                0 (parser)
+                    1028 LOAD_METHOD             10 (add_argument)
+                    1050 LOAD_CONST              47 ('--android_compiler')
+                    1052 LOAD_CONST              48 ('gcc')
+                    1054 LOAD_CONST              49 ('clang')
+                    1056 BUILD_LIST               2
+                    1058 LOAD_CONST              50 ('the android NDK compiler')
+                    1060 KW_NAMES                46
+                    1062 PRECALL                  3
+                    1066 CALL                     3
+                    1076 POP_TOP
+         
+         129        1078 LOAD_FAST                0 (parser)
+                    1080 LOAD_METHOD             10 (add_argument)
+                    1102 LOAD_CONST              51 ('--android_compiler_version')
+                    1104 LOAD_CONST              52 ('the android compiler version')
+                    1106 KW_NAMES                 8
+                    1108 PRECALL                  2
+                    1112 CALL                     2
+                    1122 POP_TOP
+         
+         130        1124 LOAD_FAST                0 (parser)
+                    1126 LOAD_METHOD             10 (add_argument)
+                    1148 LOAD_CONST              53 ('--android_api_level')
+                    1150 LOAD_CONST              54 ('the android API level')
+                    1152 KW_NAMES                 8
+                    1154 PRECALL                  2
+                    1158 CALL                     2
+                    1168 POP_TOP
+         
+         131        1170 LOAD_FAST                0 (parser)
+                    1172 LOAD_METHOD             10 (add_argument)
+                    1194 LOAD_CONST              55 ('--compiler_version')
+                    1196 LOAD_CONST              56 ('the version of compiler')
+                    1198 KW_NAMES                 8
+                    1200 PRECALL                  2
+                    1204 CALL                     2
+                    1214 POP_TOP
+         
+         132        1216 LOAD_FAST                0 (parser)
+                    1218 LOAD_METHOD             10 (add_argument)
+                    1240 LOAD_CONST              57 ('--upload')
+                    1242 LOAD_CONST              24 ('store_true')
+                    1244 LOAD_CONST              58 ('upload pacakge to conan recip')
+                    1246 LOAD_CONST              59 (False)
+                    1248 KW_NAMES                60
+                    1250 PRECALL                  4
+                    1254 CALL                     4
+                    1264 POP_TOP
+         
+         133        1266 LOAD_FAST                0 (parser)
+                    1268 LOAD_METHOD             10 (add_argument)
+                    1290 LOAD_CONST              61 ('-c')
+                    1292 LOAD_CONST              62 ('--chn')
+                    1294 LOAD_CONST              63 ('specify conan channel, will override default rule.')
+                    1296 KW_NAMES                 8
+                    1298 PRECALL                  3
+                    1302 CALL                     3
+                    1312 POP_TOP
+         
+         134        1314 LOAD_FAST                0 (parser)
+                    1316 LOAD_METHOD             10 (add_argument)
+                    1338 LOAD_CONST              64 ('-s')
+                    1340 LOAD_CONST              65 ('--settings')
+                    1342 LOAD_CONST              66 ('specify additional conan settings.')
+                    1344 LOAD_CONST              67 ('')
+                    1346 KW_NAMES                68
+                    1348 PRECALL                  4
+                    1352 CALL                     4
+                    1362 POP_TOP
+         
+         135        1364 LOAD_FAST                0 (parser)
+                    1366 LOAD_METHOD             10 (add_argument)
+                    1388 LOAD_CONST              69 ('-e')
+                    1390 LOAD_CONST              70 ('--env')
+                    1392 LOAD_CONST              71 ('specify addtional envrioment variables.')
+                    1394 KW_NAMES                 8
+                    1396 PRECALL                  3
+                    1400 CALL                     3
+                    1410 POP_TOP
+         
+         136        1412 LOAD_FAST                0 (parser)
+                    1414 LOAD_METHOD             10 (add_argument)
+                    1436 LOAD_CONST              72 ('--build_version')
+                    1438 LOAD_CONST              73 ('append building number to version, avalible with CI system.')
+                    1440 KW_NAMES                 8
+                    1442 PRECALL                  2
+                    1446 CALL                     2
                     1456 POP_TOP
          
-         144     >> 1458 LOAD_CONST              60 ('')
-                    1460 STORE_FAST               4 (git_ref)
-         
-         145        1462 LOAD_CONST              60 ('')
-                    1464 STORE_FAST               5 (version)
-         
-         146        1466 LOAD_CONST              60 ('')
-                    1468 STORE_FAST               6 (git_checkout)
+         138        1458 LOAD_FAST                0 (parser)
+                    1460 LOAD_METHOD             12 (parse_args)
+                    1482 PRECALL                  0
+                    1486 CALL                     0
+                    1496 STORE_FAST               1 (args)
+         
+         139        1498 LOAD_GLOBAL              0 (os)
+                    1510 LOAD_ATTR                1 (path)
+                    1520 LOAD_METHOD              3 (expanduser)
+                    1542 LOAD_CONST               1 ('~')
+                    1544 PRECALL                  1
+                    1548 CALL                     1
+                    1558 FORMAT_VALUE             0
+                    1560 LOAD_CONST               2 ('/.cpptools/conan_targets')
+                    1562 BUILD_STRING             2
+                    1564 STORE_FAST               2 (targets_dir)
+         
+         140        1566 LOAD_FAST                1 (args)
+                    1568 LOAD_ATTR               13 (default)
+                    1578 POP_JUMP_FORWARD_IF_FALSE    39 (to 1658)
+         
+         141        1580 LOAD_GLOBAL              0 (os)
+                    1592 LOAD_ATTR                1 (path)
+                    1602 LOAD_METHOD              6 (dirname)
+                    1624 LOAD_GLOBAL             14 (__file__)
+                    1636 PRECALL                  1
+                    1640 CALL                     1
+                    1650 FORMAT_VALUE             0
+                    1652 LOAD_CONST               3 ('/targets')
+                    1654 BUILD_STRING             2
+                    1656 STORE_FAST               2 (targets_dir)
+         
+         143     >> 1658 LOAD_FAST                1 (args)
+                    1660 LOAD_ATTR               14 (target)
+                    1670 LOAD_CONST              74 ('list')
+                    1672 COMPARE_OP               2 (==)
+                    1678 POP_JUMP_FORWARD_IF_FALSE   110 (to 1900)
+         
+         144        1680 LOAD_GLOBAL             31 (NULL + print)
+                    1692 LOAD_CONST              75 ('inside pacakges:\n')
+                    1694 PRECALL                  1
+                    1698 CALL                     1
+                    1708 POP_TOP
+         
+         145        1710 LOAD_GLOBAL              1 (NULL + os)
+                    1722 LOAD_ATTR               16 (listdir)
+                    1732 LOAD_FAST                2 (targets_dir)
+                    1734 PRECALL                  1
+                    1738 CALL                     1
+                    1748 STORE_FAST               3 (refs)
+         
+         146        1750 LOAD_FAST                3 (refs)
+                    1752 GET_ITER
+                 >> 1754 FOR_ITER                57 (to 1870)
+                    1756 STORE_FAST               4 (ref)
+         
+         147        1758 LOAD_FAST                4 (ref)
+                    1760 LOAD_METHOD             17 (endswith)
+                    1782 LOAD_CONST              76 ('.py.in')
+                    1784 PRECALL                  1
+                    1788 CALL                     1
+                    1798 POP_JUMP_FORWARD_IF_FALSE    34 (to 1868)
+         
+         148        1800 LOAD_GLOBAL             31 (NULL + print)
+                    1812 LOAD_FAST                4 (ref)
+                    1814 LOAD_METHOD             18 (removesuffix)
+                    1836 LOAD_CONST              76 ('.py.in')
+                    1838 PRECALL                  1
+                    1842 CALL                     1
+                    1852 PRECALL                  1
+                    1856 CALL                     1
+                    1866 POP_TOP
+                 >> 1868 JUMP_BACKWARD           58 (to 1754)
+         
+         149     >> 1870 LOAD_GLOBAL             39 (NULL + exit)
+                    1882 LOAD_CONST              77 (0)
+                    1884 PRECALL                  1
+                    1888 CALL                     1
+                    1898 POP_TOP
+         
+         151     >> 1900 LOAD_CONST              67 ('')
+                    1902 STORE_FAST               5 (git_ref)
+         
+         152        1904 LOAD_CONST              67 ('')
+                    1906 STORE_FAST               6 (version)
+         
+         153        1908 LOAD_CONST              67 ('')
+                    1910 STORE_FAST               7 (git_checkout)
+         
+         154        1912 LOAD_CONST              78 ('dev')
+                    1914 STORE_FAST               8 (chn)
+         
+         155        1916 LOAD_FAST                1 (args)
+                    1918 LOAD_ATTR               20 (compiler)
+                    1928 STORE_FAST               9 (compiler)
+         
+         156        1930 LOAD_FAST                1 (args)
+                    1932 LOAD_ATTR               21 (compiler_version)
+                    1942 STORE_FAST              10 (compiler_version)
+         
+         157        1944 BUILD_LIST               0
+                    1946 STORE_FAST              11 (archs)
+         
+         158        1948 BUILD_LIST               0
+                    1950 STORE_FAST              12 (android_archs)
+         
+         159        1952 LOAD_FAST                1 (args)
+                    1954 LOAD_ATTR               14 (target)
+                    1964 STORE_FAST              13 (target)
+         
+         161        1966 LOAD_GLOBAL              0 (os)
+                    1978 LOAD_ATTR                1 (path)
+                    1988 LOAD_METHOD              6 (dirname)
+                    2010 LOAD_GLOBAL             14 (__file__)
+                    2022 PRECALL                  1
+                    2026 CALL                     1
+                    2036 FORMAT_VALUE             0
+                    2038 LOAD_CONST              79 ('/conanfile.py')
+                    2040 BUILD_STRING             2
+                    2042 STORE_FAST              14 (conan_file)
+         
+         162        2044 LOAD_GLOBAL              0 (os)
+                    2056 LOAD_ATTR                1 (path)
+                    2066 LOAD_METHOD              2 (exists)
+                    2088 LOAD_FAST               14 (conan_file)
+                    2090 PRECALL                  1
+                    2094 CALL                     1
+                    2104 POP_JUMP_FORWARD_IF_FALSE    85 (to 2276)
+         
+         163        2106 LOAD_GLOBAL              0 (os)
+                    2118 LOAD_ATTR                1 (path)
+                    2128 LOAD_METHOD             22 (isdir)
+                    2150 LOAD_FAST               14 (conan_file)
+                    2152 PRECALL                  1
+                    2156 CALL                     1
+                    2166 POP_JUMP_FORWARD_IF_FALSE    21 (to 2210)
+         
+         164        2168 LOAD_GLOBAL              9 (NULL + shutil)
+                    2180 LOAD_ATTR               23 (rmtree)
+                    2190 LOAD_FAST               14 (conan_file)
+                    2192 PRECALL                  1
+                    2196 CALL                     1
+                    2206 POP_TOP
+                    2208 JUMP_FORWARD            33 (to 2276)
+         
+         166     >> 2210 LOAD_GLOBAL              1 (NULL + os)
+                    2222 LOAD_ATTR               24 (remove)
+                    2232 LOAD_GLOBAL             51 (NULL + Path)
+                    2244 LOAD_FAST               14 (conan_file)
+                    2246 PRECALL                  1
+                    2250 CALL                     1
+                    2260 PRECALL                  1
+                    2264 CALL                     1
+                    2274 POP_TOP
+         
+         168     >> 2276 LOAD_GLOBAL             53 (NULL + open)
+                    2288 LOAD_FAST                2 (targets_dir)
+                    2290 FORMAT_VALUE             0
+                    2292 LOAD_CONST              80 ('/repos.yaml')
+                    2294 BUILD_STRING             2
+                    2296 LOAD_CONST              81 ('r')
+                    2298 LOAD_CONST              82 ('utf-8')
+                    2300 KW_NAMES                83
+                    2302 PRECALL                  3
+                    2306 CALL                     3
+                    2316 STORE_FAST              15 (reposes_config)
+         
+         169        2318 LOAD_GLOBAL             55 (NULL + yaml)
+                    2330 LOAD_ATTR               28 (load)
+                    2340 LOAD_FAST               15 (reposes_config)
+                    2342 LOAD_GLOBAL             54 (yaml)
+                    2354 LOAD_ATTR               29 (Loader)
+                    2364 KW_NAMES                84
+                    2366 PRECALL                  2
+                    2370 CALL                     2
+                    2380 STORE_FAST              16 (reposes)
+         
+         171        2382 LOAD_FAST                1 (args)
+                    2384 LOAD_ATTR               14 (target)
+                    2394 STORE_FAST              17 (tmpl_file)
+         
+         173        2396 LOAD_GLOBAL             51 (NULL + Path)
+                    2408 LOAD_FAST               17 (tmpl_file)
+                    2410 PRECALL                  1
+                    2414 CALL                     1
+                    2424 LOAD_METHOD             30 (is_file)
+                    2446 PRECALL                  0
+                    2450 CALL                     0
+                    2460 POP_JUMP_FORWARD_IF_TRUE    59 (to 2580)
+         
+         174        2462 LOAD_GLOBAL             63 (NULL + find_target)
+                    2474 LOAD_FAST                2 (targets_dir)
+                    2476 LOAD_FAST               17 (tmpl_file)
+                    2478 FORMAT_VALUE             0
+                    2480 LOAD_CONST              76 ('.py.in')
+                    2482 BUILD_STRING             2
+                    2484 PRECALL                  2
+                    2488 CALL                     2
+                    2498 POP_JUMP_FORWARD_IF_FALSE     9 (to 2518)
+         
+         175        2500 LOAD_FAST                2 (targets_dir)
+                    2502 FORMAT_VALUE             0
+                    2504 LOAD_CONST              85 ('/')
+                    2506 LOAD_FAST               17 (tmpl_file)
+                    2508 FORMAT_VALUE             0
+                    2510 LOAD_CONST              76 ('.py.in')
+                    2512 BUILD_STRING             4
+                    2514 STORE_FAST              17 (tmpl_file)
+                    2516 JUMP_FORWARD            61 (to 2640)
+         
+         177     >> 2518 LOAD_GLOBAL             31 (NULL + print)
+                    2530 LOAD_CONST              86 ('Error: Invalid target.')
+                    2532 PRECALL                  1
+                    2536 CALL                     1
+                    2546 POP_TOP
+         
+         178        2548 LOAD_GLOBAL             39 (NULL + exit)
+                    2560 LOAD_CONST              87 (-1)
+                    2562 PRECALL                  1
+                    2566 CALL                     1
+                    2576 POP_TOP
+                    2578 JUMP_FORWARD            30 (to 2640)
+         
+         180     >> 2580 LOAD_GLOBAL             65 (NULL + read_target_name)
+                    2592 LOAD_FAST               17 (tmpl_file)
+                    2594 PRECALL                  1
+                    2598 CALL                     1
+                    2608 STORE_FAST              13 (target)
+         
+         181        2610 LOAD_GLOBAL             67 (NULL + read_target_version)
+                    2622 LOAD_FAST               17 (tmpl_file)
+                    2624 PRECALL                  1
+                    2628 CALL                     1
+                    2638 STORE_FAST               6 (version)
+         
+         183     >> 2640 LOAD_GLOBAL             23 (NULL + get_os_name)
+                    2652 PRECALL                  0
+                    2656 CALL                     0
+                    2666 STORE_FAST              18 (osName)
+         
+         184        2668 LOAD_FAST                9 (compiler)
+                    2670 POP_JUMP_FORWARD_IF_FALSE    19 (to 2710)
+                    2672 LOAD_GLOBAL             69 (NULL + len)
+                    2684 LOAD_FAST                9 (compiler)
+                    2686 PRECALL                  1
+                    2690 CALL                     1
+                    2700 LOAD_CONST              77 (0)
+                    2702 COMPARE_OP               2 (==)
+                    2708 POP_JUMP_FORWARD_IF_FALSE    20 (to 2750)
+         
+         185     >> 2710 LOAD_FAST               18 (osName)
+                    2712 LOAD_CONST              88 ('Windows')
+                    2714 COMPARE_OP               2 (==)
+                    2720 POP_JUMP_FORWARD_IF_FALSE     3 (to 2728)
+         
+         186        2722 LOAD_CONST              89 ('Visual Studio')
+                    2724 STORE_FAST               9 (compiler)
+                    2726 JUMP_FORWARD            11 (to 2750)
+         
+         187     >> 2728 LOAD_FAST               18 (osName)
+                    2730 LOAD_CONST              31 ('Macos')
+                    2732 COMPARE_OP               2 (==)
+                    2738 POP_JUMP_FORWARD_IF_FALSE     3 (to 2746)
+         
+         188        2740 LOAD_CONST              49 ('clang')
+                    2742 STORE_FAST               9 (compiler)
+                    2744 JUMP_FORWARD             2 (to 2750)
+         
+         190     >> 2746 LOAD_CONST              48 ('gcc')
+                    2748 STORE_FAST               9 (compiler)
+         
+         191     >> 2750 LOAD_FAST               10 (compiler_version)
+                    2752 POP_JUMP_FORWARD_IF_FALSE    19 (to 2792)
+                    2754 LOAD_GLOBAL             69 (NULL + len)
+                    2766 LOAD_FAST               10 (compiler_version)
+                    2768 PRECALL                  1
+                    2772 CALL                     1
+                    2782 LOAD_CONST              77 (0)
+                    2784 COMPARE_OP               2 (==)
+                    2790 POP_JUMP_FORWARD_IF_FALSE   136 (to 3064)
+         
+         192     >> 2792 LOAD_FAST                9 (compiler)
+                    2794 LOAD_CONST              89 ('Visual Studio')
+                    2796 COMPARE_OP               2 (==)
+                    2802 POP_JUMP_FORWARD_IF_FALSE     3 (to 2810)
+         
+         193        2804 LOAD_CONST              90 ('15')
+                    2806 STORE_FAST              10 (compiler_version)
+                    2808 JUMP_FORWARD           127 (to 3064)
+         
+         194     >> 2810 LOAD_FAST                9 (compiler)
+                    2812 LOAD_CONST              49 ('clang')
+                    2814 COMPARE_OP               2 (==)
+                    2820 POP_JUMP_FORWARD_IF_FALSE     3 (to 2828)
+         
+         195        2822 LOAD_CONST              91 ('10')
+                    2824 STORE_FAST              10 (compiler_version)
+                    2826 JUMP_FORWARD           118 (to 3064)
+         
+         196     >> 2828 LOAD_FAST                9 (compiler)
+                    2830 LOAD_CONST              48 ('gcc')
+                    2832 COMPARE_OP               2 (==)
+                    2838 POP_JUMP_FORWARD_IF_FALSE   112 (to 3064)
+         
+         197        2840 LOAD_GLOBAL              1 (NULL + os)
+                    2852 LOAD_ATTR               35 (popen)
+                    2862 LOAD_CONST              92 ('gcc -dumpversion')
+                    2864 PRECALL                  1
+                    2868 CALL                     1
+                    2878 STORE_FAST              19 (ver)
+         
+         198        2880 LOAD_FAST               19 (ver)
+                    2882 LOAD_METHOD             36 (read)
+                    2904 PRECALL                  0
+                    2908 CALL                     0
+                    2918 LOAD_METHOD             37 (strip)
+                    2940 PRECALL                  0
+                    2944 CALL                     0
+                    2954 STORE_FAST              10 (compiler_version)
+         
+         199        2956 LOAD_FAST               10 (compiler_version)
+                    2958 LOAD_METHOD             38 (count)
+                    2980 LOAD_CONST              93 ('.')
+                    2982 PRECALL                  1
+                    2986 CALL                     1
+                    2996 LOAD_CONST              94 (1)
+                    2998 COMPARE_OP               4 (>)
+                    3004 POP_JUMP_FORWARD_IF_FALSE    29 (to 3064)
+         
+         200        3006 LOAD_FAST               10 (compiler_version)
+                    3008 LOAD_CONST               0 (None)
+                    3010 LOAD_FAST               10 (compiler_version)
+                    3012 LOAD_METHOD             39 (rfind)
+                    3034 LOAD_CONST              93 ('.')
+                    3036 PRECALL                  1
+                    3040 CALL                     1
+                    3050 BUILD_SLICE              2
+                    3052 BINARY_SUBSCR
+                    3062 STORE_FAST              10 (compiler_version)
+         
+         202     >> 3064 LOAD_FAST                1 (args)
+                    3066 LOAD_ATTR               40 (arch)
+                    3076 LOAD_CONST              95 ('all')
+                    3078 COMPARE_OP               2 (==)
+                    3084 POP_JUMP_FORWARD_IF_FALSE   134 (to 3354)
+         
+         203        3086 LOAD_FAST               18 (osName)
+                    3088 LOAD_CONST              88 ('Windows')
+                    3090 COMPARE_OP               2 (==)
+                    3096 POP_JUMP_FORWARD_IF_FALSE    43 (to 3184)
+         
+         204        3098 LOAD_FAST               11 (archs)
+                    3100 LOAD_METHOD             41 (append)
+                    3122 LOAD_CONST              96 ('x86')
+                    3124 PRECALL                  1
+                    3128 CALL                     1
+                    3138 POP_TOP
+         
+         205        3140 LOAD_FAST               11 (archs)
+                    3142 LOAD_METHOD             41 (append)
+                    3164 LOAD_CONST              97 ('x86_64')
+                    3166 PRECALL                  1
+                    3170 CALL                     1
+                    3180 POP_TOP
+                    3182 JUMP_FORWARD           193 (to 3570)
+         
+         207     >> 3184 LOAD_FAST               11 (archs)
+                    3186 LOAD_METHOD             41 (append)
+                    3208 LOAD_CONST              96 ('x86')
+                    3210 PRECALL                  1
+                    3214 CALL                     1
+                    3224 POP_TOP
+         
+         208        3226 LOAD_FAST               11 (archs)
+                    3228 LOAD_METHOD             41 (append)
+                    3250 LOAD_CONST              97 ('x86_64')
+                    3252 PRECALL                  1
+                    3256 CALL                     1
+                    3266 POP_TOP
+         
+         209        3268 LOAD_FAST               11 (archs)
+                    3270 LOAD_METHOD             41 (append)
+                    3292 LOAD_CONST              98 ('armv7')
+                    3294 PRECALL                  1
+                    3298 CALL                     1
+                    3308 POP_TOP
+         
+         210        3310 LOAD_FAST               11 (archs)
+                    3312 LOAD_METHOD             41 (append)
+                    3334 LOAD_CONST              99 ('armv8')
+                    3336 PRECALL                  1
+                    3340 CALL                     1
+                    3350 POP_TOP
+                    3352 JUMP_FORWARD           108 (to 3570)
+         
+         211     >> 3354 LOAD_FAST                1 (args)
+                    3356 LOAD_ATTR               40 (arch)
+                    3366 LOAD_CONST              36 ('default')
+                    3368 COMPARE_OP               2 (==)
+                    3374 POP_JUMP_FORWARD_IF_FALSE    71 (to 3518)
+         
+         212        3376 LOAD_FAST               18 (osName)
+                    3378 LOAD_CONST              88 ('Windows')
+                    3380 COMPARE_OP               2 (==)
+                    3386 POP_JUMP_FORWARD_IF_FALSE    43 (to 3474)
+         
+         213        3388 LOAD_FAST               11 (archs)
+                    3390 LOAD_METHOD             41 (append)
+                    3412 LOAD_CONST              96 ('x86')
+                    3414 PRECALL                  1
+                    3418 CALL                     1
+                    3428 POP_TOP
+         
+         214        3430 LOAD_FAST               11 (archs)
+                    3432 LOAD_METHOD             41 (append)
+                    3454 LOAD_CONST              97 ('x86_64')
+                    3456 PRECALL                  1
+                    3460 CALL                     1
+                    3470 POP_TOP
+                    3472 JUMP_FORWARD            48 (to 3570)
+         
+         216     >> 3474 LOAD_FAST               11 (archs)
+                    3476 LOAD_METHOD             41 (append)
+                    3498 LOAD_CONST              97 ('x86_64')
+                    3500 PRECALL                  1
+                    3504 CALL                     1
+                    3514 POP_TOP
+                    3516 JUMP_FORWARD            26 (to 3570)
+         
+         218     >> 3518 LOAD_FAST               11 (archs)
+                    3520 LOAD_METHOD             41 (append)
+                    3542 LOAD_FAST                1 (args)
+                    3544 LOAD_ATTR               40 (arch)
+                    3554 PRECALL                  1
+                    3558 CALL                     1
+                    3568 POP_TOP
+         
+         221     >> 3570 LOAD_FAST                1 (args)
+                    3572 LOAD_ATTR               42 (android_arch)
+                    3582 LOAD_CONST              95 ('all')
+                    3584 COMPARE_OP               2 (==)
+                    3590 POP_JUMP_FORWARD_IF_FALSE    85 (to 3762)
+         
+         222        3592 LOAD_FAST               12 (android_archs)
+                    3594 LOAD_METHOD             41 (append)
+                    3616 LOAD_CONST              96 ('x86')
+                    3618 PRECALL                  1
+                    3622 CALL                     1
+                    3632 POP_TOP
+         
+         223        3634 LOAD_FAST               12 (android_archs)
+                    3636 LOAD_METHOD             41 (append)
+                    3658 LOAD_CONST              97 ('x86_64')
+                    3660 PRECALL                  1
+                    3664 CALL                     1
+                    3674 POP_TOP
+         
+         224        3676 LOAD_FAST               12 (android_archs)
+                    3678 LOAD_METHOD             41 (append)
+                    3700 LOAD_CONST              98 ('armv7')
+                    3702 PRECALL                  1
+                    3706 CALL                     1
+                    3716 POP_TOP
+         
+         225        3718 LOAD_FAST               12 (android_archs)
+                    3720 LOAD_METHOD             41 (append)
+                    3742 LOAD_CONST              99 ('armv8')
+                    3744 PRECALL                  1
+                    3748 CALL                     1
+                    3758 POP_TOP
+                    3760 JUMP_FORWARD            80 (to 3922)
+         
+         226     >> 3762 LOAD_FAST                1 (args)
+                    3764 LOAD_ATTR               42 (android_arch)
+                    3774 LOAD_CONST              36 ('default')
+                    3776 COMPARE_OP               2 (==)
+                    3782 POP_JUMP_FORWARD_IF_FALSE    43 (to 3870)
+         
+         227        3784 LOAD_FAST               12 (android_archs)
+                    3786 LOAD_METHOD             41 (append)
+                    3808 LOAD_CONST              98 ('armv7')
+                    3810 PRECALL                  1
+                    3814 CALL                     1
+                    3824 POP_TOP
+         
+         228        3826 LOAD_FAST               12 (android_archs)
+                    3828 LOAD_METHOD             41 (append)
+                    3850 LOAD_CONST              99 ('armv8')
+                    3852 PRECALL                  1
+                    3856 CALL                     1
+                    3866 POP_TOP
+                    3868 JUMP_FORWARD            26 (to 3922)
+         
+         230     >> 3870 LOAD_FAST               11 (archs)
+                    3872 LOAD_METHOD             41 (append)
+                    3894 LOAD_FAST                1 (args)
+                    3896 LOAD_ATTR               40 (arch)
+                    3906 PRECALL                  1
+                    3910 CALL                     1
+                    3920 POP_TOP
+         
+         232     >> 3922 LOAD_FAST                1 (args)
+                    3924 LOAD_ATTR               43 (android_compiler)
+                    3934 STORE_FAST              20 (android_compiler)
+         
+         233        3936 LOAD_FAST                1 (args)
+                    3938 LOAD_ATTR               44 (android_compiler_version)
+                    3948 STORE_FAST              21 (android_compiler_version)
+         
+         234        3950 LOAD_FAST                1 (args)
+                    3952 LOAD_ATTR               45 (android_api_level)
+                    3962 STORE_FAST              22 (android_api_level)
+         
+         235        3964 LOAD_FAST               20 (android_compiler)
+                    3966 POP_JUMP_FORWARD_IF_FALSE    19 (to 4006)
+                    3968 LOAD_GLOBAL             69 (NULL + len)
+                    3980 LOAD_FAST               20 (android_compiler)
+                    3982 PRECALL                  1
+                    3986 CALL                     1
+                    3996 LOAD_CONST              77 (0)
+                    3998 COMPARE_OP               2 (==)
+                    4004 POP_JUMP_FORWARD_IF_FALSE     2 (to 4010)
+         
+         236     >> 4006 LOAD_CONST              48 ('gcc')
+                    4008 STORE_FAST              20 (android_compiler)
+         
+         238     >> 4010 LOAD_FAST               21 (android_compiler_version)
+                    4012 POP_JUMP_FORWARD_IF_FALSE    19 (to 4052)
+                    4014 LOAD_GLOBAL             69 (NULL + len)
+                    4026 LOAD_FAST               21 (android_compiler_version)
+                    4028 PRECALL                  1
+                    4032 CALL                     1
+                    4042 LOAD_CONST              77 (0)
+                    4044 COMPARE_OP               2 (==)
+                    4050 POP_JUMP_FORWARD_IF_FALSE    11 (to 4074)
+         
+         239     >> 4052 LOAD_CONST              48 ('gcc')
+                    4054 LOAD_FAST               20 (android_compiler)
+                    4056 COMPARE_OP               2 (==)
+                    4062 POP_JUMP_FORWARD_IF_FALSE     3 (to 4070)
+         
+         240        4064 LOAD_CONST             100 ('4.9')
+                    4066 STORE_FAST              21 (android_compiler_version)
+                    4068 JUMP_FORWARD             2 (to 4074)
+         
+         242     >> 4070 LOAD_CONST             101 ('14')
+                    4072 STORE_FAST              21 (android_compiler_version)
+         
+         244     >> 4074 LOAD_FAST               22 (android_api_level)
+                    4076 POP_JUMP_FORWARD_IF_FALSE    19 (to 4116)
+                    4078 LOAD_GLOBAL             69 (NULL + len)
+                    4090 LOAD_FAST               22 (android_api_level)
+                    4092 PRECALL                  1
+                    4096 CALL                     1
+                    4106 LOAD_CONST              77 (0)
+                    4108 COMPARE_OP               2 (==)
+                    4114 POP_JUMP_FORWARD_IF_FALSE     2 (to 4120)
+         
+         245     >> 4116 LOAD_CONST             102 ('21')
+                    4118 STORE_FAST              22 (android_api_level)
+         
+         247     >> 4120 LOAD_FAST                1 (args)
+                    4122 LOAD_ATTR               46 (tag)
+                    4132 POP_JUMP_FORWARD_IF_FALSE    53 (to 4240)
+         
+         248        4134 LOAD_FAST                1 (args)
+                    4136 LOAD_ATTR               46 (tag)
+                    4146 LOAD_METHOD             37 (strip)
+                    4168 PRECALL                  0
+                    4172 CALL                     0
+                    4182 STORE_FAST               5 (git_ref)
+         
+         249        4184 LOAD_FAST                1 (args)
+                    4186 LOAD_ATTR               46 (tag)
+                    4196 LOAD_METHOD             37 (strip)
+                    4218 PRECALL                  0
+                    4222 CALL                     0
+                    4232 STORE_FAST               6 (version)
+         
+         250        4234 LOAD_CONST             103 ('stable')
+                    4236 STORE_FAST               8 (chn)
+                    4238 JUMP_FORWARD           144 (to 4528)
+         
+         251     >> 4240 LOAD_FAST                1 (args)
+                    4242 LOAD_ATTR               47 (ref)
+                    4252 POP_JUMP_FORWARD_IF_FALSE    80 (to 4414)
+         
+         252        4254 LOAD_FAST                1 (args)
+                    4256 LOAD_ATTR               47 (ref)
+                    4266 LOAD_METHOD             37 (strip)
+                    4288 PRECALL                  0
+                    4292 CALL                     0
+                    4302 STORE_FAST               5 (git_ref)
+         
+         253        4304 LOAD_FAST                1 (args)
+                    4306 LOAD_ATTR               47 (ref)
+                    4316 LOAD_METHOD             37 (strip)
+                    4338 PRECALL                  0
+                    4342 CALL                     0
+                    4352 STORE_FAST               6 (version)
+         
+         254        4354 LOAD_CONST             104 ('self.run("git checkout ')
+                    4356 LOAD_FAST                1 (args)
+                    4358 LOAD_ATTR               47 (ref)
+                    4368 LOAD_METHOD             37 (strip)
+                    4390 PRECALL                  0
+                    4394 CALL                     0
+                    4404 FORMAT_VALUE             0
+                    4406 LOAD_CONST             105 ('")')
+                    4408 BUILD_STRING             3
+                    4410 STORE_FAST               7 (git_checkout)
+                    4412 JUMP_FORWARD            57 (to 4528)
+         
+         255     >> 4414 LOAD_FAST                1 (args)
+                    4416 LOAD_ATTR               48 (branch)
+                    4426 POP_JUMP_FORWARD_IF_FALSE    50 (to 4528)
+         
+         256        4428 LOAD_FAST                1 (args)
+                    4430 LOAD_ATTR               48 (branch)
+                    4440 LOAD_METHOD             37 (strip)
+                    4462 PRECALL                  0
+                    4466 CALL                     0
+                    4476 STORE_FAST               5 (git_ref)
+         
+         257        4478 LOAD_FAST                1 (args)
+                    4480 LOAD_ATTR               48 (branch)
+                    4490 LOAD_METHOD             37 (strip)
+                    4512 PRECALL                  0
+                    4516 CALL                     0
+                    4526 STORE_FAST               8 (chn)
+         
+         259     >> 4528 LOAD_FAST                1 (args)
+                    4530 LOAD_ATTR               49 (version)
+                    4540 POP_JUMP_FORWARD_IF_FALSE     7 (to 4556)
+         
+         260        4542 LOAD_FAST                1 (args)
+                    4544 LOAD_ATTR               49 (version)
+                    4554 STORE_FAST               6 (version)
+         
+         262     >> 4556 LOAD_GLOBAL             69 (NULL + len)
+                    4568 LOAD_FAST                6 (version)
+                    4570 PRECALL                  1
+                    4574 CALL                     1
+                    4584 LOAD_CONST              77 (0)
+                    4586 COMPARE_OP               2 (==)
+                    4592 POP_JUMP_FORWARD_IF_FALSE   183 (to 4960)
+         
+         263        4594 LOAD_FAST               16 (reposes)
+                    4596 LOAD_FAST                1 (args)
+                    4598 LOAD_ATTR               14 (target)
+                    4608 BINARY_SUBSCR
+                    4618 STORE_FAST              23 (repos)
+         
+         264        4620 LOAD_FAST               23 (repos)
+                    4622 POP_JUMP_FORWARD_IF_TRUE    16 (to 4656)
+         
+         265        4624 LOAD_GLOBAL            101 (NULL + Warning)
+                    4636 LOAD_CONST             106 ('not detected version.')
+                    4638 PRECALL                  1
+                    4642 CALL                     1
+                    4652 POP_TOP
+                    4654 JUMP_FORWARD           152 (to 4960)
+         
+         267     >> 4656 LOAD_GLOBAL              1 (NULL + os)
+                    4668 LOAD_ATTR               51 (system)
+                    4678 LOAD_CONST             107 ('git clone ')
+                    4680 LOAD_FAST               23 (repos)
+                    4682 FORMAT_VALUE             0
+                    4684 LOAD_CONST             108 (' -b ')
+                    4686 LOAD_FAST                1 (args)
+                    4688 LOAD_ATTR               48 (branch)
+                    4698 FORMAT_VALUE             0
+                    4700 LOAD_CONST             109 (' src')
+                    4702 BUILD_STRING             5
+                    4704 PRECALL                  1
+                    4708 CALL                     1
+                    4718 POP_TOP
+         
+         268        4720 LOAD_GLOBAL              1 (NULL + os)
+                    4732 LOAD_ATTR               52 (chdir)
+                    4742 LOAD_CONST             110 ('src')
+                    4744 PRECALL                  1
+                    4748 CALL                     1
+                    4758 POP_TOP
+         
+         269        4760 LOAD_GLOBAL              1 (NULL + os)
+                    4772 LOAD_ATTR               35 (popen)
+                    4782 LOAD_CONST             111 ('git rev-parse --short HEAD')
+                    4784 PRECALL                  1
+                    4788 CALL                     1
+                    4798 LOAD_METHOD             36 (read)
+                    4820 PRECALL                  0
+                    4824 CALL                     0
+                    4834 STORE_FAST               6 (version)
+         
+         270        4836 LOAD_FAST                6 (version)
+                    4838 LOAD_METHOD             53 (replace)
+                    4860 LOAD_CONST             112 ('\n')
+                    4862 LOAD_CONST              67 ('')
+                    4864 PRECALL                  2
+                    4868 CALL                     2
+                    4878 STORE_FAST               6 (version)
+         
+         271        4880 LOAD_GLOBAL              1 (NULL + os)
+                    4892 LOAD_ATTR               52 (chdir)
+                    4902 LOAD_CONST             113 ('..')
+                    4904 PRECALL                  1
+                    4908 CALL                     1
+                    4918 POP_TOP
+         
+         272        4920 LOAD_GLOBAL              1 (NULL + os)
+                    4932 LOAD_ATTR               51 (system)
+                    4942 LOAD_CONST             114 ('rm -fr src')
+                    4944 PRECALL                  1
+                    4948 CALL                     1
+                    4958 POP_TOP
+         
+         274     >> 4960 LOAD_FAST                1 (args)
+                    4962 LOAD_ATTR               54 (chn)
+                    4972 POP_JUMP_FORWARD_IF_FALSE     7 (to 4988)
+         
+         275        4974 LOAD_FAST                1 (args)
+                    4976 LOAD_ATTR               54 (chn)
+                    4986 STORE_FAST               8 (chn)
+         
+         276     >> 4988 LOAD_FAST                1 (args)
+                    4990 LOAD_ATTR               55 (build_version)
+                    5000 POP_JUMP_FORWARD_IF_FALSE    13 (to 5028)
+         
+         277        5002 LOAD_FAST                6 (version)
+                    5004 LOAD_CONST              93 ('.')
+                    5006 LOAD_FAST                1 (args)
+                    5008 LOAD_ATTR               55 (build_version)
+                    5018 FORMAT_VALUE             0
+                    5020 BUILD_STRING             2
+                    5022 BINARY_OP               13 (+=)
+                    5026 STORE_FAST               6 (version)
+         
+         279     >> 5028 LOAD_FAST                1 (args)
+                    5030 LOAD_ATTR               56 (env)
+                    5040 POP_JUMP_FORWARD_IF_FALSE   104 (to 5250)
+         
+         280        5042 LOAD_FAST                1 (args)
+                    5044 LOAD_ATTR               56 (env)
+                    5054 LOAD_METHOD             57 (split)
+                    5076 LOAD_CONST             115 (',')
+                    5078 PRECALL                  1
+                    5082 CALL                     1
+                    5092 STORE_FAST              24 (envs)
+         
+         281        5094 LOAD_FAST               24 (envs)
+                    5096 GET_ITER
+                 >> 5098 FOR_ITER                75 (to 5250)
+                    5100 STORE_FAST              25 (env)
+         
+         282        5102 LOAD_FAST               25 (env)
+                    5104 LOAD_METHOD             57 (split)
+                    5126 LOAD_CONST             116 ('=')
+                    5128 PRECALL                  1
+                    5132 CALL                     1
+                    5142 STORE_FAST              26 (kv)
+         
+         283        5144 LOAD_GLOBAL             69 (NULL + len)
+                    5156 LOAD_FAST               26 (kv)
+                    5158 PRECALL                  1
+                    5162 CALL                     1
+                    5172 LOAD_CONST             117 (2)
+                    5174 COMPARE_OP               2 (==)
+                    5180 POP_JUMP_FORWARD_IF_FALSE    33 (to 5248)
+         
+         284        5182 LOAD_GLOBAL              1 (NULL + os)
+                    5194 LOAD_ATTR               58 (putenv)
+                    5204 LOAD_FAST               26 (kv)
+                    5206 LOAD_CONST              77 (0)
+                    5208 BINARY_SUBSCR
+                    5218 LOAD_FAST               26 (kv)
+                    5220 LOAD_CONST              94 (1)
+                    5222 BINARY_SUBSCR
+                    5232 PRECALL                  2
+                    5236 CALL                     2
+                    5246 POP_TOP
+                 >> 5248 JUMP_BACKWARD           76 (to 5098)
+         
+         286     >> 5250 LOAD_GLOBAL              9 (NULL + shutil)
+                    5262 LOAD_ATTR               59 (copyfile)
+                    5272 LOAD_FAST               17 (tmpl_file)
+                    5274 LOAD_FAST               14 (conan_file)
+                    5276 PRECALL                  2
+                    5280 CALL                     2
+                    5290 POP_TOP
+         
+         287        5292 LOAD_GLOBAL            121 (NULL + replace_in_file)
+                    5304 LOAD_FAST               14 (conan_file)
+                    5306 LOAD_CONST             118 ('@checkout@')
+                    5308 LOAD_FAST                7 (git_checkout)
+                    5310 PRECALL                  3
+                    5314 CALL                     3
+                    5324 POP_TOP
+         
+         288        5326 LOAD_GLOBAL             69 (NULL + len)
+                    5338 LOAD_FAST                7 (git_checkout)
+                    5340 PRECALL                  1
+                    5344 CALL                     1
+                    5354 LOAD_CONST              77 (0)
+                    5356 COMPARE_OP               4 (>)
+                    5362 POP_JUMP_FORWARD_IF_FALSE    18 (to 5400)
+         
+         289        5364 LOAD_GLOBAL            121 (NULL + replace_in_file)
+                    5376 LOAD_FAST               14 (conan_file)
+                    5378 LOAD_CONST             119 ('@git_ref@')
+                    5380 LOAD_CONST              67 ('')
+                    5382 PRECALL                  3
+                    5386 CALL                     3
+                    5396 POP_TOP
+                    5398 JUMP_FORWARD            20 (to 5440)
+         
+         291     >> 5400 LOAD_GLOBAL            121 (NULL + replace_in_file)
+                    5412 LOAD_FAST               14 (conan_file)
+                    5414 LOAD_CONST             119 ('@git_ref@')
+                    5416 LOAD_CONST             120 ('-b ')
+                    5418 LOAD_FAST                5 (git_ref)
+                    5420 FORMAT_VALUE             0
+                    5422 BUILD_STRING             2
+                    5424 PRECALL                  3
+                    5428 CALL                     3
+                    5438 POP_TOP
+         
+         292     >> 5440 LOAD_GLOBAL             69 (NULL + len)
+                    5452 LOAD_FAST                6 (version)
+                    5454 PRECALL                  1
+                    5458 CALL                     1
+                    5468 LOAD_CONST              77 (0)
+                    5470 COMPARE_OP               4 (>)
+                    5476 POP_JUMP_FORWARD_IF_FALSE    17 (to 5512)
+         
+         293        5478 LOAD_GLOBAL            121 (NULL + replace_in_file)
+                    5490 LOAD_FAST               14 (conan_file)
+                    5492 LOAD_CONST             121 ('@version@')
+                    5494 LOAD_FAST                6 (version)
+                    5496 PRECALL                  3
+                    5500 CALL                     3
+                    5510 POP_TOP
+         
+         295     >> 5512 LOAD_FAST                1 (args)
+                    5514 LOAD_ATTR               61 (without_native)
+                    5524 POP_JUMP_FORWARD_IF_TRUE    31 (to 5588)
+         
+         296        5526 LOAD_GLOBAL            125 (NULL + build_native)
+                    5538 LOAD_FAST               14 (conan_file)
+                    5540 LOAD_FAST                8 (chn)
+                    5542 LOAD_FAST                9 (compiler)
+                    5544 LOAD_FAST               10 (compiler_version)
+                    5546 LOAD_FAST               11 (archs)
+                    5548 LOAD_FAST                1 (args)
+                    5550 LOAD_ATTR               63 (debug)
+                    5560 LOAD_FAST                1 (args)
+                    5562 LOAD_ATTR               64 (settings)
+                    5572 PRECALL                  7
+                    5576 CALL                     7
+                    5586 POP_TOP
+         
+         297     >> 5588 LOAD_FAST                1 (args)
+                    5590 LOAD_ATTR               65 (android)
+                    5600 POP_JUMP_FORWARD_IF_FALSE    92 (to 5786)
+         
+         298        5602 LOAD_FAST               20 (android_compiler)
+                    5604 LOAD_METHOD             37 (strip)
+                    5626 PRECALL                  0
+                    5630 CALL                     0
+                    5640 STORE_FAST              20 (android_compiler)
+         
+         299        5642 LOAD_FAST               21 (android_compiler_version)
+                    5644 LOAD_METHOD             37 (strip)
+                    5666 PRECALL                  0
+                    5670 CALL                     0
+                    5680 STORE_FAST              21 (android_compiler_version)
+         
+         300        5682 LOAD_FAST               22 (android_api_level)
+                    5684 LOAD_METHOD             37 (strip)
+                    5706 PRECALL                  0
+                    5710 CALL                     0
+                    5720 STORE_FAST              22 (android_api_level)
+         
+         302        5722 LOAD_GLOBAL            133 (NULL + build_android)
+                    5734 LOAD_FAST               14 (conan_file)
+                    5736 LOAD_FAST                8 (chn)
+                    5738 LOAD_FAST               20 (android_compiler)
+                    5740 LOAD_FAST               21 (android_compiler_version)
+                    5742 LOAD_FAST               12 (android_archs)
+                    5744 LOAD_FAST               22 (android_api_level)
+                    5746 LOAD_FAST                1 (args)
+                    5748 LOAD_ATTR               63 (debug)
+                    5758 LOAD_FAST                1 (args)
+                    5760 LOAD_ATTR               64 (settings)
+                    5770 PRECALL                  8
+                    5774 CALL                     8
+                    5784 POP_TOP
+         
+         303     >> 5786 LOAD_GLOBAL             23 (NULL + get_os_name)
+                    5798 PRECALL                  0
+                    5802 CALL                     0
+                    5812 LOAD_CONST              31 ('Macos')
+                    5814 COMPARE_OP               2 (==)
+                    5820 POP_JUMP_FORWARD_IF_FALSE    38 (to 5898)
+         
+         304        5822 LOAD_FAST                1 (args)
+                    5824 LOAD_ATTR               67 (ios)
+                    5834 POP_JUMP_FORWARD_IF_FALSE    31 (to 5898)
+         
+         305        5836 LOAD_GLOBAL            137 (NULL + build_ios)
+                    5848 LOAD_FAST               14 (conan_file)
+                    5850 LOAD_FAST                8 (chn)
+                    5852 LOAD_FAST                9 (compiler)
+                    5854 LOAD_FAST               10 (compiler_version)
+                    5856 LOAD_FAST               11 (archs)
+                    5858 LOAD_FAST                1 (args)
+                    5860 LOAD_ATTR               63 (debug)
+                    5870 LOAD_FAST                1 (args)
+                    5872 LOAD_ATTR               64 (settings)
+                    5882 PRECALL                  7
+                    5886 CALL                     7
+                    5896 POP_TOP
+         
+         307     >> 5898 LOAD_FAST                1 (args)
+                    5900 LOAD_ATTR               69 (upload)
+                    5910 POP_JUMP_FORWARD_IF_FALSE    32 (to 5976)
+         
+         308        5912 LOAD_GLOBAL              1 (NULL + os)
+                    5924 LOAD_ATTR               51 (system)
+                    5934 LOAD_CONST             122 ('conan upload ')
+                    5936 LOAD_FAST               13 (target)
+                    5938 FORMAT_VALUE             0
+                    5940 LOAD_CONST              85 ('/')
+                    5942 LOAD_FAST                6 (version)
+                    5944 FORMAT_VALUE             0
+                    5946 LOAD_CONST             123 ('@1602/')
+                    5948 LOAD_FAST                8 (chn)
+                    5950 FORMAT_VALUE             0
+                    5952 LOAD_CONST             124 (' --all --force')
+                    5954 BUILD_STRING             7
+                    5956 PRECALL                  1
+                    5960 CALL                     1
+                    5970 POP_TOP
+                    5972 LOAD_CONST               0 (None)
+                    5974 RETURN_VALUE
          
-         147        1470 LOAD_CONST              72 ('dev')
-                    1472 STORE_FAST               7 (chn)
-         
-         148        1474 LOAD_FAST                1 (args)
-                    1476 LOAD_ATTR               15 (compiler)
-                    1486 STORE_FAST               8 (compiler)
-         
-         149        1488 LOAD_FAST                1 (args)
-                    1490 LOAD_ATTR               16 (compiler_version)
-                    1500 STORE_FAST               9 (compiler_version)
-         
-         150        1502 BUILD_LIST               0
-                    1504 STORE_FAST              10 (archs)
-         
-         151        1506 BUILD_LIST               0
-                    1508 STORE_FAST              11 (android_archs)
-         
-         152        1510 LOAD_FAST                1 (args)
-                    1512 LOAD_ATTR                5 (target)
-                    1522 STORE_FAST              12 (target)
-         
-         154        1524 LOAD_GLOBAL             14 (os)
-                    1536 LOAD_ATTR                9 (path)
-                    1546 LOAD_METHOD             10 (dirname)
-                    1568 LOAD_GLOBAL             22 (__file__)
-                    1580 PRECALL                  1
-                    1584 CALL                     1
-                    1594 FORMAT_VALUE             0
-                    1596 LOAD_CONST              73 ('/conanfile.py')
-                    1598 BUILD_STRING             2
-                    1600 STORE_FAST              13 (conan_file)
-         
-         155        1602 LOAD_GLOBAL             14 (os)
-                    1614 LOAD_ATTR                9 (path)
-                    1624 LOAD_METHOD             17 (exists)
-                    1646 LOAD_FAST               13 (conan_file)
-                    1648 PRECALL                  1
-                    1652 CALL                     1
-                    1662 POP_JUMP_FORWARD_IF_FALSE    85 (to 1834)
-         
-         156        1664 LOAD_GLOBAL             14 (os)
-                    1676 LOAD_ATTR                9 (path)
-                    1686 LOAD_METHOD             18 (isdir)
-                    1708 LOAD_FAST               13 (conan_file)
-                    1710 PRECALL                  1
-                    1714 CALL                     1
-                    1724 POP_JUMP_FORWARD_IF_FALSE    21 (to 1768)
-         
-         157        1726 LOAD_GLOBAL             39 (NULL + shutil)
-                    1738 LOAD_ATTR               20 (rmtree)
-                    1748 LOAD_FAST               13 (conan_file)
-                    1750 PRECALL                  1
-                    1754 CALL                     1
-                    1764 POP_TOP
-                    1766 JUMP_FORWARD            33 (to 1834)
-         
-         159     >> 1768 LOAD_GLOBAL             15 (NULL + os)
-                    1780 LOAD_ATTR               21 (remove)
-                    1790 LOAD_GLOBAL             45 (NULL + Path)
-                    1802 LOAD_FAST               13 (conan_file)
-                    1804 PRECALL                  1
-                    1808 CALL                     1
-                    1818 PRECALL                  1
-                    1822 CALL                     1
-                    1832 POP_TOP
-         
-         161     >> 1834 LOAD_GLOBAL             47 (NULL + open)
-                    1846 LOAD_GLOBAL             14 (os)
-                    1858 LOAD_ATTR                9 (path)
-                    1868 LOAD_METHOD             10 (dirname)
-                    1890 LOAD_GLOBAL             22 (__file__)
-                    1902 PRECALL                  1
-                    1906 CALL                     1
-                    1916 FORMAT_VALUE             0
-                    1918 LOAD_CONST              74 ('/targets/repos.yaml')
-                    1920 BUILD_STRING             2
-                    1922 LOAD_CONST              75 ('r')
-                    1924 LOAD_CONST              76 ('utf-8')
-                    1926 KW_NAMES                77
-                    1928 PRECALL                  3
-                    1932 CALL                     3
-                    1942 STORE_FAST              14 (reposes_config)
-         
-         162        1944 LOAD_GLOBAL             49 (NULL + yaml)
-                    1956 LOAD_ATTR               25 (load)
-                    1966 LOAD_FAST               14 (reposes_config)
-                    1968 LOAD_GLOBAL             48 (yaml)
-                    1980 LOAD_ATTR               26 (Loader)
-                    1990 KW_NAMES                78
-                    1992 PRECALL                  2
-                    1996 CALL                     2
-                    2006 STORE_FAST              15 (reposes)
-         
-         164        2008 LOAD_FAST                1 (args)
-                    2010 LOAD_ATTR                5 (target)
-                    2020 STORE_FAST              16 (tmpl_file)
-         
-         166        2022 LOAD_GLOBAL             45 (NULL + Path)
-                    2034 LOAD_FAST               16 (tmpl_file)
-                    2036 PRECALL                  1
-                    2040 CALL                     1
-                    2050 LOAD_METHOD             27 (is_file)
-                    2072 PRECALL                  0
-                    2076 CALL                     0
-                    2086 POP_JUMP_FORWARD_IF_TRUE   130 (to 2348)
-         
-         167        2088 LOAD_GLOBAL             57 (NULL + find_target)
-                    2100 LOAD_GLOBAL             14 (os)
-                    2112 LOAD_ATTR                9 (path)
-                    2122 LOAD_METHOD             10 (dirname)
-                    2144 LOAD_GLOBAL             22 (__file__)
-                    2156 PRECALL                  1
-                    2160 CALL                     1
-                    2170 FORMAT_VALUE             0
-                    2172 LOAD_CONST              69 ('/targets')
-                    2174 BUILD_STRING             2
-                    2176 LOAD_FAST               16 (tmpl_file)
-                    2178 FORMAT_VALUE             0
-                    2180 LOAD_CONST              70 ('.py.in')
-                    2182 BUILD_STRING             2
-                    2184 PRECALL                  2
-                    2188 CALL                     2
-                    2198 POP_JUMP_FORWARD_IF_FALSE    43 (to 2286)
-         
-         168        2200 LOAD_GLOBAL             14 (os)
-                    2212 LOAD_ATTR                9 (path)
-                    2222 LOAD_METHOD             10 (dirname)
-                    2244 LOAD_GLOBAL             22 (__file__)
-                    2256 PRECALL                  1
-                    2260 CALL                     1
-                    2270 FORMAT_VALUE             0
-                    2272 LOAD_CONST              79 ('/targets/')
-                    2274 LOAD_FAST               16 (tmpl_file)
-                    2276 FORMAT_VALUE             0
-                    2278 LOAD_CONST              70 ('.py.in')
-                    2280 BUILD_STRING             4
-                    2282 STORE_FAST              16 (tmpl_file)
-                    2284 JUMP_FORWARD            61 (to 2408)
-         
-         170     >> 2286 LOAD_GLOBAL             13 (NULL + print)
-                    2298 LOAD_CONST              80 ('Error: Invalid target.')
-                    2300 PRECALL                  1
-                    2304 CALL                     1
-                    2314 POP_TOP
-         
-         171        2316 LOAD_GLOBAL             29 (NULL + exit)
-                    2328 LOAD_CONST              81 (-1)
-                    2330 PRECALL                  1
-                    2334 CALL                     1
-                    2344 POP_TOP
-                    2346 JUMP_FORWARD            30 (to 2408)
-         
-         173     >> 2348 LOAD_GLOBAL             59 (NULL + read_target_name)
-                    2360 LOAD_FAST               16 (tmpl_file)
-                    2362 PRECALL                  1
-                    2366 CALL                     1
-                    2376 STORE_FAST              12 (target)
-         
-         174        2378 LOAD_GLOBAL             61 (NULL + read_target_version)
-                    2390 LOAD_FAST               16 (tmpl_file)
-                    2392 PRECALL                  1
-                    2396 CALL                     1
-                    2406 STORE_FAST               5 (version)
-         
-         176     >> 2408 LOAD_GLOBAL              7 (NULL + get_os_name)
-                    2420 PRECALL                  0
-                    2424 CALL                     0
-                    2434 STORE_FAST              17 (osName)
-         
-         177        2436 LOAD_FAST                8 (compiler)
-                    2438 POP_JUMP_FORWARD_IF_FALSE    19 (to 2478)
-                    2440 LOAD_GLOBAL             63 (NULL + len)
-                    2452 LOAD_FAST                8 (compiler)
-                    2454 PRECALL                  1
-                    2458 CALL                     1
-                    2468 LOAD_CONST              71 (0)
-                    2470 COMPARE_OP               2 (==)
-                    2476 POP_JUMP_FORWARD_IF_FALSE    20 (to 2518)
-         
-         178     >> 2478 LOAD_FAST               17 (osName)
-                    2480 LOAD_CONST              82 ('Windows')
-                    2482 COMPARE_OP               2 (==)
-                    2488 POP_JUMP_FORWARD_IF_FALSE     3 (to 2496)
-         
-         179        2490 LOAD_CONST              83 ('Visual Studio')
-                    2492 STORE_FAST               8 (compiler)
-                    2494 JUMP_FORWARD            11 (to 2518)
-         
-         180     >> 2496 LOAD_FAST               17 (osName)
-                    2498 LOAD_CONST              24 ('Macos')
-                    2500 COMPARE_OP               2 (==)
-                    2506 POP_JUMP_FORWARD_IF_FALSE     3 (to 2514)
-         
-         181        2508 LOAD_CONST              42 ('clang')
-                    2510 STORE_FAST               8 (compiler)
-                    2512 JUMP_FORWARD             2 (to 2518)
-         
-         183     >> 2514 LOAD_CONST              41 ('gcc')
-                    2516 STORE_FAST               8 (compiler)
-         
-         184     >> 2518 LOAD_FAST                9 (compiler_version)
-                    2520 POP_JUMP_FORWARD_IF_FALSE    19 (to 2560)
-                    2522 LOAD_GLOBAL             63 (NULL + len)
-                    2534 LOAD_FAST                9 (compiler_version)
-                    2536 PRECALL                  1
-                    2540 CALL                     1
-                    2550 LOAD_CONST              71 (0)
-                    2552 COMPARE_OP               2 (==)
-                    2558 POP_JUMP_FORWARD_IF_FALSE   136 (to 2832)
-         
-         185     >> 2560 LOAD_FAST                8 (compiler)
-                    2562 LOAD_CONST              83 ('Visual Studio')
-                    2564 COMPARE_OP               2 (==)
-                    2570 POP_JUMP_FORWARD_IF_FALSE     3 (to 2578)
-         
-         186        2572 LOAD_CONST              84 ('15')
-                    2574 STORE_FAST               9 (compiler_version)
-                    2576 JUMP_FORWARD           127 (to 2832)
-         
-         187     >> 2578 LOAD_FAST                8 (compiler)
-                    2580 LOAD_CONST              42 ('clang')
-                    2582 COMPARE_OP               2 (==)
-                    2588 POP_JUMP_FORWARD_IF_FALSE     3 (to 2596)
-         
-         188        2590 LOAD_CONST              85 ('10')
-                    2592 STORE_FAST               9 (compiler_version)
-                    2594 JUMP_FORWARD           118 (to 2832)
-         
-         189     >> 2596 LOAD_FAST                8 (compiler)
-                    2598 LOAD_CONST              41 ('gcc')
-                    2600 COMPARE_OP               2 (==)
-                    2606 POP_JUMP_FORWARD_IF_FALSE   112 (to 2832)
-         
-         190        2608 LOAD_GLOBAL             15 (NULL + os)
-                    2620 LOAD_ATTR               32 (popen)
-                    2630 LOAD_CONST              86 ('gcc -dumpversion')
-                    2632 PRECALL                  1
-                    2636 CALL                     1
-                    2646 STORE_FAST              18 (ver)
-         
-         191        2648 LOAD_FAST               18 (ver)
-                    2650 LOAD_METHOD             33 (read)
-                    2672 PRECALL                  0
-                    2676 CALL                     0
-                    2686 LOAD_METHOD             34 (strip)
-                    2708 PRECALL                  0
-                    2712 CALL                     0
-                    2722 STORE_FAST               9 (compiler_version)
-         
-         192        2724 LOAD_FAST                9 (compiler_version)
-                    2726 LOAD_METHOD             35 (count)
-                    2748 LOAD_CONST              87 ('.')
-                    2750 PRECALL                  1
-                    2754 CALL                     1
-                    2764 LOAD_CONST              88 (1)
-                    2766 COMPARE_OP               4 (>)
-                    2772 POP_JUMP_FORWARD_IF_FALSE    29 (to 2832)
-         
-         193        2774 LOAD_FAST                9 (compiler_version)
-                    2776 LOAD_CONST               0 (None)
-                    2778 LOAD_FAST                9 (compiler_version)
-                    2780 LOAD_METHOD             36 (rfind)
-                    2802 LOAD_CONST              87 ('.')
-                    2804 PRECALL                  1
-                    2808 CALL                     1
-                    2818 BUILD_SLICE              2
-                    2820 BINARY_SUBSCR
-                    2830 STORE_FAST               9 (compiler_version)
-         
-         195     >> 2832 LOAD_FAST                1 (args)
-                    2834 LOAD_ATTR               37 (arch)
-                    2844 LOAD_CONST              89 ('all')
-                    2846 COMPARE_OP               2 (==)
-                    2852 POP_JUMP_FORWARD_IF_FALSE   134 (to 3122)
-         
-         196        2854 LOAD_FAST               17 (osName)
-                    2856 LOAD_CONST              82 ('Windows')
-                    2858 COMPARE_OP               2 (==)
-                    2864 POP_JUMP_FORWARD_IF_FALSE    43 (to 2952)
-         
-         197        2866 LOAD_FAST               10 (archs)
-                    2868 LOAD_METHOD             38 (append)
-                    2890 LOAD_CONST              90 ('x86')
-                    2892 PRECALL                  1
-                    2896 CALL                     1
-                    2906 POP_TOP
-         
-         198        2908 LOAD_FAST               10 (archs)
-                    2910 LOAD_METHOD             38 (append)
-                    2932 LOAD_CONST              91 ('x86_64')
-                    2934 PRECALL                  1
-                    2938 CALL                     1
-                    2948 POP_TOP
-                    2950 JUMP_FORWARD           193 (to 3338)
-         
-         200     >> 2952 LOAD_FAST               10 (archs)
-                    2954 LOAD_METHOD             38 (append)
-                    2976 LOAD_CONST              90 ('x86')
-                    2978 PRECALL                  1
-                    2982 CALL                     1
-                    2992 POP_TOP
-         
-         201        2994 LOAD_FAST               10 (archs)
-                    2996 LOAD_METHOD             38 (append)
-                    3018 LOAD_CONST              91 ('x86_64')
-                    3020 PRECALL                  1
-                    3024 CALL                     1
-                    3034 POP_TOP
-         
-         202        3036 LOAD_FAST               10 (archs)
-                    3038 LOAD_METHOD             38 (append)
-                    3060 LOAD_CONST              92 ('armv7')
-                    3062 PRECALL                  1
-                    3066 CALL                     1
-                    3076 POP_TOP
-         
-         203        3078 LOAD_FAST               10 (archs)
-                    3080 LOAD_METHOD             38 (append)
-                    3102 LOAD_CONST              93 ('armv8')
-                    3104 PRECALL                  1
-                    3108 CALL                     1
-                    3118 POP_TOP
-                    3120 JUMP_FORWARD           108 (to 3338)
-         
-         204     >> 3122 LOAD_FAST                1 (args)
-                    3124 LOAD_ATTR               37 (arch)
-                    3134 LOAD_CONST              29 ('default')
-                    3136 COMPARE_OP               2 (==)
-                    3142 POP_JUMP_FORWARD_IF_FALSE    71 (to 3286)
-         
-         205        3144 LOAD_FAST               17 (osName)
-                    3146 LOAD_CONST              82 ('Windows')
-                    3148 COMPARE_OP               2 (==)
-                    3154 POP_JUMP_FORWARD_IF_FALSE    43 (to 3242)
-         
-         206        3156 LOAD_FAST               10 (archs)
-                    3158 LOAD_METHOD             38 (append)
-                    3180 LOAD_CONST              90 ('x86')
-                    3182 PRECALL                  1
-                    3186 CALL                     1
-                    3196 POP_TOP
-         
-         207        3198 LOAD_FAST               10 (archs)
-                    3200 LOAD_METHOD             38 (append)
-                    3222 LOAD_CONST              91 ('x86_64')
-                    3224 PRECALL                  1
-                    3228 CALL                     1
-                    3238 POP_TOP
-                    3240 JUMP_FORWARD            48 (to 3338)
-         
-         209     >> 3242 LOAD_FAST               10 (archs)
-                    3244 LOAD_METHOD             38 (append)
-                    3266 LOAD_CONST              91 ('x86_64')
-                    3268 PRECALL                  1
-                    3272 CALL                     1
-                    3282 POP_TOP
-                    3284 JUMP_FORWARD            26 (to 3338)
-         
-         211     >> 3286 LOAD_FAST               10 (archs)
-                    3288 LOAD_METHOD             38 (append)
-                    3310 LOAD_FAST                1 (args)
-                    3312 LOAD_ATTR               37 (arch)
-                    3322 PRECALL                  1
-                    3326 CALL                     1
-                    3336 POP_TOP
-         
-         214     >> 3338 LOAD_FAST                1 (args)
-                    3340 LOAD_ATTR               39 (android_arch)
-                    3350 LOAD_CONST              89 ('all')
-                    3352 COMPARE_OP               2 (==)
-                    3358 POP_JUMP_FORWARD_IF_FALSE    85 (to 3530)
-         
-         215        3360 LOAD_FAST               11 (android_archs)
-                    3362 LOAD_METHOD             38 (append)
-                    3384 LOAD_CONST              90 ('x86')
-                    3386 PRECALL                  1
-                    3390 CALL                     1
-                    3400 POP_TOP
-         
-         216        3402 LOAD_FAST               11 (android_archs)
-                    3404 LOAD_METHOD             38 (append)
-                    3426 LOAD_CONST              91 ('x86_64')
-                    3428 PRECALL                  1
-                    3432 CALL                     1
-                    3442 POP_TOP
-         
-         217        3444 LOAD_FAST               11 (android_archs)
-                    3446 LOAD_METHOD             38 (append)
-                    3468 LOAD_CONST              92 ('armv7')
-                    3470 PRECALL                  1
-                    3474 CALL                     1
-                    3484 POP_TOP
-         
-         218        3486 LOAD_FAST               11 (android_archs)
-                    3488 LOAD_METHOD             38 (append)
-                    3510 LOAD_CONST              93 ('armv8')
-                    3512 PRECALL                  1
-                    3516 CALL                     1
-                    3526 POP_TOP
-                    3528 JUMP_FORWARD            80 (to 3690)
-         
-         219     >> 3530 LOAD_FAST                1 (args)
-                    3532 LOAD_ATTR               39 (android_arch)
-                    3542 LOAD_CONST              29 ('default')
-                    3544 COMPARE_OP               2 (==)
-                    3550 POP_JUMP_FORWARD_IF_FALSE    43 (to 3638)
-         
-         220        3552 LOAD_FAST               11 (android_archs)
-                    3554 LOAD_METHOD             38 (append)
-                    3576 LOAD_CONST              92 ('armv7')
-                    3578 PRECALL                  1
-                    3582 CALL                     1
-                    3592 POP_TOP
-         
-         221        3594 LOAD_FAST               11 (android_archs)
-                    3596 LOAD_METHOD             38 (append)
-                    3618 LOAD_CONST              93 ('armv8')
-                    3620 PRECALL                  1
-                    3624 CALL                     1
-                    3634 POP_TOP
-                    3636 JUMP_FORWARD            26 (to 3690)
-         
-         223     >> 3638 LOAD_FAST               10 (archs)
-                    3640 LOAD_METHOD             38 (append)
-                    3662 LOAD_FAST                1 (args)
-                    3664 LOAD_ATTR               37 (arch)
-                    3674 PRECALL                  1
-                    3678 CALL                     1
-                    3688 POP_TOP
-         
-         225     >> 3690 LOAD_FAST                1 (args)
-                    3692 LOAD_ATTR               40 (android_compiler)
-                    3702 STORE_FAST              19 (android_compiler)
-         
-         226        3704 LOAD_FAST                1 (args)
-                    3706 LOAD_ATTR               41 (android_compiler_version)
-                    3716 STORE_FAST              20 (android_compiler_version)
-         
-         227        3718 LOAD_FAST                1 (args)
-                    3720 LOAD_ATTR               42 (android_api_level)
-                    3730 STORE_FAST              21 (android_api_level)
-         
-         228        3732 LOAD_FAST               19 (android_compiler)
-                    3734 POP_JUMP_FORWARD_IF_FALSE    19 (to 3774)
-                    3736 LOAD_GLOBAL             63 (NULL + len)
-                    3748 LOAD_FAST               19 (android_compiler)
-                    3750 PRECALL                  1
-                    3754 CALL                     1
-                    3764 LOAD_CONST              71 (0)
-                    3766 COMPARE_OP               2 (==)
-                    3772 POP_JUMP_FORWARD_IF_FALSE     2 (to 3778)
-         
-         229     >> 3774 LOAD_CONST              41 ('gcc')
-                    3776 STORE_FAST              19 (android_compiler)
-         
-         231     >> 3778 LOAD_FAST               20 (android_compiler_version)
-                    3780 POP_JUMP_FORWARD_IF_FALSE    19 (to 3820)
-                    3782 LOAD_GLOBAL             63 (NULL + len)
-                    3794 LOAD_FAST               20 (android_compiler_version)
-                    3796 PRECALL                  1
-                    3800 CALL                     1
-                    3810 LOAD_CONST              71 (0)
-                    3812 COMPARE_OP               2 (==)
-                    3818 POP_JUMP_FORWARD_IF_FALSE    11 (to 3842)
-         
-         232     >> 3820 LOAD_CONST              41 ('gcc')
-                    3822 LOAD_FAST               19 (android_compiler)
-                    3824 COMPARE_OP               2 (==)
-                    3830 POP_JUMP_FORWARD_IF_FALSE     3 (to 3838)
-         
-         233        3832 LOAD_CONST              94 ('4.9')
-                    3834 STORE_FAST              20 (android_compiler_version)
-                    3836 JUMP_FORWARD             2 (to 3842)
-         
-         235     >> 3838 LOAD_CONST              95 ('14')
-                    3840 STORE_FAST              20 (android_compiler_version)
-         
-         237     >> 3842 LOAD_FAST               21 (android_api_level)
-                    3844 POP_JUMP_FORWARD_IF_FALSE    19 (to 3884)
-                    3846 LOAD_GLOBAL             63 (NULL + len)
-                    3858 LOAD_FAST               21 (android_api_level)
-                    3860 PRECALL                  1
-                    3864 CALL                     1
-                    3874 LOAD_CONST              71 (0)
-                    3876 COMPARE_OP               2 (==)
-                    3882 POP_JUMP_FORWARD_IF_FALSE     2 (to 3888)
-         
-         238     >> 3884 LOAD_CONST              96 ('21')
-                    3886 STORE_FAST              21 (android_api_level)
-         
-         240     >> 3888 LOAD_FAST                1 (args)
-                    3890 LOAD_ATTR               43 (tag)
-                    3900 POP_JUMP_FORWARD_IF_FALSE    53 (to 4008)
-         
-         241        3902 LOAD_FAST                1 (args)
-                    3904 LOAD_ATTR               43 (tag)
-                    3914 LOAD_METHOD             34 (strip)
-                    3936 PRECALL                  0
-                    3940 CALL                     0
-                    3950 STORE_FAST               4 (git_ref)
-         
-         242        3952 LOAD_FAST                1 (args)
-                    3954 LOAD_ATTR               43 (tag)
-                    3964 LOAD_METHOD             34 (strip)
-                    3986 PRECALL                  0
-                    3990 CALL                     0
-                    4000 STORE_FAST               5 (version)
-         
-         243        4002 LOAD_CONST              97 ('stable')
-                    4004 STORE_FAST               7 (chn)
-                    4006 JUMP_FORWARD           144 (to 4296)
-         
-         244     >> 4008 LOAD_FAST                1 (args)
-                    4010 LOAD_ATTR               44 (ref)
-                    4020 POP_JUMP_FORWARD_IF_FALSE    80 (to 4182)
-         
-         245        4022 LOAD_FAST                1 (args)
-                    4024 LOAD_ATTR               44 (ref)
-                    4034 LOAD_METHOD             34 (strip)
-                    4056 PRECALL                  0
-                    4060 CALL                     0
-                    4070 STORE_FAST               4 (git_ref)
-         
-         246        4072 LOAD_FAST                1 (args)
-                    4074 LOAD_ATTR               44 (ref)
-                    4084 LOAD_METHOD             34 (strip)
-                    4106 PRECALL                  0
-                    4110 CALL                     0
-                    4120 STORE_FAST               5 (version)
-         
-         247        4122 LOAD_CONST              98 ('self.run("git checkout ')
-                    4124 LOAD_FAST                1 (args)
-                    4126 LOAD_ATTR               44 (ref)
-                    4136 LOAD_METHOD             34 (strip)
-                    4158 PRECALL                  0
-                    4162 CALL                     0
-                    4172 FORMAT_VALUE             0
-                    4174 LOAD_CONST              99 ('")')
-                    4176 BUILD_STRING             3
-                    4178 STORE_FAST               6 (git_checkout)
-                    4180 JUMP_FORWARD            57 (to 4296)
-         
-         248     >> 4182 LOAD_FAST                1 (args)
-                    4184 LOAD_ATTR               45 (branch)
-                    4194 POP_JUMP_FORWARD_IF_FALSE    50 (to 4296)
-         
-         249        4196 LOAD_FAST                1 (args)
-                    4198 LOAD_ATTR               45 (branch)
-                    4208 LOAD_METHOD             34 (strip)
-                    4230 PRECALL                  0
-                    4234 CALL                     0
-                    4244 STORE_FAST               4 (git_ref)
-         
-         250        4246 LOAD_FAST                1 (args)
-                    4248 LOAD_ATTR               45 (branch)
-                    4258 LOAD_METHOD             34 (strip)
-                    4280 PRECALL                  0
-                    4284 CALL                     0
-                    4294 STORE_FAST               7 (chn)
-         
-         252     >> 4296 LOAD_FAST                1 (args)
-                    4298 LOAD_ATTR               46 (version)
-                    4308 POP_JUMP_FORWARD_IF_FALSE     7 (to 4324)
-         
-         253        4310 LOAD_FAST                1 (args)
-                    4312 LOAD_ATTR               46 (version)
-                    4322 STORE_FAST               5 (version)
-         
-         255     >> 4324 LOAD_GLOBAL             63 (NULL + len)
-                    4336 LOAD_FAST                5 (version)
-                    4338 PRECALL                  1
-                    4342 CALL                     1
-                    4352 LOAD_CONST              71 (0)
-                    4354 COMPARE_OP               2 (==)
-                    4360 POP_JUMP_FORWARD_IF_FALSE   183 (to 4728)
-         
-         256        4362 LOAD_FAST               15 (reposes)
-                    4364 LOAD_FAST                1 (args)
-                    4366 LOAD_ATTR                5 (target)
-                    4376 BINARY_SUBSCR
-                    4386 STORE_FAST              22 (repos)
-         
-         257        4388 LOAD_FAST               22 (repos)
-                    4390 POP_JUMP_FORWARD_IF_TRUE    16 (to 4424)
-         
-         258        4392 LOAD_GLOBAL             95 (NULL + Warning)
-                    4404 LOAD_CONST             100 ('not detected version.')
-                    4406 PRECALL                  1
-                    4410 CALL                     1
-                    4420 POP_TOP
-                    4422 JUMP_FORWARD           152 (to 4728)
-         
-         260     >> 4424 LOAD_GLOBAL             15 (NULL + os)
-                    4436 LOAD_ATTR               48 (system)
-                    4446 LOAD_CONST             101 ('git clone ')
-                    4448 LOAD_FAST               22 (repos)
-                    4450 FORMAT_VALUE             0
-                    4452 LOAD_CONST             102 (' -b ')
-                    4454 LOAD_FAST                1 (args)
-                    4456 LOAD_ATTR               45 (branch)
-                    4466 FORMAT_VALUE             0
-                    4468 LOAD_CONST             103 (' src')
-                    4470 BUILD_STRING             5
-                    4472 PRECALL                  1
-                    4476 CALL                     1
-                    4486 POP_TOP
-         
-         261        4488 LOAD_GLOBAL             15 (NULL + os)
-                    4500 LOAD_ATTR               49 (chdir)
-                    4510 LOAD_CONST             104 ('src')
-                    4512 PRECALL                  1
-                    4516 CALL                     1
-                    4526 POP_TOP
-         
-         262        4528 LOAD_GLOBAL             15 (NULL + os)
-                    4540 LOAD_ATTR               32 (popen)
-                    4550 LOAD_CONST             105 ('git rev-parse --short HEAD')
-                    4552 PRECALL                  1
-                    4556 CALL                     1
-                    4566 LOAD_METHOD             33 (read)
-                    4588 PRECALL                  0
-                    4592 CALL                     0
-                    4602 STORE_FAST               5 (version)
-         
-         263        4604 LOAD_FAST                5 (version)
-                    4606 LOAD_METHOD             50 (replace)
-                    4628 LOAD_CONST             106 ('\n')
-                    4630 LOAD_CONST              60 ('')
-                    4632 PRECALL                  2
-                    4636 CALL                     2
-                    4646 STORE_FAST               5 (version)
-         
-         264        4648 LOAD_GLOBAL             15 (NULL + os)
-                    4660 LOAD_ATTR               49 (chdir)
-                    4670 LOAD_CONST             107 ('..')
-                    4672 PRECALL                  1
-                    4676 CALL                     1
-                    4686 POP_TOP
-         
-         265        4688 LOAD_GLOBAL             15 (NULL + os)
-                    4700 LOAD_ATTR               48 (system)
-                    4710 LOAD_CONST             108 ('rm -fr src')
-                    4712 PRECALL                  1
-                    4716 CALL                     1
-                    4726 POP_TOP
-         
-         267     >> 4728 LOAD_FAST                1 (args)
-                    4730 LOAD_ATTR               51 (chn)
-                    4740 POP_JUMP_FORWARD_IF_FALSE     7 (to 4756)
-         
-         268        4742 LOAD_FAST                1 (args)
-                    4744 LOAD_ATTR               51 (chn)
-                    4754 STORE_FAST               7 (chn)
-         
-         269     >> 4756 LOAD_FAST                1 (args)
-                    4758 LOAD_ATTR               52 (build_version)
-                    4768 POP_JUMP_FORWARD_IF_FALSE    13 (to 4796)
-         
-         270        4770 LOAD_FAST                5 (version)
-                    4772 LOAD_CONST              87 ('.')
-                    4774 LOAD_FAST                1 (args)
-                    4776 LOAD_ATTR               52 (build_version)
-                    4786 FORMAT_VALUE             0
-                    4788 BUILD_STRING             2
-                    4790 BINARY_OP               13 (+=)
-                    4794 STORE_FAST               5 (version)
-         
-         272     >> 4796 LOAD_FAST                1 (args)
-                    4798 LOAD_ATTR               53 (env)
-                    4808 POP_JUMP_FORWARD_IF_FALSE   104 (to 5018)
-         
-         273        4810 LOAD_FAST                1 (args)
-                    4812 LOAD_ATTR               53 (env)
-                    4822 LOAD_METHOD             54 (split)
-                    4844 LOAD_CONST             109 (',')
-                    4846 PRECALL                  1
-                    4850 CALL                     1
-                    4860 STORE_FAST              23 (envs)
-         
-         274        4862 LOAD_FAST               23 (envs)
-                    4864 GET_ITER
-                 >> 4866 FOR_ITER                75 (to 5018)
-                    4868 STORE_FAST              24 (env)
-         
-         275        4870 LOAD_FAST               24 (env)
-                    4872 LOAD_METHOD             54 (split)
-                    4894 LOAD_CONST             110 ('=')
-                    4896 PRECALL                  1
-                    4900 CALL                     1
-                    4910 STORE_FAST              25 (kv)
-         
-         276        4912 LOAD_GLOBAL             63 (NULL + len)
-                    4924 LOAD_FAST               25 (kv)
-                    4926 PRECALL                  1
-                    4930 CALL                     1
-                    4940 LOAD_CONST             111 (2)
-                    4942 COMPARE_OP               2 (==)
-                    4948 POP_JUMP_FORWARD_IF_FALSE    33 (to 5016)
-         
-         277        4950 LOAD_GLOBAL             15 (NULL + os)
-                    4962 LOAD_ATTR               55 (putenv)
-                    4972 LOAD_FAST               25 (kv)
-                    4974 LOAD_CONST              71 (0)
-                    4976 BINARY_SUBSCR
-                    4986 LOAD_FAST               25 (kv)
-                    4988 LOAD_CONST              88 (1)
-                    4990 BINARY_SUBSCR
-                    5000 PRECALL                  2
-                    5004 CALL                     2
-                    5014 POP_TOP
-                 >> 5016 JUMP_BACKWARD           76 (to 4866)
-         
-         279     >> 5018 LOAD_GLOBAL             39 (NULL + shutil)
-                    5030 LOAD_ATTR               56 (copyfile)
-                    5040 LOAD_FAST               16 (tmpl_file)
-                    5042 LOAD_FAST               13 (conan_file)
-                    5044 PRECALL                  2
-                    5048 CALL                     2
-                    5058 POP_TOP
-         
-         280        5060 LOAD_GLOBAL            115 (NULL + replace_in_file)
-                    5072 LOAD_FAST               13 (conan_file)
-                    5074 LOAD_CONST             112 ('@checkout@')
-                    5076 LOAD_FAST                6 (git_checkout)
-                    5078 PRECALL                  3
-                    5082 CALL                     3
-                    5092 POP_TOP
-         
-         281        5094 LOAD_GLOBAL             63 (NULL + len)
-                    5106 LOAD_FAST                6 (git_checkout)
-                    5108 PRECALL                  1
-                    5112 CALL                     1
-                    5122 LOAD_CONST              71 (0)
-                    5124 COMPARE_OP               4 (>)
-                    5130 POP_JUMP_FORWARD_IF_FALSE    18 (to 5168)
-         
-         282        5132 LOAD_GLOBAL            115 (NULL + replace_in_file)
-                    5144 LOAD_FAST               13 (conan_file)
-                    5146 LOAD_CONST             113 ('@git_ref@')
-                    5148 LOAD_CONST              60 ('')
-                    5150 PRECALL                  3
-                    5154 CALL                     3
-                    5164 POP_TOP
-                    5166 JUMP_FORWARD            20 (to 5208)
-         
-         284     >> 5168 LOAD_GLOBAL            115 (NULL + replace_in_file)
-                    5180 LOAD_FAST               13 (conan_file)
-                    5182 LOAD_CONST             113 ('@git_ref@')
-                    5184 LOAD_CONST             114 ('-b ')
-                    5186 LOAD_FAST                4 (git_ref)
-                    5188 FORMAT_VALUE             0
-                    5190 BUILD_STRING             2
-                    5192 PRECALL                  3
-                    5196 CALL                     3
-                    5206 POP_TOP
-         
-         285     >> 5208 LOAD_GLOBAL             63 (NULL + len)
-                    5220 LOAD_FAST                5 (version)
-                    5222 PRECALL                  1
-                    5226 CALL                     1
-                    5236 LOAD_CONST              71 (0)
-                    5238 COMPARE_OP               4 (>)
-                    5244 POP_JUMP_FORWARD_IF_FALSE    17 (to 5280)
-         
-         286        5246 LOAD_GLOBAL            115 (NULL + replace_in_file)
-                    5258 LOAD_FAST               13 (conan_file)
-                    5260 LOAD_CONST             115 ('@version@')
-                    5262 LOAD_FAST                5 (version)
-                    5264 PRECALL                  3
-                    5268 CALL                     3
-                    5278 POP_TOP
-         
-         288     >> 5280 LOAD_FAST                1 (args)
-                    5282 LOAD_ATTR               58 (without_native)
-                    5292 POP_JUMP_FORWARD_IF_TRUE    31 (to 5356)
-         
-         289        5294 LOAD_GLOBAL            119 (NULL + build_native)
-                    5306 LOAD_FAST               13 (conan_file)
-                    5308 LOAD_FAST                7 (chn)
-                    5310 LOAD_FAST                8 (compiler)
-                    5312 LOAD_FAST                9 (compiler_version)
-                    5314 LOAD_FAST               10 (archs)
-                    5316 LOAD_FAST                1 (args)
-                    5318 LOAD_ATTR               60 (debug)
-                    5328 LOAD_FAST                1 (args)
-                    5330 LOAD_ATTR               61 (settings)
-                    5340 PRECALL                  7
-                    5344 CALL                     7
-                    5354 POP_TOP
-         
-         290     >> 5356 LOAD_FAST                1 (args)
-                    5358 LOAD_ATTR               62 (android)
-                    5368 POP_JUMP_FORWARD_IF_FALSE    92 (to 5554)
-         
-         291        5370 LOAD_FAST               19 (android_compiler)
-                    5372 LOAD_METHOD             34 (strip)
-                    5394 PRECALL                  0
-                    5398 CALL                     0
-                    5408 STORE_FAST              19 (android_compiler)
-         
-         292        5410 LOAD_FAST               20 (android_compiler_version)
-                    5412 LOAD_METHOD             34 (strip)
-                    5434 PRECALL                  0
-                    5438 CALL                     0
-                    5448 STORE_FAST              20 (android_compiler_version)
-         
-         293        5450 LOAD_FAST               21 (android_api_level)
-                    5452 LOAD_METHOD             34 (strip)
-                    5474 PRECALL                  0
-                    5478 CALL                     0
-                    5488 STORE_FAST              21 (android_api_level)
-         
-         295        5490 LOAD_GLOBAL            127 (NULL + build_android)
-                    5502 LOAD_FAST               13 (conan_file)
-                    5504 LOAD_FAST                7 (chn)
-                    5506 LOAD_FAST               19 (android_compiler)
-                    5508 LOAD_FAST               20 (android_compiler_version)
-                    5510 LOAD_FAST               11 (android_archs)
-                    5512 LOAD_FAST               21 (android_api_level)
-                    5514 LOAD_FAST                1 (args)
-                    5516 LOAD_ATTR               60 (debug)
-                    5526 LOAD_FAST                1 (args)
-                    5528 LOAD_ATTR               61 (settings)
-                    5538 PRECALL                  8
-                    5542 CALL                     8
-                    5552 POP_TOP
-         
-         296     >> 5554 LOAD_GLOBAL              7 (NULL + get_os_name)
-                    5566 PRECALL                  0
-                    5570 CALL                     0
-                    5580 LOAD_CONST              24 ('Macos')
-                    5582 COMPARE_OP               2 (==)
-                    5588 POP_JUMP_FORWARD_IF_FALSE    38 (to 5666)
-         
-         297        5590 LOAD_FAST                1 (args)
-                    5592 LOAD_ATTR               64 (ios)
-                    5602 POP_JUMP_FORWARD_IF_FALSE    31 (to 5666)
-         
-         298        5604 LOAD_GLOBAL            131 (NULL + build_ios)
-                    5616 LOAD_FAST               13 (conan_file)
-                    5618 LOAD_FAST                7 (chn)
-                    5620 LOAD_FAST                8 (compiler)
-                    5622 LOAD_FAST                9 (compiler_version)
-                    5624 LOAD_FAST               10 (archs)
-                    5626 LOAD_FAST                1 (args)
-                    5628 LOAD_ATTR               60 (debug)
-                    5638 LOAD_FAST                1 (args)
-                    5640 LOAD_ATTR               61 (settings)
-                    5650 PRECALL                  7
-                    5654 CALL                     7
-                    5664 POP_TOP
-         
-         300     >> 5666 LOAD_FAST                1 (args)
-                    5668 LOAD_ATTR               66 (upload)
-                    5678 POP_JUMP_FORWARD_IF_FALSE    32 (to 5744)
-         
-         301        5680 LOAD_GLOBAL             15 (NULL + os)
-                    5692 LOAD_ATTR               48 (system)
-                    5702 LOAD_CONST             116 ('conan upload ')
-                    5704 LOAD_FAST               12 (target)
-                    5706 FORMAT_VALUE             0
-                    5708 LOAD_CONST             117 ('/')
-                    5710 LOAD_FAST                5 (version)
-                    5712 FORMAT_VALUE             0
-                    5714 LOAD_CONST             118 ('@1602/')
-                    5716 LOAD_FAST                7 (chn)
-                    5718 FORMAT_VALUE             0
-                    5720 LOAD_CONST             119 (' --all --force')
-                    5722 BUILD_STRING             7
-                    5724 PRECALL                  1
-                    5728 CALL                     1
-                    5738 POP_TOP
-                    5740 LOAD_CONST               0 (None)
-                    5742 RETURN_VALUE
-         
-         300     >> 5744 LOAD_CONST               0 (None)
-                    5746 RETURN_VALUE
+         307     >> 5976 LOAD_CONST               0 (None)
+                    5978 RETURN_VALUE
          consts
             None
+            '~'
+            '/.cpptools/conan_targets'
+            '/targets'
             'Generate project files of MaxME based platform etc.'
             ('description',)
             'target'
             "the target project name.special an predefined project name or an 'conanfile.py.in'"
             ('help',)
             '-t'
             '--tag'
@@ -2568,16 +2630,20 @@
             "the git branch of target, if specified, use 'branch' as conan channel"
             '-r'
             '--ref'
             "the git ref identify of target, if specified, use 'dev' as conan chanel and use 'ref' as version"
             '-v'
             '--version'
             'the conan package version, if specified will override default.'
-            '--without_native'
+            '-d'
+            '--default'
+            'force use default rule to build package. if not set this option, we first use "${user_dir}/.cpptools/conan_targets" as conanbuild configurations.'
             'store_true'
+            ('help', 'action')
+            '--without_native'
             'not build native package'
             ('action', 'help')
             '--android'
             'build android package.'
             'Macos'
             '--ios'
             'build ios package.'
@@ -2619,25 +2685,24 @@
             '-e'
             '--env'
             'specify addtional envrioment variables.'
             '--build_version'
             'append building number to version, avalible with CI system.'
             'list'
             'inside pacakges:\n'
-            '/targets'
             '.py.in'
             0
             'dev'
             '/conanfile.py'
-            '/targets/repos.yaml'
+            '/repos.yaml'
             'r'
             'utf-8'
             ('encoding',)
             ('Loader',)
-            '/targets/'
+            '/'
             'Error: Invalid target.'
             -1
             'Windows'
             'Visual Studio'
             '15'
             '10'
             'gcc -dumpversion'
@@ -2667,41 +2732,41 @@
             '='
             2
             '@checkout@'
             '@git_ref@'
             '-b '
             '@version@'
             'conan upload '
-            '/'
             '@1602/'
             ' --all --force'
-         names      ('argparse', 'ArgumentParser', 'add_argument', 'get_os_name', 'parse_args', 'target', 'print', 'os', 'listdir', 'path', 'dirname', '__file__', 'endswith', 'removesuffix', 'exit', 'compiler', 'compiler_version', 'exists', 'isdir', 'shutil', 'rmtree', 'remove', 'Path', 'open', 'yaml', 'load', 'Loader', 'is_file', 'find_target', 'read_target_name', 'read_target_version', 'len', 'popen', 'read', 'strip', 'count', 'rfind', 'arch', 'append', 'android_arch', 'android_compiler', 'android_compiler_version', 'android_api_level', 'tag', 'ref', 'branch', 'version', 'Warning', 'system', 'chdir', 'replace', 'chn', 'build_version', 'env', 'split', 'putenv', 'copyfile', 'replace_in_file', 'without_native', 'build_native', 'debug', 'settings', 'android', 'build_android', 'ios', 'build_ios', 'upload')
-         varnames   ('parser', 'args', 'refs', 'ref', 'git_ref', 'version', 'git_checkout', 'chn', 'compiler', 'compiler_version', 'archs', 'android_archs', 'target', 'conan_file', 'reposes_config', 'reposes', 'tmpl_file', 'osName', 'ver', 'android_compiler', 'android_compiler_version', 'android_api_level', 'repos', 'envs', 'env', 'kv')
+         names      ('os', 'path', 'exists', 'expanduser', 'shutil', 'copytree', 'dirname', '__file__', 'argparse', 'ArgumentParser', 'add_argument', 'get_os_name', 'parse_args', 'default', 'target', 'print', 'listdir', 'endswith', 'removesuffix', 'exit', 'compiler', 'compiler_version', 'isdir', 'rmtree', 'remove', 'Path', 'open', 'yaml', 'load', 'Loader', 'is_file', 'find_target', 'read_target_name', 'read_target_version', 'len', 'popen', 'read', 'strip', 'count', 'rfind', 'arch', 'append', 'android_arch', 'android_compiler', 'android_compiler_version', 'android_api_level', 'tag', 'ref', 'branch', 'version', 'Warning', 'system', 'chdir', 'replace', 'chn', 'build_version', 'env', 'split', 'putenv', 'copyfile', 'replace_in_file', 'without_native', 'build_native', 'debug', 'settings', 'android', 'build_android', 'ios', 'build_ios', 'upload')
+         varnames   ('parser', 'args', 'targets_dir', 'refs', 'ref', 'git_ref', 'version', 'git_checkout', 'chn', 'compiler', 'compiler_version', 'archs', 'android_archs', 'target', 'conan_file', 'reposes_config', 'reposes', 'tmpl_file', 'osName', 'ver', 'android_compiler', 'android_compiler_version', 'android_api_level', 'repos', 'envs', 'env', 'kv')
          freevars   ()
          cellvars   ()
          filename   '\\Program Files\\WindowsApps\\PythonSoftwareFoundation.Python.3.11_3.11.1008.0_x64__qbz5n2kfra8p0\\Lib\\site-packages\\conanbuild\\builder.py'
          name       'run'
          firstlineno 107
          lnotab
-            0x0201160102ff12032e0130013001300130013001300124013001360136
-            013001340134012e012e012e0132013001320130012e02280216011e0172
-            0108012a0146011e0204010401040104010e010e01040104010e024e013e
-            013e012a0242026e0140020e024201700156021e0120021e011e021c012a
-            010c0106010c01060204012a010c0106010c0106010c0128014c0132013a
-            0216010c012a012c022a012a012a012c0116010c012a012c022c02340316
-            012a012a012a012c0116012a012c0234020e010e010e012a0104022a010c
-            01060204022a0104020e013201320106010e01320132013c010e01320132
-            020e010e0226011a0104012002400128014c012c01280128020e010e010e
-            011a020e01340108012a01260144022a012201260124022801260122020e
-            013e010e01280128012802400124010e013e020e0140ff
+            0x02017e01b402160102ff12032e01300130013001300132013001300124
+            013001360136013001340134012e012e012e0132013001320130012e0228
+            0144010e014e0216011e01280108012a0146011e0204010401040104010e
+            010e01040104010e024e013e013e012a0242022a0140020e024201260112
+            021e0120021e011e021c012a010c0106010c01060204012a010c0106010c
+            0106010c0128014c0132013a0216010c012a012c022a012a012a012c0116
+            010c012a012c022c02340316012a012a012a012c0116012a012c0234020e
+            010e010e012a0104022a010c01060204022a0104020e013201320106010e
+            01320132013c010e01320132020e010e0226011a0104012002400128014c
+            012c01280128020e010e010e011a020e01340108012a01260144022a0122
+            01260124022801260122020e013e010e01280128012802400124010e013e
+            020e0140ff
       '__main__'
       ('',)
    names      ('argparse', 'sys', 'os', 'shutil', 'pathlib', 'Path', 'fileinput', 'yaml', 'platform', 'stat', 'get_os_name', 'str', 'replace_in_file', 'replace_in_dir', 'bool', 'find_target', 'list', 'build_native', 'build_android', 'build_ios', 'rm_error_handler', 'read_target_name', 'read_target_version', 'run', '__name__', 'exit')
    varnames   ()
    freevars   ()
    cellvars   ()
    filename   '\\Program Files\\WindowsApps\\PythonSoftwareFoundation.Python.3.11_3.11.1008.0_x64__qbz5n2kfra8p0\\Lib\\site-packages\\conanbuild\\builder.py'
    name       '<module>'
    firstlineno 1
    lnotab
       0x00ff020108020801080108010c01080108010801080206071406140914
-      0826152a0a260a0604100a100a067f00450c0134ff
+      0826152a0a260a0604100a100a067f004c0c0134ff
```

## Program Files/WindowsApps/PythonSoftwareFoundation.Python.3.11_3.11.1008.0_x64__qbz5n2kfra8p0/Lib/site-packages/conanbuild/__pycache__/conanfile.cpython-311.pyc

### Python bytecode

```diff
@@ -1,9 +1,9 @@
 magic:    0xa70d0d0a
-moddate:  0xfe214b64 (Fri Apr 28 01:31:42 2023 UTC)
+moddate:  0x02667864 (Thu Jun  1 09:33:54 2023 UTC)
 files sz: 13292
 code
    argcount  : 0
    nlocals   : 0
    stacksize : 5
    flags     : 0
    code
```

## Program Files/WindowsApps/PythonSoftwareFoundation.Python.3.11_3.11.1008.0_x64__qbz5n2kfra8p0/Lib/site-packages/oasc/__pycache__/CppGenerator.cpython-311.pyc

### Python bytecode

```diff
@@ -1,9 +1,9 @@
 magic:    0xa70d0d0a
-moddate:  0x3c2e4b64 (Fri Apr 28 02:23:56 2023 UTC)
+moddate:  0xf55c7864 (Thu Jun  1 08:55:17 2023 UTC)
 files sz: 47070
 code
    argcount  : 0
    nlocals   : 0
    stacksize : 4
    flags     : 0
    code
```

## Program Files/WindowsApps/PythonSoftwareFoundation.Python.3.11_3.11.1008.0_x64__qbz5n2kfra8p0/Lib/site-packages/oasc/__pycache__/OpenAPIXG.cpython-311.pyc

### Python bytecode

```diff
@@ -1,9 +1,9 @@
 magic:    0xa70d0d0a
-moddate:  0x92644b64 (Fri Apr 28 06:15:46 2023 UTC)
+moddate:  0xf55c7864 (Thu Jun  1 08:55:17 2023 UTC)
 files sz: 4258
 code
    argcount  : 0
    nlocals   : 0
    stacksize : 10
    flags     : 0
    code
```

## Program Files/WindowsApps/PythonSoftwareFoundation.Python.3.11_3.11.1008.0_x64__qbz5n2kfra8p0/Lib/site-packages/startcpp/__pycache__/entry.cpython-311.pyc

### Python bytecode

```diff
@@ -1,9 +1,9 @@
 magic:    0xa70d0d0a
-moddate:  0x4afd2464 (Thu Mar 30 03:08:58 2023 UTC)
+moddate:  0xf55c7864 (Thu Jun  1 08:55:17 2023 UTC)
 files sz: 4364
 code
    argcount  : 0
    nlocals   : 0
    stacksize : 6
    flags     : 0
    code
```

## Program Files/WindowsApps/PythonSoftwareFoundation.Python.3.11_3.11.1008.0_x64__qbz5n2kfra8p0/Scripts/conanbuild-script.py

```diff
@@ -1,14 +1,14 @@
 #!C:\Users\tiger\AppData\Local\Microsoft\WindowsApps\PythonSoftwareFoundation.Python.3.11_qbz5n2kfra8p0\python.exe
-# EASY-INSTALL-ENTRY-SCRIPT: 'cpptools==1.0.0','console_scripts','conanbuild'
+# EASY-INSTALL-ENTRY-SCRIPT: 'cpptools==1.0.1','console_scripts','conanbuild'
 import re
 import sys
 
 # for compatibility with easy_install; see #2198
-__requires__ = 'cpptools==1.0.0'
+__requires__ = 'cpptools==1.0.1'
 
 try:
     from importlib.metadata import distribution
 except ImportError:
     try:
         from importlib_metadata import distribution
     except ImportError:
@@ -26,8 +26,8 @@
 
 
 globals().setdefault('load_entry_point', importlib_load_entry_point)
 
 
 if __name__ == '__main__':
     sys.argv[0] = re.sub(r'(-script\.pyw?|\.exe)?$', '', sys.argv[0])
-    sys.exit(load_entry_point('cpptools==1.0.0', 'console_scripts', 'conanbuild')())
+    sys.exit(load_entry_point('cpptools==1.0.1', 'console_scripts', 'conanbuild')())
```

## Program Files/WindowsApps/PythonSoftwareFoundation.Python.3.11_3.11.1008.0_x64__qbz5n2kfra8p0/Scripts/oasc-script.py

```diff
@@ -1,14 +1,14 @@
 #!C:\Users\tiger\AppData\Local\Microsoft\WindowsApps\PythonSoftwareFoundation.Python.3.11_qbz5n2kfra8p0\python.exe
-# EASY-INSTALL-ENTRY-SCRIPT: 'cpptools==1.0.0','console_scripts','oasc'
+# EASY-INSTALL-ENTRY-SCRIPT: 'cpptools==1.0.1','console_scripts','oasc'
 import re
 import sys
 
 # for compatibility with easy_install; see #2198
-__requires__ = 'cpptools==1.0.0'
+__requires__ = 'cpptools==1.0.1'
 
 try:
     from importlib.metadata import distribution
 except ImportError:
     try:
         from importlib_metadata import distribution
     except ImportError:
@@ -26,8 +26,8 @@
 
 
 globals().setdefault('load_entry_point', importlib_load_entry_point)
 
 
 if __name__ == '__main__':
     sys.argv[0] = re.sub(r'(-script\.pyw?|\.exe)?$', '', sys.argv[0])
-    sys.exit(load_entry_point('cpptools==1.0.0', 'console_scripts', 'oasc')())
+    sys.exit(load_entry_point('cpptools==1.0.1', 'console_scripts', 'oasc')())
```

## Program Files/WindowsApps/PythonSoftwareFoundation.Python.3.11_3.11.1008.0_x64__qbz5n2kfra8p0/Scripts/startcpp-script.py

```diff
@@ -1,14 +1,14 @@
 #!C:\Users\tiger\AppData\Local\Microsoft\WindowsApps\PythonSoftwareFoundation.Python.3.11_qbz5n2kfra8p0\python.exe
-# EASY-INSTALL-ENTRY-SCRIPT: 'cpptools==1.0.0','console_scripts','startcpp'
+# EASY-INSTALL-ENTRY-SCRIPT: 'cpptools==1.0.1','console_scripts','startcpp'
 import re
 import sys
 
 # for compatibility with easy_install; see #2198
-__requires__ = 'cpptools==1.0.0'
+__requires__ = 'cpptools==1.0.1'
 
 try:
     from importlib.metadata import distribution
 except ImportError:
     try:
         from importlib_metadata import distribution
     except ImportError:
@@ -26,8 +26,8 @@
 
 
 globals().setdefault('load_entry_point', importlib_load_entry_point)
 
 
 if __name__ == '__main__':
     sys.argv[0] = re.sub(r'(-script\.pyw?|\.exe)?$', '', sys.argv[0])
-    sys.exit(load_entry_point('cpptools==1.0.0', 'console_scripts', 'startcpp')())
+    sys.exit(load_entry_point('cpptools==1.0.1', 'console_scripts', 'startcpp')())
```

## Comparing `Program Files/WindowsApps/PythonSoftwareFoundation.Python.3.11_3.11.1008.0_x64__qbz5n2kfra8p0/Lib/site-packages/cpptools-1.0.0-py3.11.egg-info/PKG-INFO` & `Program Files/WindowsApps/PythonSoftwareFoundation.Python.3.11_3.11.1008.0_x64__qbz5n2kfra8p0/Lib/site-packages/cpptools-1.0.1-py3.11.egg-info/PKG-INFO`

 * *Files 0% similar despite different names*

```diff
@@ -1,10 +1,10 @@
 Metadata-Version: 2.1
 Name: cpptools
-Version: 1.0.0
+Version: 1.0.1
 Summary: The toolset for c/c++ project & package.
 Home-page: https://gitlab.gz.cvte.cn/1602/cpptools
 Author: TigerLau
 Author-email: tigerliu1985@hotmail.com
 Classifier: Programming Language :: Python :: 3
 Classifier: License :: OSI Approved :: MIT License
 Classifier: Operating System :: OS Independent
```

## Comparing `Program Files/WindowsApps/PythonSoftwareFoundation.Python.3.11_3.11.1008.0_x64__qbz5n2kfra8p0/Lib/site-packages/cpptools-1.0.0-py3.11.egg-info/SOURCES.txt` & `Program Files/WindowsApps/PythonSoftwareFoundation.Python.3.11_3.11.1008.0_x64__qbz5n2kfra8p0/Lib/site-packages/cpptools-1.0.1-py3.11.egg-info/SOURCES.txt`

 * *Files identical despite different names*

